{"sysstat": {
	"hosts": [
		{
			"nodename": "star-dtn2.testbed100.es.net",
			"sysname": "Linux",
			"release": "5.15.0-117-generic",
			"machine": "x86_64",
			"number-of-cpus": 32,
			"date": "08/05/2024",
			"statistics": [
				{
					"timestamp": "02:59:30 PM",
					"cpu-load": [
						{"cpu": "0", "usr": 0.00, "nice": 0.00, "sys": 0.00, "iowait": 0.00, "irq": 0.00, "soft": 0.00, "steal": 0.00, "guest": 0.00, "gnice": 0.00, "idle": 100.00},
						{"cpu": "1", "usr": 0.00, "nice": 0.00, "sys": 0.00, "iowait": 0.00, "irq": 0.00, "soft": 0.00, "steal": 0.00, "guest": 0.00, "gnice": 0.00, "idle": 100.00},
						{"cpu": "2", "usr": 0.00, "nice": 0.00, "sys": 0.00, "iowait": 0.00, "irq": 0.00, "soft": 0.00, "steal": 0.00, "guest": 0.00, "gnice": 0.00, "idle": 100.00},
						{"cpu": "3", "usr": 0.00, "nice": 0.00, "sys": 0.00, "iowait": 0.00, "irq": 0.00, "soft": 0.00, "steal": 0.00, "guest": 0.00, "gnice": 0.00, "idle": 100.00},
						{"cpu": "4", "usr": 0.00, "nice": 0.00, "sys": 0.00, "iowait": 0.00, "irq": 0.00, "soft": 0.00, "steal": 0.00, "guest": 0.00, "gnice": 0.00, "idle": 100.00},
						{"cpu": "5", "usr": 0.00, "nice": 0.00, "sys": 0.00, "iowait": 0.00, "irq": 0.00, "soft": 0.00, "steal": 0.00, "guest": 0.00, "gnice": 0.00, "idle": 100.00},
						{"cpu": "6", "usr": 0.00, "nice": 0.00, "sys": 0.00, "iowait": 0.00, "irq": 0.00, "soft": 0.00, "steal": 0.00, "guest": 0.00, "gnice": 0.00, "idle": 100.00},
						{"cpu": "7", "usr": 0.00, "nice": 0.00, "sys": 0.00, "iowait": 0.00, "irq": 0.00, "soft": 0.00, "steal": 0.00, "guest": 0.00, "gnice": 0.00, "idle": 100.00},
						{"cpu": "8", "usr": 0.00, "nice": 0.00, "sys": 0.00, "iowait": 0.00, "irq": 0.00, "soft": 0.00, "steal": 0.00, "guest": 0.00, "gnice": 0.00, "idle": 100.00},
						{"cpu": "9", "usr": 0.00, "nice": 0.00, "sys": 0.00, "iowait": 0.00, "irq": 0.00, "soft": 0.00, "steal": 0.00, "guest": 0.00, "gnice": 0.00, "idle": 100.00},
						{"cpu": "10", "usr": 0.00, "nice": 0.00, "sys": 0.00, "iowait": 0.00, "irq": 0.00, "soft": 0.00, "steal": 0.00, "guest": 0.00, "gnice": 0.00, "idle": 100.00},
						{"cpu": "11", "usr": 0.00, "nice": 0.00, "sys": 0.00, "iowait": 0.00, "irq": 0.00, "soft": 0.00, "steal": 0.00, "guest": 0.00, "gnice": 0.00, "idle": 100.00},
						{"cpu": "12", "usr": 0.00, "nice": 0.00, "sys": 0.50, "iowait": 0.00, "irq": 0.00, "soft": 0.00, "steal": 0.00, "guest": 0.00, "gnice": 0.00, "idle": 99.50},
						{"cpu": "13", "usr": 0.00, "nice": 0.00, "sys": 0.00, "iowait": 0.00, "irq": 0.00, "soft": 0.00, "steal": 0.00, "guest": 0.00, "gnice": 0.00, "idle": 100.00},
						{"cpu": "14", "usr": 0.00, "nice": 0.00, "sys": 0.00, "iowait": 0.00, "irq": 0.00, "soft": 0.00, "steal": 0.00, "guest": 0.00, "gnice": 0.00, "idle": 100.00},
						{"cpu": "15", "usr": 0.00, "nice": 0.00, "sys": 0.00, "iowait": 0.00, "irq": 0.00, "soft": 0.00, "steal": 0.00, "guest": 0.00, "gnice": 0.00, "idle": 100.00}
					]
				},
				{
					"timestamp": "02:59:32 PM",
					"cpu-load": [
						{"cpu": "0", "usr": 0.00, "nice": 0.00, "sys": 0.00, "iowait": 0.00, "irq": 0.00, "soft": 0.00, "steal": 0.00, "guest": 0.00, "gnice": 0.00, "idle": 100.00},
						{"cpu": "1", "usr": 0.00, "nice": 0.00, "sys": 0.00, "iowait": 0.00, "irq": 0.00, "soft": 0.00, "steal": 0.00, "guest": 0.00, "gnice": 0.00, "idle": 100.00},
						{"cpu": "2", "usr": 0.00, "nice": 0.00, "sys": 0.00, "iowait": 0.00, "irq": 0.00, "soft": 0.00, "steal": 0.00, "guest": 0.00, "gnice": 0.00, "idle": 100.00},
						{"cpu": "3", "usr": 0.00, "nice": 0.00, "sys": 0.50, "iowait": 0.00, "irq": 0.00, "soft": 0.00, "steal": 0.00, "guest": 0.00, "gnice": 0.00, "idle": 99.50},
						{"cpu": "4", "usr": 0.00, "nice": 0.00, "sys": 0.00, "iowait": 0.00, "irq": 0.00, "soft": 0.00, "steal": 0.00, "guest": 0.00, "gnice": 0.00, "idle": 100.00},
						{"cpu": "5", "usr": 0.00, "nice": 0.00, "sys": 0.00, "iowait": 0.00, "irq": 0.00, "soft": 0.00, "steal": 0.00, "guest": 0.00, "gnice": 0.00, "idle": 100.00},
						{"cpu": "6", "usr": 0.00, "nice": 0.00, "sys": 0.00, "iowait": 0.00, "irq": 0.00, "soft": 0.00, "steal": 0.00, "guest": 0.00, "gnice": 0.00, "idle": 100.00},
						{"cpu": "7", "usr": 0.00, "nice": 0.00, "sys": 0.00, "iowait": 0.00, "irq": 0.00, "soft": 0.00, "steal": 0.00, "guest": 0.00, "gnice": 0.00, "idle": 100.00},
						{"cpu": "8", "usr": 0.00, "nice": 0.00, "sys": 0.00, "iowait": 0.00, "irq": 0.00, "soft": 0.00, "steal": 0.00, "guest": 0.00, "gnice": 0.00, "idle": 100.00},
						{"cpu": "9", "usr": 0.00, "nice": 0.00, "sys": 0.00, "iowait": 0.00, "irq": 0.00, "soft": 0.00, "steal": 0.00, "guest": 0.00, "gnice": 0.00, "idle": 100.00},
						{"cpu": "10", "usr": 0.00, "nice": 0.00, "sys": 0.00, "iowait": 0.00, "irq": 0.00, "soft": 0.00, "steal": 0.00, "guest": 0.00, "gnice": 0.00, "idle": 100.00},
						{"cpu": "11", "usr": 0.00, "nice": 0.00, "sys": 0.00, "iowait": 0.00, "irq": 0.00, "soft": 0.00, "steal": 0.00, "guest": 0.00, "gnice": 0.00, "idle": 100.00},
						{"cpu": "12", "usr": 1.00, "nice": 0.00, "sys": 0.00, "iowait": 0.00, "irq": 0.00, "soft": 0.00, "steal": 0.00, "guest": 0.00, "gnice": 0.00, "idle": 99.00},
						{"cpu": "13", "usr": 0.00, "nice": 0.00, "sys": 0.00, "iowait": 0.00, "irq": 0.00, "soft": 0.00, "steal": 0.00, "guest": 0.00, "gnice": 0.00, "idle": 100.00},
						{"cpu": "14", "usr": 0.00, "nice": 0.00, "sys": 0.00, "iowait": 0.00, "irq": 0.00, "soft": 0.00, "steal": 0.00, "guest": 0.00, "gnice": 0.00, "idle": 100.00},
						{"cpu": "15", "usr": 0.00, "nice": 0.00, "sys": 0.00, "iowait": 0.00, "irq": 0.00, "soft": 0.00, "steal": 0.00, "guest": 0.00, "gnice": 0.00, "idle": 100.00}
					]
				},
				{
					"timestamp": "02:59:34 PM",
					"cpu-load": [
						{"cpu": "0", "usr": 0.00, "nice": 0.00, "sys": 0.00, "iowait": 0.00, "irq": 0.00, "soft": 0.00, "steal": 0.00, "guest": 0.00, "gnice": 0.00, "idle": 100.00},
						{"cpu": "1", "usr": 0.00, "nice": 0.00, "sys": 0.00, "iowait": 0.00, "irq": 0.00, "soft": 0.00, "steal": 0.00, "guest": 0.00, "gnice": 0.00, "idle": 100.00},
						{"cpu": "2", "usr": 0.00, "nice": 0.00, "sys": 0.00, "iowait": 0.00, "irq": 0.00, "soft": 0.00, "steal": 0.00, "guest": 0.00, "gnice": 0.00, "idle": 100.00},
						{"cpu": "3", "usr": 0.00, "nice": 0.00, "sys": 0.00, "iowait": 0.00, "irq": 0.00, "soft": 18.12, "steal": 0.00, "guest": 0.00, "gnice": 0.00, "idle": 81.88},
						{"cpu": "4", "usr": 0.00, "nice": 0.00, "sys": 0.00, "iowait": 0.00, "irq": 0.00, "soft": 0.00, "steal": 0.00, "guest": 0.00, "gnice": 0.00, "idle": 100.00},
						{"cpu": "5", "usr": 0.00, "nice": 0.00, "sys": 0.00, "iowait": 0.00, "irq": 0.00, "soft": 0.00, "steal": 0.00, "guest": 0.00, "gnice": 0.00, "idle": 100.00},
						{"cpu": "6", "usr": 0.00, "nice": 0.00, "sys": 0.00, "iowait": 0.00, "irq": 0.00, "soft": 0.00, "steal": 0.00, "guest": 0.00, "gnice": 0.00, "idle": 100.00},
						{"cpu": "7", "usr": 0.00, "nice": 0.00, "sys": 0.00, "iowait": 0.00, "irq": 0.00, "soft": 0.00, "steal": 0.00, "guest": 0.00, "gnice": 0.00, "idle": 100.00},
						{"cpu": "8", "usr": 0.00, "nice": 0.00, "sys": 0.00, "iowait": 0.00, "irq": 0.00, "soft": 0.00, "steal": 0.00, "guest": 0.00, "gnice": 0.00, "idle": 100.00},
						{"cpu": "9", "usr": 0.00, "nice": 0.00, "sys": 0.00, "iowait": 0.00, "irq": 0.00, "soft": 0.00, "steal": 0.00, "guest": 0.00, "gnice": 0.00, "idle": 100.00},
						{"cpu": "10", "usr": 1.00, "nice": 0.00, "sys": 77.11, "iowait": 0.00, "irq": 0.00, "soft": 0.00, "steal": 0.00, "guest": 0.00, "gnice": 0.00, "idle": 21.89},
						{"cpu": "11", "usr": 0.00, "nice": 0.00, "sys": 0.00, "iowait": 0.00, "irq": 0.00, "soft": 0.00, "steal": 0.00, "guest": 0.00, "gnice": 0.00, "idle": 100.00},
						{"cpu": "12", "usr": 0.00, "nice": 0.00, "sys": 0.50, "iowait": 0.00, "irq": 0.00, "soft": 0.00, "steal": 0.00, "guest": 0.00, "gnice": 0.00, "idle": 99.50},
						{"cpu": "13", "usr": 0.00, "nice": 0.00, "sys": 0.00, "iowait": 0.00, "irq": 0.00, "soft": 0.00, "steal": 0.00, "guest": 0.00, "gnice": 0.00, "idle": 100.00},
						{"cpu": "14", "usr": 0.00, "nice": 0.00, "sys": 0.00, "iowait": 0.00, "irq": 0.00, "soft": 0.00, "steal": 0.00, "guest": 0.00, "gnice": 0.00, "idle": 100.00},
						{"cpu": "15", "usr": 0.00, "nice": 0.00, "sys": 0.00, "iowait": 0.00, "irq": 0.00, "soft": 0.00, "steal": 0.00, "guest": 0.00, "gnice": 0.00, "idle": 100.00}
					]
				},
				{
					"timestamp": "02:59:36 PM",
					"cpu-load": [
						{"cpu": "0", "usr": 0.00, "nice": 0.00, "sys": 0.00, "iowait": 0.00, "irq": 0.00, "soft": 0.00, "steal": 0.00, "guest": 0.00, "gnice": 0.00, "idle": 100.00},
						{"cpu": "1", "usr": 0.00, "nice": 0.00, "sys": 0.00, "iowait": 0.00, "irq": 0.00, "soft": 0.00, "steal": 0.00, "guest": 0.00, "gnice": 0.00, "idle": 100.00},
						{"cpu": "2", "usr": 0.00, "nice": 0.00, "sys": 0.00, "iowait": 0.00, "irq": 0.00, "soft": 0.52, "steal": 0.00, "guest": 0.00, "gnice": 0.00, "idle": 99.48},
						{"cpu": "3", "usr": 0.00, "nice": 0.00, "sys": 0.00, "iowait": 0.00, "irq": 0.00, "soft": 26.05, "steal": 0.00, "guest": 0.00, "gnice": 0.00, "idle": 73.95},
						{"cpu": "4", "usr": 0.00, "nice": 0.00, "sys": 0.00, "iowait": 0.00, "irq": 0.00, "soft": 0.00, "steal": 0.00, "guest": 0.00, "gnice": 0.00, "idle": 100.00},
						{"cpu": "5", "usr": 0.00, "nice": 0.00, "sys": 0.00, "iowait": 0.00, "irq": 0.00, "soft": 0.00, "steal": 0.00, "guest": 0.00, "gnice": 0.00, "idle": 100.00},
						{"cpu": "6", "usr": 0.00, "nice": 0.00, "sys": 0.00, "iowait": 0.00, "irq": 0.00, "soft": 0.00, "steal": 0.00, "guest": 0.00, "gnice": 0.00, "idle": 100.00},
						{"cpu": "7", "usr": 0.00, "nice": 0.00, "sys": 0.00, "iowait": 0.00, "irq": 0.00, "soft": 0.00, "steal": 0.00, "guest": 0.00, "gnice": 0.00, "idle": 100.00},
						{"cpu": "8", "usr": 0.00, "nice": 0.00, "sys": 0.00, "iowait": 0.00, "irq": 0.00, "soft": 0.00, "steal": 0.00, "guest": 0.00, "gnice": 0.00, "idle": 100.00},
						{"cpu": "9", "usr": 0.00, "nice": 0.00, "sys": 0.00, "iowait": 0.00, "irq": 0.00, "soft": 0.00, "steal": 0.00, "guest": 0.00, "gnice": 0.00, "idle": 100.00},
						{"cpu": "10", "usr": 0.00, "nice": 0.00, "sys": 100.00, "iowait": 0.00, "irq": 0.00, "soft": 0.00, "steal": 0.00, "guest": 0.00, "gnice": 0.00, "idle": 0.00},
						{"cpu": "11", "usr": 0.00, "nice": 0.00, "sys": 0.00, "iowait": 0.00, "irq": 0.00, "soft": 0.00, "steal": 0.00, "guest": 0.00, "gnice": 0.00, "idle": 100.00},
						{"cpu": "12", "usr": 0.00, "nice": 0.00, "sys": 0.50, "iowait": 0.00, "irq": 0.00, "soft": 0.00, "steal": 0.00, "guest": 0.00, "gnice": 0.00, "idle": 99.50},
						{"cpu": "13", "usr": 0.00, "nice": 0.00, "sys": 0.00, "iowait": 0.00, "irq": 0.00, "soft": 0.00, "steal": 0.00, "guest": 0.00, "gnice": 0.00, "idle": 100.00},
						{"cpu": "14", "usr": 0.00, "nice": 0.00, "sys": 0.00, "iowait": 0.00, "irq": 0.00, "soft": 0.00, "steal": 0.00, "guest": 0.00, "gnice": 0.00, "idle": 100.00},
						{"cpu": "15", "usr": 0.00, "nice": 0.00, "sys": 0.00, "iowait": 0.00, "irq": 0.00, "soft": 0.00, "steal": 0.00, "guest": 0.00, "gnice": 0.00, "idle": 100.00}
					]
				},
				{
					"timestamp": "02:59:38 PM",
					"cpu-load": [
						{"cpu": "0", "usr": 0.00, "nice": 0.00, "sys": 0.00, "iowait": 0.00, "irq": 0.00, "soft": 0.00, "steal": 0.00, "guest": 0.00, "gnice": 0.00, "idle": 100.00},
						{"cpu": "1", "usr": 0.00, "nice": 0.00, "sys": 0.00, "iowait": 0.00, "irq": 0.00, "soft": 0.00, "steal": 0.00, "guest": 0.00, "gnice": 0.00, "idle": 100.00},
						{"cpu": "2", "usr": 0.52, "nice": 0.00, "sys": 0.00, "iowait": 0.00, "irq": 0.00, "soft": 2.58, "steal": 0.00, "guest": 0.00, "gnice": 0.00, "idle": 96.91},
						{"cpu": "3", "usr": 0.00, "nice": 0.00, "sys": 0.00, "iowait": 0.00, "irq": 0.00, "soft": 27.35, "steal": 0.00, "guest": 0.00, "gnice": 0.00, "idle": 72.65},
						{"cpu": "4", "usr": 0.00, "nice": 0.00, "sys": 0.00, "iowait": 0.00, "irq": 0.00, "soft": 0.00, "steal": 0.00, "guest": 0.00, "gnice": 0.00, "idle": 100.00},
						{"cpu": "5", "usr": 0.00, "nice": 0.00, "sys": 0.00, "iowait": 0.00, "irq": 0.00, "soft": 0.00, "steal": 0.00, "guest": 0.00, "gnice": 0.00, "idle": 100.00},
						{"cpu": "6", "usr": 0.00, "nice": 0.00, "sys": 0.00, "iowait": 0.00, "irq": 0.00, "soft": 0.00, "steal": 0.00, "guest": 0.00, "gnice": 0.00, "idle": 100.00},
						{"cpu": "7", "usr": 0.00, "nice": 0.00, "sys": 0.00, "iowait": 0.00, "irq": 0.00, "soft": 0.00, "steal": 0.00, "guest": 0.00, "gnice": 0.00, "idle": 100.00},
						{"cpu": "8", "usr": 0.00, "nice": 0.00, "sys": 0.00, "iowait": 0.00, "irq": 0.00, "soft": 0.00, "steal": 0.00, "guest": 0.00, "gnice": 0.00, "idle": 100.00},
						{"cpu": "9", "usr": 0.00, "nice": 0.00, "sys": 0.00, "iowait": 0.00, "irq": 0.00, "soft": 0.00, "steal": 0.00, "guest": 0.00, "gnice": 0.00, "idle": 100.00},
						{"cpu": "10", "usr": 1.00, "nice": 0.00, "sys": 99.00, "iowait": 0.00, "irq": 0.00, "soft": 0.00, "steal": 0.00, "guest": 0.00, "gnice": 0.00, "idle": 0.00},
						{"cpu": "11", "usr": 0.00, "nice": 0.00, "sys": 0.00, "iowait": 0.00, "irq": 0.00, "soft": 0.00, "steal": 0.00, "guest": 0.00, "gnice": 0.00, "idle": 100.00},
						{"cpu": "12", "usr": 0.00, "nice": 0.00, "sys": 0.50, "iowait": 0.00, "irq": 0.00, "soft": 0.00, "steal": 0.00, "guest": 0.00, "gnice": 0.00, "idle": 99.50},
						{"cpu": "13", "usr": 0.00, "nice": 0.00, "sys": 0.00, "iowait": 0.00, "irq": 0.00, "soft": 0.00, "steal": 0.00, "guest": 0.00, "gnice": 0.00, "idle": 100.00},
						{"cpu": "14", "usr": 0.50, "nice": 0.00, "sys": 0.00, "iowait": 0.00, "irq": 0.00, "soft": 0.00, "steal": 0.00, "guest": 0.00, "gnice": 0.00, "idle": 99.50},
						{"cpu": "15", "usr": 0.00, "nice": 0.00, "sys": 0.00, "iowait": 0.00, "irq": 0.00, "soft": 0.00, "steal": 0.00, "guest": 0.00, "gnice": 0.00, "idle": 100.00}
					]
				},
				{
					"timestamp": "02:59:40 PM",
					"cpu-load": [
						{"cpu": "0", "usr": 0.00, "nice": 0.00, "sys": 0.00, "iowait": 0.00, "irq": 0.00, "soft": 0.00, "steal": 0.00, "guest": 0.00, "gnice": 0.00, "idle": 100.00},
						{"cpu": "1", "usr": 0.00, "nice": 0.00, "sys": 0.00, "iowait": 0.00, "irq": 0.00, "soft": 0.00, "steal": 0.00, "guest": 0.00, "gnice": 0.00, "idle": 100.00},
						{"cpu": "2", "usr": 0.00, "nice": 0.00, "sys": 0.00, "iowait": 0.00, "irq": 0.00, "soft": 0.00, "steal": 0.00, "guest": 0.00, "gnice": 0.00, "idle": 100.00},
						{"cpu": "3", "usr": 0.00, "nice": 0.00, "sys": 0.00, "iowait": 0.00, "irq": 0.00, "soft": 28.33, "steal": 0.00, "guest": 0.00, "gnice": 0.00, "idle": 71.67},
						{"cpu": "4", "usr": 0.00, "nice": 0.00, "sys": 0.00, "iowait": 0.00, "irq": 0.00, "soft": 0.00, "steal": 0.00, "guest": 0.00, "gnice": 0.00, "idle": 100.00},
						{"cpu": "5", "usr": 0.00, "nice": 0.00, "sys": 0.00, "iowait": 0.00, "irq": 0.00, "soft": 0.00, "steal": 0.00, "guest": 0.00, "gnice": 0.00, "idle": 100.00},
						{"cpu": "6", "usr": 0.00, "nice": 0.00, "sys": 0.00, "iowait": 0.00, "irq": 0.00, "soft": 0.00, "steal": 0.00, "guest": 0.00, "gnice": 0.00, "idle": 100.00},
						{"cpu": "7", "usr": 0.00, "nice": 0.00, "sys": 0.00, "iowait": 0.00, "irq": 0.00, "soft": 0.00, "steal": 0.00, "guest": 0.00, "gnice": 0.00, "idle": 100.00},
						{"cpu": "8", "usr": 0.00, "nice": 0.00, "sys": 0.00, "iowait": 0.00, "irq": 0.00, "soft": 0.00, "steal": 0.00, "guest": 0.00, "gnice": 0.00, "idle": 100.00},
						{"cpu": "9", "usr": 0.00, "nice": 0.00, "sys": 0.00, "iowait": 0.00, "irq": 0.00, "soft": 0.00, "steal": 0.00, "guest": 0.00, "gnice": 0.00, "idle": 100.00},
						{"cpu": "10", "usr": 0.50, "nice": 0.00, "sys": 99.50, "iowait": 0.00, "irq": 0.00, "soft": 0.00, "steal": 0.00, "guest": 0.00, "gnice": 0.00, "idle": 0.00},
						{"cpu": "11", "usr": 0.00, "nice": 0.00, "sys": 0.00, "iowait": 0.00, "irq": 0.00, "soft": 0.00, "steal": 0.00, "guest": 0.00, "gnice": 0.00, "idle": 100.00},
						{"cpu": "12", "usr": 0.50, "nice": 0.00, "sys": 0.50, "iowait": 0.00, "irq": 0.00, "soft": 0.00, "steal": 0.00, "guest": 0.00, "gnice": 0.00, "idle": 99.00},
						{"cpu": "13", "usr": 0.00, "nice": 0.00, "sys": 0.00, "iowait": 0.00, "irq": 0.00, "soft": 0.00, "steal": 0.00, "guest": 0.00, "gnice": 0.00, "idle": 100.00},
						{"cpu": "14", "usr": 0.00, "nice": 0.00, "sys": 0.00, "iowait": 0.00, "irq": 0.00, "soft": 0.00, "steal": 0.00, "guest": 0.00, "gnice": 0.00, "idle": 100.00},
						{"cpu": "15", "usr": 0.00, "nice": 0.00, "sys": 0.00, "iowait": 0.00, "irq": 0.00, "soft": 0.00, "steal": 0.00, "guest": 0.00, "gnice": 0.00, "idle": 100.00}
					]
				},
				{
					"timestamp": "02:59:42 PM",
					"cpu-load": [
						{"cpu": "0", "usr": 0.00, "nice": 0.00, "sys": 0.00, "iowait": 0.00, "irq": 0.00, "soft": 0.00, "steal": 0.00, "guest": 0.00, "gnice": 0.00, "idle": 100.00},
						{"cpu": "1", "usr": 0.00, "nice": 0.00, "sys": 0.00, "iowait": 0.00, "irq": 0.00, "soft": 0.00, "steal": 0.00, "guest": 0.00, "gnice": 0.00, "idle": 100.00},
						{"cpu": "2", "usr": 0.00, "nice": 0.00, "sys": 0.51, "iowait": 0.00, "irq": 0.00, "soft": 1.03, "steal": 0.00, "guest": 0.00, "gnice": 0.00, "idle": 98.46},
						{"cpu": "3", "usr": 0.00, "nice": 0.00, "sys": 0.00, "iowait": 0.00, "irq": 0.00, "soft": 22.32, "steal": 0.00, "guest": 0.00, "gnice": 0.00, "idle": 77.68},
						{"cpu": "4", "usr": 0.00, "nice": 0.00, "sys": 0.00, "iowait": 0.00, "irq": 0.00, "soft": 0.00, "steal": 0.00, "guest": 0.00, "gnice": 0.00, "idle": 100.00},
						{"cpu": "5", "usr": 0.00, "nice": 0.00, "sys": 0.00, "iowait": 0.00, "irq": 0.00, "soft": 0.00, "steal": 0.00, "guest": 0.00, "gnice": 0.00, "idle": 100.00},
						{"cpu": "6", "usr": 0.00, "nice": 0.00, "sys": 0.00, "iowait": 0.00, "irq": 0.00, "soft": 0.00, "steal": 0.00, "guest": 0.00, "gnice": 0.00, "idle": 100.00},
						{"cpu": "7", "usr": 0.00, "nice": 0.00, "sys": 0.00, "iowait": 0.00, "irq": 0.00, "soft": 0.00, "steal": 0.00, "guest": 0.00, "gnice": 0.00, "idle": 100.00},
						{"cpu": "8", "usr": 0.00, "nice": 0.00, "sys": 0.00, "iowait": 0.00, "irq": 0.00, "soft": 0.00, "steal": 0.00, "guest": 0.00, "gnice": 0.00, "idle": 100.00},
						{"cpu": "9", "usr": 0.00, "nice": 0.00, "sys": 0.00, "iowait": 0.00, "irq": 0.00, "soft": 0.00, "steal": 0.00, "guest": 0.00, "gnice": 0.00, "idle": 100.00},
						{"cpu": "10", "usr": 0.50, "nice": 0.00, "sys": 99.50, "iowait": 0.00, "irq": 0.00, "soft": 0.00, "steal": 0.00, "guest": 0.00, "gnice": 0.00, "idle": 0.00},
						{"cpu": "11", "usr": 0.00, "nice": 0.00, "sys": 0.00, "iowait": 0.00, "irq": 0.00, "soft": 0.00, "steal": 0.00, "guest": 0.00, "gnice": 0.00, "idle": 100.00},
						{"cpu": "12", "usr": 0.50, "nice": 0.00, "sys": 0.50, "iowait": 0.00, "irq": 0.00, "soft": 0.00, "steal": 0.00, "guest": 0.00, "gnice": 0.00, "idle": 99.00},
						{"cpu": "13", "usr": 0.00, "nice": 0.00, "sys": 0.00, "iowait": 0.00, "irq": 0.00, "soft": 0.00, "steal": 0.00, "guest": 0.00, "gnice": 0.00, "idle": 100.00},
						{"cpu": "14", "usr": 0.00, "nice": 0.00, "sys": 0.00, "iowait": 0.00, "irq": 0.00, "soft": 0.00, "steal": 0.00, "guest": 0.00, "gnice": 0.00, "idle": 100.00},
						{"cpu": "15", "usr": 0.00, "nice": 0.00, "sys": 0.00, "iowait": 0.00, "irq": 0.00, "soft": 0.00, "steal": 0.00, "guest": 0.00, "gnice": 0.00, "idle": 100.00}
					]
				},
				{
					"timestamp": "02:59:44 PM",
					"cpu-load": [
						{"cpu": "0", "usr": 0.00, "nice": 0.00, "sys": 0.00, "iowait": 0.00, "irq": 0.00, "soft": 0.00, "steal": 0.00, "guest": 0.00, "gnice": 0.00, "idle": 100.00},
						{"cpu": "1", "usr": 0.00, "nice": 0.00, "sys": 0.00, "iowait": 0.00, "irq": 0.00, "soft": 0.00, "steal": 0.00, "guest": 0.00, "gnice": 0.00, "idle": 100.00},
						{"cpu": "2", "usr": 0.00, "nice": 0.00, "sys": 0.00, "iowait": 0.00, "irq": 0.00, "soft": 1.03, "steal": 0.00, "guest": 0.00, "gnice": 0.00, "idle": 98.97},
						{"cpu": "3", "usr": 0.00, "nice": 0.00, "sys": 0.00, "iowait": 0.00, "irq": 0.00, "soft": 26.89, "steal": 0.00, "guest": 0.00, "gnice": 0.00, "idle": 73.11},
						{"cpu": "4", "usr": 0.00, "nice": 0.00, "sys": 0.00, "iowait": 0.00, "irq": 0.00, "soft": 0.00, "steal": 0.00, "guest": 0.00, "gnice": 0.00, "idle": 100.00},
						{"cpu": "5", "usr": 0.00, "nice": 0.00, "sys": 0.00, "iowait": 0.00, "irq": 0.00, "soft": 0.00, "steal": 0.00, "guest": 0.00, "gnice": 0.00, "idle": 100.00},
						{"cpu": "6", "usr": 0.00, "nice": 0.00, "sys": 0.00, "iowait": 0.00, "irq": 0.00, "soft": 0.00, "steal": 0.00, "guest": 0.00, "gnice": 0.00, "idle": 100.00},
						{"cpu": "7", "usr": 0.00, "nice": 0.00, "sys": 0.00, "iowait": 0.00, "irq": 0.00, "soft": 0.00, "steal": 0.00, "guest": 0.00, "gnice": 0.00, "idle": 100.00},
						{"cpu": "8", "usr": 0.00, "nice": 0.00, "sys": 0.00, "iowait": 0.00, "irq": 0.00, "soft": 0.00, "steal": 0.00, "guest": 0.00, "gnice": 0.00, "idle": 100.00},
						{"cpu": "9", "usr": 0.00, "nice": 0.00, "sys": 0.00, "iowait": 0.00, "irq": 0.00, "soft": 0.00, "steal": 0.00, "guest": 0.00, "gnice": 0.00, "idle": 100.00},
						{"cpu": "10", "usr": 1.00, "nice": 0.00, "sys": 99.00, "iowait": 0.00, "irq": 0.00, "soft": 0.00, "steal": 0.00, "guest": 0.00, "gnice": 0.00, "idle": 0.00},
						{"cpu": "11", "usr": 0.00, "nice": 0.00, "sys": 0.00, "iowait": 0.00, "irq": 0.00, "soft": 0.00, "steal": 0.00, "guest": 0.00, "gnice": 0.00, "idle": 100.00},
						{"cpu": "12", "usr": 0.50, "nice": 0.00, "sys": 0.50, "iowait": 0.00, "irq": 0.00, "soft": 0.00, "steal": 0.00, "guest": 0.00, "gnice": 0.00, "idle": 99.00},
						{"cpu": "13", "usr": 0.00, "nice": 0.00, "sys": 0.00, "iowait": 0.00, "irq": 0.00, "soft": 0.00, "steal": 0.00, "guest": 0.00, "gnice": 0.00, "idle": 100.00},
						{"cpu": "14", "usr": 0.00, "nice": 0.00, "sys": 0.00, "iowait": 0.00, "irq": 0.00, "soft": 0.00, "steal": 0.00, "guest": 0.00, "gnice": 0.00, "idle": 100.00},
						{"cpu": "15", "usr": 0.00, "nice": 0.00, "sys": 0.00, "iowait": 0.00, "irq": 0.00, "soft": 0.00, "steal": 0.00, "guest": 0.00, "gnice": 0.00, "idle": 100.00}
					]
				},
				{
					"timestamp": "02:59:46 PM",
					"cpu-load": [
						{"cpu": "0", "usr": 0.00, "nice": 0.00, "sys": 0.00, "iowait": 0.00, "irq": 0.00, "soft": 0.00, "steal": 0.00, "guest": 0.00, "gnice": 0.00, "idle": 100.00},
						{"cpu": "1", "usr": 0.00, "nice": 0.00, "sys": 0.00, "iowait": 0.00, "irq": 0.00, "soft": 0.00, "steal": 0.00, "guest": 0.00, "gnice": 0.00, "idle": 100.00},
						{"cpu": "2", "usr": 0.00, "nice": 0.00, "sys": 0.00, "iowait": 0.00, "irq": 0.00, "soft": 0.00, "steal": 0.00, "guest": 0.00, "gnice": 0.00, "idle": 100.00},
						{"cpu": "3", "usr": 0.00, "nice": 0.00, "sys": 0.83, "iowait": 0.00, "irq": 0.00, "soft": 28.10, "steal": 0.00, "guest": 0.00, "gnice": 0.00, "idle": 71.07},
						{"cpu": "4", "usr": 0.00, "nice": 0.00, "sys": 0.00, "iowait": 0.00, "irq": 0.00, "soft": 0.00, "steal": 0.00, "guest": 0.00, "gnice": 0.00, "idle": 100.00},
						{"cpu": "5", "usr": 0.00, "nice": 0.00, "sys": 0.00, "iowait": 0.00, "irq": 0.00, "soft": 0.00, "steal": 0.00, "guest": 0.00, "gnice": 0.00, "idle": 100.00},
						{"cpu": "6", "usr": 0.00, "nice": 0.00, "sys": 0.00, "iowait": 0.00, "irq": 0.00, "soft": 0.00, "steal": 0.00, "guest": 0.00, "gnice": 0.00, "idle": 100.00},
						{"cpu": "7", "usr": 0.00, "nice": 0.00, "sys": 0.00, "iowait": 0.00, "irq": 0.00, "soft": 0.00, "steal": 0.00, "guest": 0.00, "gnice": 0.00, "idle": 100.00},
						{"cpu": "8", "usr": 0.00, "nice": 0.00, "sys": 0.00, "iowait": 0.00, "irq": 0.00, "soft": 0.00, "steal": 0.00, "guest": 0.00, "gnice": 0.00, "idle": 100.00},
						{"cpu": "9", "usr": 0.00, "nice": 0.00, "sys": 0.00, "iowait": 0.00, "irq": 0.00, "soft": 0.00, "steal": 0.00, "guest": 0.00, "gnice": 0.00, "idle": 100.00},
						{"cpu": "10", "usr": 1.00, "nice": 0.00, "sys": 99.00, "iowait": 0.00, "irq": 0.00, "soft": 0.00, "steal": 0.00, "guest": 0.00, "gnice": 0.00, "idle": 0.00},
						{"cpu": "11", "usr": 0.00, "nice": 0.00, "sys": 0.00, "iowait": 0.00, "irq": 0.00, "soft": 0.00, "steal": 0.00, "guest": 0.00, "gnice": 0.00, "idle": 100.00},
						{"cpu": "12", "usr": 0.00, "nice": 0.00, "sys": 0.50, "iowait": 0.00, "irq": 0.00, "soft": 0.00, "steal": 0.00, "guest": 0.00, "gnice": 0.00, "idle": 99.50},
						{"cpu": "13", "usr": 0.00, "nice": 0.00, "sys": 0.00, "iowait": 0.00, "irq": 0.00, "soft": 0.00, "steal": 0.00, "guest": 0.00, "gnice": 0.00, "idle": 100.00},
						{"cpu": "14", "usr": 0.00, "nice": 0.00, "sys": 0.00, "iowait": 0.00, "irq": 0.00, "soft": 0.00, "steal": 0.00, "guest": 0.00, "gnice": 0.00, "idle": 100.00},
						{"cpu": "15", "usr": 0.00, "nice": 0.00, "sys": 0.00, "iowait": 0.00, "irq": 0.00, "soft": 0.00, "steal": 0.00, "guest": 0.00, "gnice": 0.00, "idle": 100.00}
					]
				},
				{
					"timestamp": "02:59:48 PM",
					"cpu-load": [
						{"cpu": "0", "usr": 0.00, "nice": 0.00, "sys": 0.00, "iowait": 0.00, "irq": 0.00, "soft": 0.00, "steal": 0.00, "guest": 0.00, "gnice": 0.00, "idle": 100.00},
						{"cpu": "1", "usr": 0.00, "nice": 0.00, "sys": 0.00, "iowait": 0.00, "irq": 0.00, "soft": 0.00, "steal": 0.00, "guest": 0.00, "gnice": 0.00, "idle": 100.00},
						{"cpu": "2", "usr": 0.00, "nice": 0.00, "sys": 0.52, "iowait": 0.00, "irq": 0.00, "soft": 0.52, "steal": 0.00, "guest": 0.00, "gnice": 0.00, "idle": 98.95},
						{"cpu": "3", "usr": 0.00, "nice": 0.00, "sys": 0.00, "iowait": 0.00, "irq": 0.00, "soft": 24.35, "steal": 0.00, "guest": 0.00, "gnice": 0.00, "idle": 75.65},
						{"cpu": "4", "usr": 0.00, "nice": 0.00, "sys": 0.00, "iowait": 0.00, "irq": 0.00, "soft": 0.00, "steal": 0.00, "guest": 0.00, "gnice": 0.00, "idle": 100.00},
						{"cpu": "5", "usr": 0.00, "nice": 0.00, "sys": 0.00, "iowait": 0.00, "irq": 0.00, "soft": 0.00, "steal": 0.00, "guest": 0.00, "gnice": 0.00, "idle": 100.00},
						{"cpu": "6", "usr": 0.00, "nice": 0.00, "sys": 0.00, "iowait": 0.00, "irq": 0.00, "soft": 0.00, "steal": 0.00, "guest": 0.00, "gnice": 0.00, "idle": 100.00},
						{"cpu": "7", "usr": 0.00, "nice": 0.00, "sys": 0.00, "iowait": 0.00, "irq": 0.00, "soft": 0.00, "steal": 0.00, "guest": 0.00, "gnice": 0.00, "idle": 100.00},
						{"cpu": "8", "usr": 0.00, "nice": 0.00, "sys": 0.00, "iowait": 0.00, "irq": 0.00, "soft": 0.00, "steal": 0.00, "guest": 0.00, "gnice": 0.00, "idle": 100.00},
						{"cpu": "9", "usr": 0.00, "nice": 0.00, "sys": 0.00, "iowait": 0.00, "irq": 0.00, "soft": 0.00, "steal": 0.00, "guest": 0.00, "gnice": 0.00, "idle": 100.00},
						{"cpu": "10", "usr": 0.50, "nice": 0.00, "sys": 99.50, "iowait": 0.00, "irq": 0.00, "soft": 0.00, "steal": 0.00, "guest": 0.00, "gnice": 0.00, "idle": 0.00},
						{"cpu": "11", "usr": 0.00, "nice": 0.00, "sys": 0.00, "iowait": 0.00, "irq": 0.00, "soft": 0.00, "steal": 0.00, "guest": 0.00, "gnice": 0.00, "idle": 100.00},
						{"cpu": "12", "usr": 0.50, "nice": 0.00, "sys": 0.50, "iowait": 0.00, "irq": 0.00, "soft": 0.00, "steal": 0.00, "guest": 0.00, "gnice": 0.00, "idle": 99.00},
						{"cpu": "13", "usr": 0.00, "nice": 0.00, "sys": 0.00, "iowait": 0.00, "irq": 0.00, "soft": 0.00, "steal": 0.00, "guest": 0.00, "gnice": 0.00, "idle": 100.00},
						{"cpu": "14", "usr": 0.00, "nice": 0.00, "sys": 0.00, "iowait": 0.00, "irq": 0.00, "soft": 0.00, "steal": 0.00, "guest": 0.00, "gnice": 0.00, "idle": 100.00},
						{"cpu": "15", "usr": 0.00, "nice": 0.00, "sys": 0.00, "iowait": 0.00, "irq": 0.00, "soft": 0.00, "steal": 0.00, "guest": 0.00, "gnice": 0.00, "idle": 100.00}
					]
				},
				{
					"timestamp": "02:59:50 PM",
					"cpu-load": [
						{"cpu": "0", "usr": 0.00, "nice": 0.00, "sys": 0.00, "iowait": 0.00, "irq": 0.00, "soft": 0.00, "steal": 0.00, "guest": 0.00, "gnice": 0.00, "idle": 100.00},
						{"cpu": "1", "usr": 0.00, "nice": 0.00, "sys": 0.00, "iowait": 0.00, "irq": 0.00, "soft": 0.00, "steal": 0.00, "guest": 0.00, "gnice": 0.00, "idle": 100.00},
						{"cpu": "2", "usr": 0.00, "nice": 0.00, "sys": 0.00, "iowait": 0.00, "irq": 0.00, "soft": 1.04, "steal": 0.00, "guest": 0.00, "gnice": 0.00, "idle": 98.96},
						{"cpu": "3", "usr": 0.00, "nice": 0.00, "sys": 0.00, "iowait": 0.00, "irq": 0.00, "soft": 27.50, "steal": 0.00, "guest": 0.00, "gnice": 0.00, "idle": 72.50},
						{"cpu": "4", "usr": 0.00, "nice": 0.00, "sys": 0.00, "iowait": 0.00, "irq": 0.00, "soft": 0.00, "steal": 0.00, "guest": 0.00, "gnice": 0.00, "idle": 100.00},
						{"cpu": "5", "usr": 0.00, "nice": 0.00, "sys": 0.00, "iowait": 0.00, "irq": 0.00, "soft": 0.00, "steal": 0.00, "guest": 0.00, "gnice": 0.00, "idle": 100.00},
						{"cpu": "6", "usr": 0.00, "nice": 0.00, "sys": 0.00, "iowait": 0.00, "irq": 0.00, "soft": 0.00, "steal": 0.00, "guest": 0.00, "gnice": 0.00, "idle": 100.00},
						{"cpu": "7", "usr": 0.00, "nice": 0.00, "sys": 0.00, "iowait": 0.00, "irq": 0.00, "soft": 0.00, "steal": 0.00, "guest": 0.00, "gnice": 0.00, "idle": 100.00},
						{"cpu": "8", "usr": 0.00, "nice": 0.00, "sys": 0.00, "iowait": 0.00, "irq": 0.00, "soft": 0.00, "steal": 0.00, "guest": 0.00, "gnice": 0.00, "idle": 100.00},
						{"cpu": "9", "usr": 0.00, "nice": 0.00, "sys": 0.00, "iowait": 0.00, "irq": 0.00, "soft": 0.00, "steal": 0.00, "guest": 0.00, "gnice": 0.00, "idle": 100.00},
						{"cpu": "10", "usr": 1.00, "nice": 0.00, "sys": 99.00, "iowait": 0.00, "irq": 0.00, "soft": 0.00, "steal": 0.00, "guest": 0.00, "gnice": 0.00, "idle": 0.00},
						{"cpu": "11", "usr": 0.00, "nice": 0.00, "sys": 0.00, "iowait": 0.00, "irq": 0.00, "soft": 0.00, "steal": 0.00, "guest": 0.00, "gnice": 0.00, "idle": 100.00},
						{"cpu": "12", "usr": 0.00, "nice": 0.00, "sys": 0.50, "iowait": 0.00, "irq": 0.00, "soft": 0.00, "steal": 0.00, "guest": 0.00, "gnice": 0.00, "idle": 99.50},
						{"cpu": "13", "usr": 0.00, "nice": 0.00, "sys": 0.00, "iowait": 0.00, "irq": 0.00, "soft": 0.00, "steal": 0.00, "guest": 0.00, "gnice": 0.00, "idle": 100.00},
						{"cpu": "14", "usr": 0.00, "nice": 0.00, "sys": 0.00, "iowait": 0.00, "irq": 0.00, "soft": 0.00, "steal": 0.00, "guest": 0.00, "gnice": 0.00, "idle": 100.00},
						{"cpu": "15", "usr": 0.00, "nice": 0.00, "sys": 0.00, "iowait": 0.00, "irq": 0.00, "soft": 0.00, "steal": 0.00, "guest": 0.00, "gnice": 0.00, "idle": 100.00}
					]
				},
				{
					"timestamp": "02:59:52 PM",
					"cpu-load": [
						{"cpu": "0", "usr": 0.00, "nice": 0.00, "sys": 0.00, "iowait": 0.00, "irq": 0.00, "soft": 0.00, "steal": 0.00, "guest": 0.00, "gnice": 0.00, "idle": 100.00},
						{"cpu": "1", "usr": 0.00, "nice": 0.00, "sys": 0.00, "iowait": 0.00, "irq": 0.00, "soft": 0.00, "steal": 0.00, "guest": 0.00, "gnice": 0.00, "idle": 100.00},
						{"cpu": "2", "usr": 0.51, "nice": 0.00, "sys": 0.51, "iowait": 0.00, "irq": 0.00, "soft": 0.51, "steal": 0.00, "guest": 0.00, "gnice": 0.00, "idle": 98.46},
						{"cpu": "3", "usr": 0.00, "nice": 0.00, "sys": 0.00, "iowait": 0.00, "irq": 0.00, "soft": 26.09, "steal": 0.00, "guest": 0.00, "gnice": 0.00, "idle": 73.91},
						{"cpu": "4", "usr": 0.00, "nice": 0.00, "sys": 0.00, "iowait": 0.00, "irq": 0.00, "soft": 0.00, "steal": 0.00, "guest": 0.00, "gnice": 0.00, "idle": 100.00},
						{"cpu": "5", "usr": 0.00, "nice": 0.00, "sys": 0.00, "iowait": 0.00, "irq": 0.00, "soft": 0.00, "steal": 0.00, "guest": 0.00, "gnice": 0.00, "idle": 100.00},
						{"cpu": "6", "usr": 0.00, "nice": 0.00, "sys": 0.00, "iowait": 0.00, "irq": 0.00, "soft": 0.00, "steal": 0.00, "guest": 0.00, "gnice": 0.00, "idle": 100.00},
						{"cpu": "7", "usr": 0.00, "nice": 0.00, "sys": 0.00, "iowait": 0.00, "irq": 0.00, "soft": 0.00, "steal": 0.00, "guest": 0.00, "gnice": 0.00, "idle": 100.00},
						{"cpu": "8", "usr": 0.00, "nice": 0.00, "sys": 0.00, "iowait": 0.00, "irq": 0.00, "soft": 0.00, "steal": 0.00, "guest": 0.00, "gnice": 0.00, "idle": 100.00},
						{"cpu": "9", "usr": 0.00, "nice": 0.00, "sys": 0.00, "iowait": 0.00, "irq": 0.00, "soft": 0.00, "steal": 0.00, "guest": 0.00, "gnice": 0.00, "idle": 100.00},
						{"cpu": "10", "usr": 1.00, "nice": 0.00, "sys": 99.00, "iowait": 0.00, "irq": 0.00, "soft": 0.00, "steal": 0.00, "guest": 0.00, "gnice": 0.00, "idle": 0.00},
						{"cpu": "11", "usr": 0.00, "nice": 0.00, "sys": 0.00, "iowait": 0.00, "irq": 0.00, "soft": 0.00, "steal": 0.00, "guest": 0.00, "gnice": 0.00, "idle": 100.00},
						{"cpu": "12", "usr": 0.50, "nice": 0.00, "sys": 0.50, "iowait": 0.00, "irq": 0.00, "soft": 0.00, "steal": 0.00, "guest": 0.00, "gnice": 0.00, "idle": 99.00},
						{"cpu": "13", "usr": 0.00, "nice": 0.00, "sys": 0.00, "iowait": 0.00, "irq": 0.00, "soft": 0.00, "steal": 0.00, "guest": 0.00, "gnice": 0.00, "idle": 100.00},
						{"cpu": "14", "usr": 0.00, "nice": 0.00, "sys": 0.00, "iowait": 0.00, "irq": 0.00, "soft": 0.00, "steal": 0.00, "guest": 0.00, "gnice": 0.00, "idle": 100.00},
						{"cpu": "15", "usr": 0.00, "nice": 0.00, "sys": 0.00, "iowait": 0.00, "irq": 0.00, "soft": 0.00, "steal": 0.00, "guest": 0.00, "gnice": 0.00, "idle": 100.00}
					]
				},
				{
					"timestamp": "02:59:54 PM",
					"cpu-load": [
						{"cpu": "0", "usr": 0.00, "nice": 0.00, "sys": 0.00, "iowait": 0.00, "irq": 0.00, "soft": 0.00, "steal": 0.00, "guest": 0.00, "gnice": 0.00, "idle": 100.00},
						{"cpu": "1", "usr": 0.00, "nice": 0.00, "sys": 0.00, "iowait": 0.00, "irq": 0.00, "soft": 0.00, "steal": 0.00, "guest": 0.00, "gnice": 0.00, "idle": 100.00},
						{"cpu": "2", "usr": 0.00, "nice": 0.00, "sys": 0.00, "iowait": 0.00, "irq": 0.00, "soft": 0.52, "steal": 0.00, "guest": 0.00, "gnice": 0.00, "idle": 99.48},
						{"cpu": "3", "usr": 0.00, "nice": 0.00, "sys": 0.00, "iowait": 0.00, "irq": 0.00, "soft": 28.33, "steal": 0.00, "guest": 0.00, "gnice": 0.00, "idle": 71.67},
						{"cpu": "4", "usr": 0.00, "nice": 0.00, "sys": 0.00, "iowait": 0.00, "irq": 0.00, "soft": 0.00, "steal": 0.00, "guest": 0.00, "gnice": 0.00, "idle": 100.00},
						{"cpu": "5", "usr": 0.00, "nice": 0.00, "sys": 0.00, "iowait": 0.00, "irq": 0.00, "soft": 0.00, "steal": 0.00, "guest": 0.00, "gnice": 0.00, "idle": 100.00},
						{"cpu": "6", "usr": 0.00, "nice": 0.00, "sys": 0.00, "iowait": 0.00, "irq": 0.00, "soft": 0.00, "steal": 0.00, "guest": 0.00, "gnice": 0.00, "idle": 100.00},
						{"cpu": "7", "usr": 0.00, "nice": 0.00, "sys": 0.00, "iowait": 0.00, "irq": 0.00, "soft": 0.00, "steal": 0.00, "guest": 0.00, "gnice": 0.00, "idle": 100.00},
						{"cpu": "8", "usr": 0.00, "nice": 0.00, "sys": 0.00, "iowait": 0.00, "irq": 0.00, "soft": 0.00, "steal": 0.00, "guest": 0.00, "gnice": 0.00, "idle": 100.00},
						{"cpu": "9", "usr": 0.00, "nice": 0.00, "sys": 0.00, "iowait": 0.00, "irq": 0.00, "soft": 0.00, "steal": 0.00, "guest": 0.00, "gnice": 0.00, "idle": 100.00},
						{"cpu": "10", "usr": 1.50, "nice": 0.00, "sys": 98.50, "iowait": 0.00, "irq": 0.00, "soft": 0.00, "steal": 0.00, "guest": 0.00, "gnice": 0.00, "idle": 0.00},
						{"cpu": "11", "usr": 0.00, "nice": 0.00, "sys": 0.00, "iowait": 0.00, "irq": 0.00, "soft": 0.00, "steal": 0.00, "guest": 0.00, "gnice": 0.00, "idle": 100.00},
						{"cpu": "12", "usr": 0.50, "nice": 0.00, "sys": 0.50, "iowait": 0.00, "irq": 0.00, "soft": 0.00, "steal": 0.00, "guest": 0.00, "gnice": 0.00, "idle": 99.00},
						{"cpu": "13", "usr": 0.00, "nice": 0.00, "sys": 0.00, "iowait": 0.00, "irq": 0.00, "soft": 0.00, "steal": 0.00, "guest": 0.00, "gnice": 0.00, "idle": 100.00},
						{"cpu": "14", "usr": 0.00, "nice": 0.00, "sys": 0.00, "iowait": 0.00, "irq": 0.00, "soft": 0.00, "steal": 0.00, "guest": 0.00, "gnice": 0.00, "idle": 100.00},
						{"cpu": "15", "usr": 0.00, "nice": 0.00, "sys": 0.00, "iowait": 0.00, "irq": 0.00, "soft": 0.00, "steal": 0.00, "guest": 0.00, "gnice": 0.00, "idle": 100.00}
					]
				},
				{
					"timestamp": "02:59:56 PM",
					"cpu-load": [
						{"cpu": "0", "usr": 0.00, "nice": 0.00, "sys": 0.00, "iowait": 0.00, "irq": 0.00, "soft": 0.00, "steal": 0.00, "guest": 0.00, "gnice": 0.00, "idle": 100.00},
						{"cpu": "1", "usr": 0.00, "nice": 0.00, "sys": 0.00, "iowait": 0.00, "irq": 0.00, "soft": 0.00, "steal": 0.00, "guest": 0.00, "gnice": 0.00, "idle": 100.00},
						{"cpu": "2", "usr": 0.00, "nice": 0.00, "sys": 0.00, "iowait": 0.00, "irq": 0.00, "soft": 0.52, "steal": 0.00, "guest": 0.00, "gnice": 0.00, "idle": 99.48},
						{"cpu": "3", "usr": 0.00, "nice": 0.00, "sys": 0.00, "iowait": 0.00, "irq": 0.00, "soft": 20.18, "steal": 0.00, "guest": 0.00, "gnice": 0.00, "idle": 79.82},
						{"cpu": "4", "usr": 0.00, "nice": 0.00, "sys": 0.00, "iowait": 0.00, "irq": 0.00, "soft": 0.00, "steal": 0.00, "guest": 0.00, "gnice": 0.00, "idle": 100.00},
						{"cpu": "5", "usr": 0.00, "nice": 0.00, "sys": 0.00, "iowait": 0.00, "irq": 0.00, "soft": 0.00, "steal": 0.00, "guest": 0.00, "gnice": 0.00, "idle": 100.00},
						{"cpu": "6", "usr": 0.00, "nice": 0.00, "sys": 0.00, "iowait": 0.00, "irq": 0.00, "soft": 0.00, "steal": 0.00, "guest": 0.00, "gnice": 0.00, "idle": 100.00},
						{"cpu": "7", "usr": 0.00, "nice": 0.00, "sys": 0.00, "iowait": 0.00, "irq": 0.00, "soft": 0.00, "steal": 0.00, "guest": 0.00, "gnice": 0.00, "idle": 100.00},
						{"cpu": "8", "usr": 0.00, "nice": 0.00, "sys": 0.00, "iowait": 0.00, "irq": 0.00, "soft": 0.00, "steal": 0.00, "guest": 0.00, "gnice": 0.00, "idle": 100.00},
						{"cpu": "9", "usr": 0.00, "nice": 0.00, "sys": 0.00, "iowait": 0.00, "irq": 0.00, "soft": 0.00, "steal": 0.00, "guest": 0.00, "gnice": 0.00, "idle": 100.00},
						{"cpu": "10", "usr": 1.00, "nice": 0.00, "sys": 99.00, "iowait": 0.00, "irq": 0.00, "soft": 0.00, "steal": 0.00, "guest": 0.00, "gnice": 0.00, "idle": 0.00},
						{"cpu": "11", "usr": 0.00, "nice": 0.00, "sys": 0.00, "iowait": 0.00, "irq": 0.00, "soft": 0.00, "steal": 0.00, "guest": 0.00, "gnice": 0.00, "idle": 100.00},
						{"cpu": "12", "usr": 0.00, "nice": 0.00, "sys": 1.00, "iowait": 0.00, "irq": 0.00, "soft": 0.00, "steal": 0.00, "guest": 0.00, "gnice": 0.00, "idle": 99.00},
						{"cpu": "13", "usr": 0.00, "nice": 0.00, "sys": 0.00, "iowait": 0.00, "irq": 0.00, "soft": 0.00, "steal": 0.00, "guest": 0.00, "gnice": 0.00, "idle": 100.00},
						{"cpu": "14", "usr": 0.00, "nice": 0.00, "sys": 0.50, "iowait": 0.00, "irq": 0.00, "soft": 0.00, "steal": 0.00, "guest": 0.00, "gnice": 0.00, "idle": 99.50},
						{"cpu": "15", "usr": 0.00, "nice": 0.00, "sys": 0.00, "iowait": 0.00, "irq": 0.00, "soft": 0.00, "steal": 0.00, "guest": 0.00, "gnice": 0.00, "idle": 100.00}
					]
				},
				{
					"timestamp": "02:59:58 PM",
					"cpu-load": [
						{"cpu": "0", "usr": 0.00, "nice": 0.00, "sys": 0.00, "iowait": 0.00, "irq": 0.00, "soft": 0.00, "steal": 0.00, "guest": 0.00, "gnice": 0.00, "idle": 100.00},
						{"cpu": "1", "usr": 0.00, "nice": 0.00, "sys": 0.00, "iowait": 0.00, "irq": 0.00, "soft": 0.00, "steal": 0.00, "guest": 0.00, "gnice": 0.00, "idle": 100.00},
						{"cpu": "2", "usr": 0.00, "nice": 0.00, "sys": 0.00, "iowait": 0.00, "irq": 0.00, "soft": 0.52, "steal": 0.00, "guest": 0.00, "gnice": 0.00, "idle": 99.48},
						{"cpu": "3", "usr": 0.00, "nice": 0.00, "sys": 0.00, "iowait": 0.00, "irq": 0.00, "soft": 26.50, "steal": 0.00, "guest": 0.00, "gnice": 0.00, "idle": 73.50},
						{"cpu": "4", "usr": 0.00, "nice": 0.00, "sys": 0.00, "iowait": 0.00, "irq": 0.00, "soft": 0.00, "steal": 0.00, "guest": 0.00, "gnice": 0.00, "idle": 100.00},
						{"cpu": "5", "usr": 0.00, "nice": 0.00, "sys": 0.00, "iowait": 0.00, "irq": 0.00, "soft": 0.00, "steal": 0.00, "guest": 0.00, "gnice": 0.00, "idle": 100.00},
						{"cpu": "6", "usr": 0.00, "nice": 0.00, "sys": 0.00, "iowait": 0.00, "irq": 0.00, "soft": 0.00, "steal": 0.00, "guest": 0.00, "gnice": 0.00, "idle": 100.00},
						{"cpu": "7", "usr": 0.00, "nice": 0.00, "sys": 0.00, "iowait": 0.00, "irq": 0.00, "soft": 0.00, "steal": 0.00, "guest": 0.00, "gnice": 0.00, "idle": 100.00},
						{"cpu": "8", "usr": 0.00, "nice": 0.00, "sys": 0.00, "iowait": 0.00, "irq": 0.00, "soft": 0.00, "steal": 0.00, "guest": 0.00, "gnice": 0.00, "idle": 100.00},
						{"cpu": "9", "usr": 0.00, "nice": 0.00, "sys": 0.00, "iowait": 0.00, "irq": 0.00, "soft": 0.00, "steal": 0.00, "guest": 0.00, "gnice": 0.00, "idle": 100.00},
						{"cpu": "10", "usr": 0.00, "nice": 0.00, "sys": 100.00, "iowait": 0.00, "irq": 0.00, "soft": 0.00, "steal": 0.00, "guest": 0.00, "gnice": 0.00, "idle": 0.00},
						{"cpu": "11", "usr": 0.00, "nice": 0.00, "sys": 0.00, "iowait": 0.00, "irq": 0.00, "soft": 0.00, "steal": 0.00, "guest": 0.00, "gnice": 0.00, "idle": 100.00},
						{"cpu": "12", "usr": 0.00, "nice": 0.00, "sys": 0.50, "iowait": 0.00, "irq": 0.00, "soft": 0.00, "steal": 0.00, "guest": 0.00, "gnice": 0.00, "idle": 99.50},
						{"cpu": "13", "usr": 0.00, "nice": 0.00, "sys": 0.00, "iowait": 0.00, "irq": 0.00, "soft": 0.00, "steal": 0.00, "guest": 0.00, "gnice": 0.00, "idle": 100.00},
						{"cpu": "14", "usr": 0.00, "nice": 0.00, "sys": 0.00, "iowait": 0.00, "irq": 0.00, "soft": 0.00, "steal": 0.00, "guest": 0.00, "gnice": 0.00, "idle": 100.00},
						{"cpu": "15", "usr": 0.00, "nice": 0.00, "sys": 0.00, "iowait": 0.00, "irq": 0.00, "soft": 0.00, "steal": 0.00, "guest": 0.00, "gnice": 0.00, "idle": 100.00}
					]
				},
				{
					"timestamp": "03:00:00 PM",
					"cpu-load": [
						{"cpu": "0", "usr": 0.00, "nice": 0.00, "sys": 0.00, "iowait": 0.00, "irq": 0.00, "soft": 0.00, "steal": 0.00, "guest": 0.00, "gnice": 0.00, "idle": 100.00},
						{"cpu": "1", "usr": 0.00, "nice": 0.00, "sys": 0.00, "iowait": 0.00, "irq": 0.00, "soft": 0.00, "steal": 0.00, "guest": 0.00, "gnice": 0.00, "idle": 100.00},
						{"cpu": "2", "usr": 0.00, "nice": 0.00, "sys": 0.00, "iowait": 0.00, "irq": 0.00, "soft": 0.52, "steal": 0.00, "guest": 0.00, "gnice": 0.00, "idle": 99.48},
						{"cpu": "3", "usr": 0.00, "nice": 0.00, "sys": 0.00, "iowait": 0.00, "irq": 0.00, "soft": 25.86, "steal": 0.00, "guest": 0.00, "gnice": 0.00, "idle": 74.14},
						{"cpu": "4", "usr": 0.00, "nice": 0.00, "sys": 0.00, "iowait": 0.00, "irq": 0.00, "soft": 0.00, "steal": 0.00, "guest": 0.00, "gnice": 0.00, "idle": 100.00},
						{"cpu": "5", "usr": 0.00, "nice": 0.00, "sys": 0.00, "iowait": 0.00, "irq": 0.00, "soft": 0.00, "steal": 0.00, "guest": 0.00, "gnice": 0.00, "idle": 100.00},
						{"cpu": "6", "usr": 0.00, "nice": 0.00, "sys": 0.00, "iowait": 0.00, "irq": 0.00, "soft": 0.00, "steal": 0.00, "guest": 0.00, "gnice": 0.00, "idle": 100.00},
						{"cpu": "7", "usr": 0.00, "nice": 0.00, "sys": 0.00, "iowait": 0.00, "irq": 0.00, "soft": 0.00, "steal": 0.00, "guest": 0.00, "gnice": 0.00, "idle": 100.00},
						{"cpu": "8", "usr": 0.00, "nice": 0.00, "sys": 0.00, "iowait": 0.00, "irq": 0.00, "soft": 0.00, "steal": 0.00, "guest": 0.00, "gnice": 0.00, "idle": 100.00},
						{"cpu": "9", "usr": 0.00, "nice": 0.00, "sys": 0.00, "iowait": 0.00, "irq": 0.00, "soft": 0.00, "steal": 0.00, "guest": 0.00, "gnice": 0.00, "idle": 100.00},
						{"cpu": "10", "usr": 1.00, "nice": 0.00, "sys": 99.00, "iowait": 0.00, "irq": 0.00, "soft": 0.00, "steal": 0.00, "guest": 0.00, "gnice": 0.00, "idle": 0.00},
						{"cpu": "11", "usr": 0.00, "nice": 0.00, "sys": 0.00, "iowait": 0.00, "irq": 0.00, "soft": 0.00, "steal": 0.00, "guest": 0.00, "gnice": 0.00, "idle": 100.00},
						{"cpu": "12", "usr": 0.00, "nice": 0.00, "sys": 0.50, "iowait": 0.00, "irq": 0.00, "soft": 0.00, "steal": 0.00, "guest": 0.00, "gnice": 0.00, "idle": 99.50},
						{"cpu": "13", "usr": 0.00, "nice": 0.00, "sys": 0.00, "iowait": 0.00, "irq": 0.00, "soft": 0.00, "steal": 0.00, "guest": 0.00, "gnice": 0.00, "idle": 100.00},
						{"cpu": "14", "usr": 0.00, "nice": 0.00, "sys": 0.00, "iowait": 0.00, "irq": 0.00, "soft": 0.00, "steal": 0.00, "guest": 0.00, "gnice": 0.00, "idle": 100.00},
						{"cpu": "15", "usr": 0.00, "nice": 0.00, "sys": 0.00, "iowait": 0.00, "irq": 0.00, "soft": 0.00, "steal": 0.00, "guest": 0.00, "gnice": 0.00, "idle": 100.00}
					]
				},
				{
					"timestamp": "03:00:02 PM",
					"cpu-load": [
						{"cpu": "0", "usr": 0.00, "nice": 0.00, "sys": 0.00, "iowait": 0.00, "irq": 0.00, "soft": 0.00, "steal": 0.00, "guest": 0.00, "gnice": 0.00, "idle": 100.00},
						{"cpu": "1", "usr": 0.00, "nice": 0.00, "sys": 0.00, "iowait": 0.00, "irq": 0.00, "soft": 0.00, "steal": 0.00, "guest": 0.00, "gnice": 0.00, "idle": 100.00},
						{"cpu": "2", "usr": 0.00, "nice": 0.00, "sys": 0.52, "iowait": 0.00, "irq": 0.00, "soft": 0.00, "steal": 0.00, "guest": 0.00, "gnice": 0.00, "idle": 99.48},
						{"cpu": "3", "usr": 0.00, "nice": 0.00, "sys": 0.00, "iowait": 0.00, "irq": 0.00, "soft": 25.86, "steal": 0.00, "guest": 0.00, "gnice": 0.00, "idle": 74.14},
						{"cpu": "4", "usr": 0.00, "nice": 0.00, "sys": 0.00, "iowait": 0.00, "irq": 0.00, "soft": 0.00, "steal": 0.00, "guest": 0.00, "gnice": 0.00, "idle": 100.00},
						{"cpu": "5", "usr": 0.00, "nice": 0.00, "sys": 0.00, "iowait": 0.00, "irq": 0.00, "soft": 0.00, "steal": 0.00, "guest": 0.00, "gnice": 0.00, "idle": 100.00},
						{"cpu": "6", "usr": 0.00, "nice": 0.00, "sys": 0.00, "iowait": 0.00, "irq": 0.00, "soft": 0.00, "steal": 0.00, "guest": 0.00, "gnice": 0.00, "idle": 100.00},
						{"cpu": "7", "usr": 0.00, "nice": 0.00, "sys": 0.00, "iowait": 0.00, "irq": 0.00, "soft": 0.00, "steal": 0.00, "guest": 0.00, "gnice": 0.00, "idle": 100.00},
						{"cpu": "8", "usr": 0.00, "nice": 0.00, "sys": 0.00, "iowait": 0.00, "irq": 0.00, "soft": 0.00, "steal": 0.00, "guest": 0.00, "gnice": 0.00, "idle": 100.00},
						{"cpu": "9", "usr": 0.00, "nice": 0.00, "sys": 0.00, "iowait": 0.00, "irq": 0.00, "soft": 0.00, "steal": 0.00, "guest": 0.00, "gnice": 0.00, "idle": 100.00},
						{"cpu": "10", "usr": 0.50, "nice": 0.00, "sys": 99.50, "iowait": 0.00, "irq": 0.00, "soft": 0.00, "steal": 0.00, "guest": 0.00, "gnice": 0.00, "idle": 0.00},
						{"cpu": "11", "usr": 0.00, "nice": 0.00, "sys": 0.00, "iowait": 0.00, "irq": 0.00, "soft": 0.00, "steal": 0.00, "guest": 0.00, "gnice": 0.00, "idle": 100.00},
						{"cpu": "12", "usr": 0.00, "nice": 0.00, "sys": 1.00, "iowait": 0.00, "irq": 0.00, "soft": 0.00, "steal": 0.00, "guest": 0.00, "gnice": 0.00, "idle": 99.00},
						{"cpu": "13", "usr": 0.00, "nice": 0.00, "sys": 0.00, "iowait": 0.00, "irq": 0.00, "soft": 0.00, "steal": 0.00, "guest": 0.00, "gnice": 0.00, "idle": 100.00},
						{"cpu": "14", "usr": 0.00, "nice": 0.00, "sys": 0.00, "iowait": 0.00, "irq": 0.00, "soft": 0.00, "steal": 0.00, "guest": 0.00, "gnice": 0.00, "idle": 100.00},
						{"cpu": "15", "usr": 0.00, "nice": 0.00, "sys": 0.00, "iowait": 0.00, "irq": 0.00, "soft": 0.00, "steal": 0.00, "guest": 0.00, "gnice": 0.00, "idle": 100.00}
					]
				},
				{
					"timestamp": "03:00:04 PM",
					"cpu-load": [
						{"cpu": "0", "usr": 0.00, "nice": 0.00, "sys": 0.00, "iowait": 0.00, "irq": 0.00, "soft": 0.00, "steal": 0.00, "guest": 0.00, "gnice": 0.00, "idle": 100.00},
						{"cpu": "1", "usr": 0.00, "nice": 0.00, "sys": 0.00, "iowait": 0.00, "irq": 0.00, "soft": 0.00, "steal": 0.00, "guest": 0.00, "gnice": 0.00, "idle": 100.00},
						{"cpu": "2", "usr": 0.00, "nice": 0.00, "sys": 0.00, "iowait": 0.00, "irq": 0.00, "soft": 0.00, "steal": 0.00, "guest": 0.00, "gnice": 0.00, "idle": 100.00},
						{"cpu": "3", "usr": 0.00, "nice": 0.00, "sys": 0.00, "iowait": 0.00, "irq": 0.00, "soft": 24.35, "steal": 0.00, "guest": 0.00, "gnice": 0.00, "idle": 75.65},
						{"cpu": "4", "usr": 0.00, "nice": 0.00, "sys": 0.00, "iowait": 0.00, "irq": 0.00, "soft": 0.00, "steal": 0.00, "guest": 0.00, "gnice": 0.00, "idle": 100.00},
						{"cpu": "5", "usr": 0.00, "nice": 0.00, "sys": 0.00, "iowait": 0.00, "irq": 0.00, "soft": 0.00, "steal": 0.00, "guest": 0.00, "gnice": 0.00, "idle": 100.00},
						{"cpu": "6", "usr": 0.00, "nice": 0.00, "sys": 0.00, "iowait": 0.00, "irq": 0.00, "soft": 0.00, "steal": 0.00, "guest": 0.00, "gnice": 0.00, "idle": 100.00},
						{"cpu": "7", "usr": 0.00, "nice": 0.00, "sys": 0.00, "iowait": 0.00, "irq": 0.00, "soft": 0.00, "steal": 0.00, "guest": 0.00, "gnice": 0.00, "idle": 100.00},
						{"cpu": "8", "usr": 0.00, "nice": 0.00, "sys": 0.00, "iowait": 0.00, "irq": 0.00, "soft": 0.00, "steal": 0.00, "guest": 0.00, "gnice": 0.00, "idle": 100.00},
						{"cpu": "9", "usr": 0.00, "nice": 0.00, "sys": 0.00, "iowait": 0.00, "irq": 0.00, "soft": 0.00, "steal": 0.00, "guest": 0.00, "gnice": 0.00, "idle": 100.00},
						{"cpu": "10", "usr": 1.00, "nice": 0.00, "sys": 99.00, "iowait": 0.00, "irq": 0.00, "soft": 0.00, "steal": 0.00, "guest": 0.00, "gnice": 0.00, "idle": 0.00},
						{"cpu": "11", "usr": 0.00, "nice": 0.00, "sys": 0.00, "iowait": 0.00, "irq": 0.00, "soft": 0.00, "steal": 0.00, "guest": 0.00, "gnice": 0.00, "idle": 100.00},
						{"cpu": "12", "usr": 0.50, "nice": 0.00, "sys": 0.50, "iowait": 0.00, "irq": 0.00, "soft": 0.00, "steal": 0.00, "guest": 0.00, "gnice": 0.00, "idle": 99.00},
						{"cpu": "13", "usr": 0.00, "nice": 0.00, "sys": 0.00, "iowait": 0.00, "irq": 0.00, "soft": 0.00, "steal": 0.00, "guest": 0.00, "gnice": 0.00, "idle": 100.00},
						{"cpu": "14", "usr": 0.00, "nice": 0.00, "sys": 0.00, "iowait": 0.00, "irq": 0.00, "soft": 0.00, "steal": 0.00, "guest": 0.00, "gnice": 0.00, "idle": 100.00},
						{"cpu": "15", "usr": 0.00, "nice": 0.00, "sys": 0.00, "iowait": 0.00, "irq": 0.00, "soft": 0.00, "steal": 0.00, "guest": 0.00, "gnice": 0.00, "idle": 100.00}
					]
				},
				{
					"timestamp": "03:00:06 PM",
					"cpu-load": [
						{"cpu": "0", "usr": 0.00, "nice": 0.00, "sys": 0.00, "iowait": 0.00, "irq": 0.00, "soft": 0.00, "steal": 0.00, "guest": 0.00, "gnice": 0.00, "idle": 100.00},
						{"cpu": "1", "usr": 0.00, "nice": 0.00, "sys": 0.00, "iowait": 0.00, "irq": 0.00, "soft": 0.00, "steal": 0.00, "guest": 0.00, "gnice": 0.00, "idle": 100.00},
						{"cpu": "2", "usr": 0.00, "nice": 0.00, "sys": 0.00, "iowait": 0.00, "irq": 0.00, "soft": 0.52, "steal": 0.00, "guest": 0.00, "gnice": 0.00, "idle": 99.48},
						{"cpu": "3", "usr": 0.00, "nice": 0.00, "sys": 0.00, "iowait": 0.00, "irq": 0.00, "soft": 26.72, "steal": 0.00, "guest": 0.00, "gnice": 0.00, "idle": 73.28},
						{"cpu": "4", "usr": 0.00, "nice": 0.00, "sys": 0.00, "iowait": 0.00, "irq": 0.00, "soft": 0.00, "steal": 0.00, "guest": 0.00, "gnice": 0.00, "idle": 100.00},
						{"cpu": "5", "usr": 0.00, "nice": 0.00, "sys": 0.00, "iowait": 0.00, "irq": 0.00, "soft": 0.00, "steal": 0.00, "guest": 0.00, "gnice": 0.00, "idle": 100.00},
						{"cpu": "6", "usr": 0.00, "nice": 0.00, "sys": 0.00, "iowait": 0.00, "irq": 0.00, "soft": 0.00, "steal": 0.00, "guest": 0.00, "gnice": 0.00, "idle": 100.00},
						{"cpu": "7", "usr": 0.00, "nice": 0.00, "sys": 0.00, "iowait": 0.00, "irq": 0.00, "soft": 0.00, "steal": 0.00, "guest": 0.00, "gnice": 0.00, "idle": 100.00},
						{"cpu": "8", "usr": 0.00, "nice": 0.00, "sys": 0.00, "iowait": 0.00, "irq": 0.00, "soft": 0.00, "steal": 0.00, "guest": 0.00, "gnice": 0.00, "idle": 100.00},
						{"cpu": "9", "usr": 0.00, "nice": 0.00, "sys": 0.00, "iowait": 0.00, "irq": 0.00, "soft": 0.00, "steal": 0.00, "guest": 0.00, "gnice": 0.00, "idle": 100.00},
						{"cpu": "10", "usr": 0.50, "nice": 0.00, "sys": 99.50, "iowait": 0.00, "irq": 0.00, "soft": 0.00, "steal": 0.00, "guest": 0.00, "gnice": 0.00, "idle": 0.00},
						{"cpu": "11", "usr": 0.00, "nice": 0.00, "sys": 0.00, "iowait": 0.00, "irq": 0.00, "soft": 0.00, "steal": 0.00, "guest": 0.00, "gnice": 0.00, "idle": 100.00},
						{"cpu": "12", "usr": 0.00, "nice": 0.00, "sys": 0.50, "iowait": 0.00, "irq": 0.00, "soft": 0.00, "steal": 0.00, "guest": 0.00, "gnice": 0.00, "idle": 99.50},
						{"cpu": "13", "usr": 0.00, "nice": 0.00, "sys": 0.00, "iowait": 0.00, "irq": 0.00, "soft": 0.00, "steal": 0.00, "guest": 0.00, "gnice": 0.00, "idle": 100.00},
						{"cpu": "14", "usr": 0.00, "nice": 0.00, "sys": 0.00, "iowait": 0.00, "irq": 0.00, "soft": 0.00, "steal": 0.00, "guest": 0.00, "gnice": 0.00, "idle": 100.00},
						{"cpu": "15", "usr": 0.00, "nice": 0.00, "sys": 0.00, "iowait": 0.00, "irq": 0.00, "soft": 0.00, "steal": 0.00, "guest": 0.00, "gnice": 0.00, "idle": 100.00}
					]
				},
				{
					"timestamp": "03:00:08 PM",
					"cpu-load": [
						{"cpu": "0", "usr": 0.00, "nice": 0.00, "sys": 0.00, "iowait": 0.00, "irq": 0.00, "soft": 0.00, "steal": 0.00, "guest": 0.00, "gnice": 0.00, "idle": 100.00},
						{"cpu": "1", "usr": 0.00, "nice": 0.00, "sys": 0.00, "iowait": 0.00, "irq": 0.00, "soft": 0.00, "steal": 0.00, "guest": 0.00, "gnice": 0.00, "idle": 100.00},
						{"cpu": "2", "usr": 0.00, "nice": 0.00, "sys": 0.00, "iowait": 0.00, "irq": 0.00, "soft": 1.54, "steal": 0.00, "guest": 0.00, "gnice": 0.00, "idle": 98.46},
						{"cpu": "3", "usr": 0.00, "nice": 0.00, "sys": 0.00, "iowait": 0.00, "irq": 0.00, "soft": 26.09, "steal": 0.00, "guest": 0.00, "gnice": 0.00, "idle": 73.91},
						{"cpu": "4", "usr": 0.00, "nice": 0.00, "sys": 0.00, "iowait": 0.00, "irq": 0.00, "soft": 0.00, "steal": 0.00, "guest": 0.00, "gnice": 0.00, "idle": 100.00},
						{"cpu": "5", "usr": 0.00, "nice": 0.00, "sys": 0.00, "iowait": 0.00, "irq": 0.00, "soft": 0.00, "steal": 0.00, "guest": 0.00, "gnice": 0.00, "idle": 100.00},
						{"cpu": "6", "usr": 0.00, "nice": 0.00, "sys": 0.00, "iowait": 0.00, "irq": 0.00, "soft": 0.00, "steal": 0.00, "guest": 0.00, "gnice": 0.00, "idle": 100.00},
						{"cpu": "7", "usr": 0.00, "nice": 0.00, "sys": 0.00, "iowait": 0.00, "irq": 0.00, "soft": 0.00, "steal": 0.00, "guest": 0.00, "gnice": 0.00, "idle": 100.00},
						{"cpu": "8", "usr": 0.00, "nice": 0.00, "sys": 0.00, "iowait": 0.00, "irq": 0.00, "soft": 0.00, "steal": 0.00, "guest": 0.00, "gnice": 0.00, "idle": 100.00},
						{"cpu": "9", "usr": 0.00, "nice": 0.00, "sys": 0.00, "iowait": 0.00, "irq": 0.00, "soft": 0.00, "steal": 0.00, "guest": 0.00, "gnice": 0.00, "idle": 100.00},
						{"cpu": "10", "usr": 1.00, "nice": 0.00, "sys": 99.00, "iowait": 0.00, "irq": 0.00, "soft": 0.00, "steal": 0.00, "guest": 0.00, "gnice": 0.00, "idle": 0.00},
						{"cpu": "11", "usr": 0.00, "nice": 0.00, "sys": 0.00, "iowait": 0.00, "irq": 0.00, "soft": 0.00, "steal": 0.00, "guest": 0.00, "gnice": 0.00, "idle": 100.00},
						{"cpu": "12", "usr": 0.00, "nice": 0.00, "sys": 0.50, "iowait": 0.00, "irq": 0.00, "soft": 0.00, "steal": 0.00, "guest": 0.00, "gnice": 0.00, "idle": 99.50},
						{"cpu": "13", "usr": 0.00, "nice": 0.00, "sys": 0.00, "iowait": 0.00, "irq": 0.00, "soft": 0.00, "steal": 0.00, "guest": 0.00, "gnice": 0.00, "idle": 100.00},
						{"cpu": "14", "usr": 0.00, "nice": 0.00, "sys": 0.00, "iowait": 0.00, "irq": 0.00, "soft": 0.00, "steal": 0.00, "guest": 0.00, "gnice": 0.00, "idle": 100.00},
						{"cpu": "15", "usr": 0.00, "nice": 0.00, "sys": 0.00, "iowait": 0.00, "irq": 0.00, "soft": 0.00, "steal": 0.00, "guest": 0.00, "gnice": 0.00, "idle": 100.00}
					]
				},
				{
					"timestamp": "03:00:10 PM",
					"cpu-load": [
						{"cpu": "0", "usr": 0.00, "nice": 0.00, "sys": 0.00, "iowait": 0.00, "irq": 0.00, "soft": 0.00, "steal": 0.00, "guest": 0.00, "gnice": 0.00, "idle": 100.00},
						{"cpu": "1", "usr": 0.00, "nice": 0.00, "sys": 0.00, "iowait": 0.00, "irq": 0.00, "soft": 0.00, "steal": 0.00, "guest": 0.00, "gnice": 0.00, "idle": 100.00},
						{"cpu": "2", "usr": 0.00, "nice": 0.00, "sys": 0.00, "iowait": 0.00, "irq": 0.00, "soft": 0.00, "steal": 0.00, "guest": 0.00, "gnice": 0.00, "idle": 100.00},
						{"cpu": "3", "usr": 0.00, "nice": 0.00, "sys": 0.00, "iowait": 0.00, "irq": 0.00, "soft": 28.21, "steal": 0.00, "guest": 0.00, "gnice": 0.00, "idle": 71.79},
						{"cpu": "4", "usr": 0.00, "nice": 0.00, "sys": 0.00, "iowait": 0.00, "irq": 0.00, "soft": 0.00, "steal": 0.00, "guest": 0.00, "gnice": 0.00, "idle": 100.00},
						{"cpu": "5", "usr": 0.00, "nice": 0.00, "sys": 0.00, "iowait": 0.00, "irq": 0.00, "soft": 0.00, "steal": 0.00, "guest": 0.00, "gnice": 0.00, "idle": 100.00},
						{"cpu": "6", "usr": 0.00, "nice": 0.00, "sys": 0.00, "iowait": 0.00, "irq": 0.00, "soft": 0.00, "steal": 0.00, "guest": 0.00, "gnice": 0.00, "idle": 100.00},
						{"cpu": "7", "usr": 0.00, "nice": 0.00, "sys": 0.00, "iowait": 0.00, "irq": 0.00, "soft": 0.00, "steal": 0.00, "guest": 0.00, "gnice": 0.00, "idle": 100.00},
						{"cpu": "8", "usr": 0.00, "nice": 0.00, "sys": 0.00, "iowait": 0.00, "irq": 0.00, "soft": 0.00, "steal": 0.00, "guest": 0.00, "gnice": 0.00, "idle": 100.00},
						{"cpu": "9", "usr": 0.00, "nice": 0.00, "sys": 0.00, "iowait": 0.00, "irq": 0.00, "soft": 0.00, "steal": 0.00, "guest": 0.00, "gnice": 0.00, "idle": 100.00},
						{"cpu": "10", "usr": 0.50, "nice": 0.00, "sys": 99.50, "iowait": 0.00, "irq": 0.00, "soft": 0.00, "steal": 0.00, "guest": 0.00, "gnice": 0.00, "idle": 0.00},
						{"cpu": "11", "usr": 0.00, "nice": 0.00, "sys": 0.00, "iowait": 0.00, "irq": 0.00, "soft": 0.00, "steal": 0.00, "guest": 0.00, "gnice": 0.00, "idle": 100.00},
						{"cpu": "12", "usr": 0.50, "nice": 0.00, "sys": 0.00, "iowait": 0.00, "irq": 0.00, "soft": 0.00, "steal": 0.00, "guest": 0.00, "gnice": 0.00, "idle": 99.50},
						{"cpu": "13", "usr": 0.00, "nice": 0.00, "sys": 0.00, "iowait": 0.00, "irq": 0.00, "soft": 0.00, "steal": 0.00, "guest": 0.00, "gnice": 0.00, "idle": 100.00},
						{"cpu": "14", "usr": 0.00, "nice": 0.00, "sys": 0.00, "iowait": 0.00, "irq": 0.00, "soft": 0.00, "steal": 0.00, "guest": 0.00, "gnice": 0.00, "idle": 100.00},
						{"cpu": "15", "usr": 0.00, "nice": 0.00, "sys": 0.00, "iowait": 0.00, "irq": 0.00, "soft": 0.00, "steal": 0.00, "guest": 0.00, "gnice": 0.00, "idle": 100.00}
					]
				},
				{
					"timestamp": "03:00:12 PM",
					"cpu-load": [
						{"cpu": "0", "usr": 0.00, "nice": 0.00, "sys": 0.00, "iowait": 0.00, "irq": 0.00, "soft": 0.00, "steal": 0.00, "guest": 0.00, "gnice": 0.00, "idle": 100.00},
						{"cpu": "1", "usr": 0.00, "nice": 0.00, "sys": 0.00, "iowait": 0.00, "irq": 0.00, "soft": 0.00, "steal": 0.00, "guest": 0.00, "gnice": 0.00, "idle": 100.00},
						{"cpu": "2", "usr": 0.00, "nice": 0.00, "sys": 1.04, "iowait": 0.00, "irq": 0.00, "soft": 1.56, "steal": 0.00, "guest": 0.00, "gnice": 0.00, "idle": 97.40},
						{"cpu": "3", "usr": 0.93, "nice": 0.00, "sys": 0.00, "iowait": 0.00, "irq": 0.00, "soft": 21.30, "steal": 0.00, "guest": 0.00, "gnice": 0.00, "idle": 77.78},
						{"cpu": "4", "usr": 0.00, "nice": 0.00, "sys": 0.00, "iowait": 0.00, "irq": 0.00, "soft": 0.00, "steal": 0.00, "guest": 0.00, "gnice": 0.00, "idle": 100.00},
						{"cpu": "5", "usr": 0.00, "nice": 0.00, "sys": 0.00, "iowait": 0.00, "irq": 0.00, "soft": 0.00, "steal": 0.00, "guest": 0.00, "gnice": 0.00, "idle": 100.00},
						{"cpu": "6", "usr": 0.00, "nice": 0.00, "sys": 0.00, "iowait": 0.00, "irq": 0.00, "soft": 0.00, "steal": 0.00, "guest": 0.00, "gnice": 0.00, "idle": 100.00},
						{"cpu": "7", "usr": 0.00, "nice": 0.00, "sys": 0.00, "iowait": 0.00, "irq": 0.00, "soft": 0.00, "steal": 0.00, "guest": 0.00, "gnice": 0.00, "idle": 100.00},
						{"cpu": "8", "usr": 0.00, "nice": 0.00, "sys": 0.00, "iowait": 0.00, "irq": 0.00, "soft": 0.00, "steal": 0.00, "guest": 0.00, "gnice": 0.00, "idle": 100.00},
						{"cpu": "9", "usr": 0.00, "nice": 0.00, "sys": 0.00, "iowait": 0.00, "irq": 0.00, "soft": 0.00, "steal": 0.00, "guest": 0.00, "gnice": 0.00, "idle": 100.00},
						{"cpu": "10", "usr": 1.50, "nice": 0.00, "sys": 98.50, "iowait": 0.00, "irq": 0.00, "soft": 0.00, "steal": 0.00, "guest": 0.00, "gnice": 0.00, "idle": 0.00},
						{"cpu": "11", "usr": 0.00, "nice": 0.00, "sys": 0.00, "iowait": 0.00, "irq": 0.00, "soft": 0.00, "steal": 0.00, "guest": 0.00, "gnice": 0.00, "idle": 100.00},
						{"cpu": "12", "usr": 0.00, "nice": 0.00, "sys": 0.50, "iowait": 0.00, "irq": 0.00, "soft": 0.00, "steal": 0.00, "guest": 0.00, "gnice": 0.00, "idle": 99.50},
						{"cpu": "13", "usr": 0.00, "nice": 0.00, "sys": 0.00, "iowait": 0.00, "irq": 0.00, "soft": 0.00, "steal": 0.00, "guest": 0.00, "gnice": 0.00, "idle": 100.00},
						{"cpu": "14", "usr": 0.00, "nice": 0.00, "sys": 0.00, "iowait": 2.00, "irq": 0.00, "soft": 0.00, "steal": 0.00, "guest": 0.00, "gnice": 0.00, "idle": 98.00},
						{"cpu": "15", "usr": 0.00, "nice": 0.00, "sys": 0.00, "iowait": 0.00, "irq": 0.00, "soft": 0.00, "steal": 0.00, "guest": 0.00, "gnice": 0.00, "idle": 100.00}
					]
				},
				{
					"timestamp": "03:00:14 PM",
					"cpu-load": [
						{"cpu": "0", "usr": 0.00, "nice": 0.00, "sys": 0.00, "iowait": 0.00, "irq": 0.00, "soft": 0.00, "steal": 0.00, "guest": 0.00, "gnice": 0.00, "idle": 100.00},
						{"cpu": "1", "usr": 0.00, "nice": 0.00, "sys": 0.00, "iowait": 0.00, "irq": 0.00, "soft": 0.00, "steal": 0.00, "guest": 0.00, "gnice": 0.00, "idle": 100.00},
						{"cpu": "2", "usr": 0.00, "nice": 0.00, "sys": 0.00, "iowait": 0.00, "irq": 0.00, "soft": 0.52, "steal": 0.00, "guest": 0.00, "gnice": 0.00, "idle": 99.48},
						{"cpu": "3", "usr": 0.00, "nice": 0.00, "sys": 0.00, "iowait": 0.00, "irq": 0.00, "soft": 27.50, "steal": 0.00, "guest": 0.00, "gnice": 0.00, "idle": 72.50},
						{"cpu": "4", "usr": 0.00, "nice": 0.00, "sys": 0.00, "iowait": 0.00, "irq": 0.00, "soft": 0.00, "steal": 0.00, "guest": 0.00, "gnice": 0.00, "idle": 100.00},
						{"cpu": "5", "usr": 0.00, "nice": 0.00, "sys": 0.00, "iowait": 0.00, "irq": 0.00, "soft": 0.00, "steal": 0.00, "guest": 0.00, "gnice": 0.00, "idle": 100.00},
						{"cpu": "6", "usr": 0.00, "nice": 0.00, "sys": 0.00, "iowait": 0.00, "irq": 0.00, "soft": 0.00, "steal": 0.00, "guest": 0.00, "gnice": 0.00, "idle": 100.00},
						{"cpu": "7", "usr": 0.00, "nice": 0.00, "sys": 0.00, "iowait": 0.00, "irq": 0.00, "soft": 0.00, "steal": 0.00, "guest": 0.00, "gnice": 0.00, "idle": 100.00},
						{"cpu": "8", "usr": 0.00, "nice": 0.00, "sys": 0.00, "iowait": 0.00, "irq": 0.00, "soft": 0.00, "steal": 0.00, "guest": 0.00, "gnice": 0.00, "idle": 100.00},
						{"cpu": "9", "usr": 0.00, "nice": 0.00, "sys": 0.00, "iowait": 0.00, "irq": 0.00, "soft": 0.00, "steal": 0.00, "guest": 0.00, "gnice": 0.00, "idle": 100.00},
						{"cpu": "10", "usr": 0.50, "nice": 0.00, "sys": 99.50, "iowait": 0.00, "irq": 0.00, "soft": 0.00, "steal": 0.00, "guest": 0.00, "gnice": 0.00, "idle": 0.00},
						{"cpu": "11", "usr": 0.00, "nice": 0.00, "sys": 0.00, "iowait": 0.00, "irq": 0.00, "soft": 0.00, "steal": 0.00, "guest": 0.00, "gnice": 0.00, "idle": 100.00},
						{"cpu": "12", "usr": 0.50, "nice": 0.00, "sys": 0.00, "iowait": 0.00, "irq": 0.00, "soft": 0.00, "steal": 0.00, "guest": 0.00, "gnice": 0.00, "idle": 99.50},
						{"cpu": "13", "usr": 0.00, "nice": 0.00, "sys": 0.00, "iowait": 0.00, "irq": 0.00, "soft": 0.00, "steal": 0.00, "guest": 0.00, "gnice": 0.00, "idle": 100.00},
						{"cpu": "14", "usr": 0.00, "nice": 0.00, "sys": 0.00, "iowait": 0.00, "irq": 0.00, "soft": 0.00, "steal": 0.00, "guest": 0.00, "gnice": 0.00, "idle": 100.00},
						{"cpu": "15", "usr": 0.00, "nice": 0.00, "sys": 0.00, "iowait": 0.00, "irq": 0.00, "soft": 0.00, "steal": 0.00, "guest": 0.00, "gnice": 0.00, "idle": 100.00}
					]
				},
				{
					"timestamp": "03:00:16 PM",
					"cpu-load": [
						{"cpu": "0", "usr": 0.00, "nice": 0.00, "sys": 0.00, "iowait": 0.00, "irq": 0.00, "soft": 0.00, "steal": 0.00, "guest": 0.00, "gnice": 0.00, "idle": 100.00},
						{"cpu": "1", "usr": 0.00, "nice": 0.00, "sys": 0.00, "iowait": 0.00, "irq": 0.00, "soft": 0.00, "steal": 0.00, "guest": 0.00, "gnice": 0.00, "idle": 100.00},
						{"cpu": "2", "usr": 0.00, "nice": 0.00, "sys": 0.00, "iowait": 0.00, "irq": 0.00, "soft": 0.52, "steal": 0.00, "guest": 0.00, "gnice": 0.00, "idle": 99.48},
						{"cpu": "3", "usr": 0.00, "nice": 0.00, "sys": 0.00, "iowait": 0.00, "irq": 0.00, "soft": 27.97, "steal": 0.00, "guest": 0.00, "gnice": 0.00, "idle": 72.03},
						{"cpu": "4", "usr": 0.00, "nice": 0.00, "sys": 0.00, "iowait": 0.00, "irq": 0.00, "soft": 0.00, "steal": 0.00, "guest": 0.00, "gnice": 0.00, "idle": 100.00},
						{"cpu": "5", "usr": 0.00, "nice": 0.00, "sys": 0.00, "iowait": 0.00, "irq": 0.00, "soft": 0.00, "steal": 0.00, "guest": 0.00, "gnice": 0.00, "idle": 100.00},
						{"cpu": "6", "usr": 0.00, "nice": 0.00, "sys": 0.00, "iowait": 0.00, "irq": 0.00, "soft": 0.00, "steal": 0.00, "guest": 0.00, "gnice": 0.00, "idle": 100.00},
						{"cpu": "7", "usr": 0.00, "nice": 0.00, "sys": 0.00, "iowait": 0.00, "irq": 0.00, "soft": 0.00, "steal": 0.00, "guest": 0.00, "gnice": 0.00, "idle": 100.00},
						{"cpu": "8", "usr": 0.00, "nice": 0.00, "sys": 0.00, "iowait": 0.00, "irq": 0.00, "soft": 0.00, "steal": 0.00, "guest": 0.00, "gnice": 0.00, "idle": 100.00},
						{"cpu": "9", "usr": 0.00, "nice": 0.00, "sys": 0.00, "iowait": 0.00, "irq": 0.00, "soft": 0.00, "steal": 0.00, "guest": 0.00, "gnice": 0.00, "idle": 100.00},
						{"cpu": "10", "usr": 0.50, "nice": 0.00, "sys": 99.50, "iowait": 0.00, "irq": 0.00, "soft": 0.00, "steal": 0.00, "guest": 0.00, "gnice": 0.00, "idle": 0.00},
						{"cpu": "11", "usr": 0.00, "nice": 0.00, "sys": 0.00, "iowait": 0.00, "irq": 0.00, "soft": 0.00, "steal": 0.00, "guest": 0.00, "gnice": 0.00, "idle": 100.00},
						{"cpu": "12", "usr": 0.00, "nice": 0.00, "sys": 0.50, "iowait": 0.00, "irq": 0.00, "soft": 0.00, "steal": 0.00, "guest": 0.00, "gnice": 0.00, "idle": 99.50},
						{"cpu": "13", "usr": 0.00, "nice": 0.00, "sys": 0.00, "iowait": 0.00, "irq": 0.00, "soft": 0.00, "steal": 0.00, "guest": 0.00, "gnice": 0.00, "idle": 100.00},
						{"cpu": "14", "usr": 0.00, "nice": 0.00, "sys": 0.00, "iowait": 0.00, "irq": 0.00, "soft": 0.00, "steal": 0.00, "guest": 0.00, "gnice": 0.00, "idle": 100.00},
						{"cpu": "15", "usr": 0.00, "nice": 0.00, "sys": 0.00, "iowait": 0.00, "irq": 0.00, "soft": 0.00, "steal": 0.00, "guest": 0.00, "gnice": 0.00, "idle": 100.00}
					]
				},
				{
					"timestamp": "03:00:18 PM",
					"cpu-load": [
						{"cpu": "0", "usr": 0.00, "nice": 0.00, "sys": 0.00, "iowait": 0.00, "irq": 0.00, "soft": 0.00, "steal": 0.00, "guest": 0.00, "gnice": 0.00, "idle": 100.00},
						{"cpu": "1", "usr": 0.00, "nice": 0.00, "sys": 0.00, "iowait": 0.00, "irq": 0.00, "soft": 0.00, "steal": 0.00, "guest": 0.00, "gnice": 0.00, "idle": 100.00},
						{"cpu": "2", "usr": 0.00, "nice": 0.00, "sys": 0.00, "iowait": 0.00, "irq": 0.00, "soft": 1.03, "steal": 0.00, "guest": 0.00, "gnice": 0.00, "idle": 98.97},
						{"cpu": "3", "usr": 0.00, "nice": 0.00, "sys": 0.00, "iowait": 0.00, "irq": 0.00, "soft": 27.59, "steal": 0.00, "guest": 0.00, "gnice": 0.00, "idle": 72.41},
						{"cpu": "4", "usr": 0.00, "nice": 0.00, "sys": 0.00, "iowait": 0.00, "irq": 0.00, "soft": 0.00, "steal": 0.00, "guest": 0.00, "gnice": 0.00, "idle": 100.00},
						{"cpu": "5", "usr": 0.00, "nice": 0.00, "sys": 0.00, "iowait": 0.00, "irq": 0.00, "soft": 0.00, "steal": 0.00, "guest": 0.00, "gnice": 0.00, "idle": 100.00},
						{"cpu": "6", "usr": 0.00, "nice": 0.00, "sys": 0.00, "iowait": 0.00, "irq": 0.00, "soft": 0.00, "steal": 0.00, "guest": 0.00, "gnice": 0.00, "idle": 100.00},
						{"cpu": "7", "usr": 0.00, "nice": 0.00, "sys": 0.00, "iowait": 0.00, "irq": 0.00, "soft": 0.00, "steal": 0.00, "guest": 0.00, "gnice": 0.00, "idle": 100.00},
						{"cpu": "8", "usr": 0.00, "nice": 0.00, "sys": 0.00, "iowait": 0.00, "irq": 0.00, "soft": 0.00, "steal": 0.00, "guest": 0.00, "gnice": 0.00, "idle": 100.00},
						{"cpu": "9", "usr": 0.00, "nice": 0.00, "sys": 0.00, "iowait": 0.00, "irq": 0.00, "soft": 0.00, "steal": 0.00, "guest": 0.00, "gnice": 0.00, "idle": 100.00},
						{"cpu": "10", "usr": 1.00, "nice": 0.00, "sys": 99.00, "iowait": 0.00, "irq": 0.00, "soft": 0.00, "steal": 0.00, "guest": 0.00, "gnice": 0.00, "idle": 0.00},
						{"cpu": "11", "usr": 0.00, "nice": 0.00, "sys": 0.00, "iowait": 0.00, "irq": 0.00, "soft": 0.00, "steal": 0.00, "guest": 0.00, "gnice": 0.00, "idle": 100.00},
						{"cpu": "12", "usr": 0.50, "nice": 0.00, "sys": 0.00, "iowait": 0.00, "irq": 0.00, "soft": 0.00, "steal": 0.00, "guest": 0.00, "gnice": 0.00, "idle": 99.50},
						{"cpu": "13", "usr": 0.00, "nice": 0.00, "sys": 0.00, "iowait": 0.00, "irq": 0.00, "soft": 0.00, "steal": 0.00, "guest": 0.00, "gnice": 0.00, "idle": 100.00},
						{"cpu": "14", "usr": 0.00, "nice": 0.00, "sys": 0.00, "iowait": 0.00, "irq": 0.00, "soft": 0.00, "steal": 0.00, "guest": 0.00, "gnice": 0.00, "idle": 100.00},
						{"cpu": "15", "usr": 0.00, "nice": 0.00, "sys": 0.00, "iowait": 0.00, "irq": 0.00, "soft": 0.00, "steal": 0.00, "guest": 0.00, "gnice": 0.00, "idle": 100.00}
					]
				},
				{
					"timestamp": "03:00:20 PM",
					"cpu-load": [
						{"cpu": "0", "usr": 0.00, "nice": 0.00, "sys": 0.00, "iowait": 0.00, "irq": 0.00, "soft": 0.00, "steal": 0.00, "guest": 0.00, "gnice": 0.00, "idle": 100.00},
						{"cpu": "1", "usr": 0.00, "nice": 0.00, "sys": 0.00, "iowait": 0.00, "irq": 0.00, "soft": 0.00, "steal": 0.00, "guest": 0.00, "gnice": 0.00, "idle": 100.00},
						{"cpu": "2", "usr": 0.00, "nice": 0.00, "sys": 0.00, "iowait": 0.00, "irq": 0.00, "soft": 0.52, "steal": 0.00, "guest": 0.00, "gnice": 0.00, "idle": 99.48},
						{"cpu": "3", "usr": 0.00, "nice": 0.00, "sys": 0.00, "iowait": 0.00, "irq": 0.00, "soft": 25.86, "steal": 0.00, "guest": 0.00, "gnice": 0.00, "idle": 74.14},
						{"cpu": "4", "usr": 0.00, "nice": 0.00, "sys": 0.00, "iowait": 0.00, "irq": 0.00, "soft": 0.00, "steal": 0.00, "guest": 0.00, "gnice": 0.00, "idle": 100.00},
						{"cpu": "5", "usr": 0.00, "nice": 0.00, "sys": 0.00, "iowait": 0.00, "irq": 0.00, "soft": 0.00, "steal": 0.00, "guest": 0.00, "gnice": 0.00, "idle": 100.00},
						{"cpu": "6", "usr": 0.00, "nice": 0.00, "sys": 0.00, "iowait": 0.00, "irq": 0.00, "soft": 0.00, "steal": 0.00, "guest": 0.00, "gnice": 0.00, "idle": 100.00},
						{"cpu": "7", "usr": 0.00, "nice": 0.00, "sys": 0.00, "iowait": 0.00, "irq": 0.00, "soft": 0.00, "steal": 0.00, "guest": 0.00, "gnice": 0.00, "idle": 100.00},
						{"cpu": "8", "usr": 0.00, "nice": 0.00, "sys": 0.00, "iowait": 0.00, "irq": 0.00, "soft": 0.00, "steal": 0.00, "guest": 0.00, "gnice": 0.00, "idle": 100.00},
						{"cpu": "9", "usr": 0.00, "nice": 0.00, "sys": 0.00, "iowait": 0.00, "irq": 0.00, "soft": 0.00, "steal": 0.00, "guest": 0.00, "gnice": 0.00, "idle": 100.00},
						{"cpu": "10", "usr": 1.00, "nice": 0.00, "sys": 99.00, "iowait": 0.00, "irq": 0.00, "soft": 0.00, "steal": 0.00, "guest": 0.00, "gnice": 0.00, "idle": 0.00},
						{"cpu": "11", "usr": 0.00, "nice": 0.00, "sys": 0.00, "iowait": 0.00, "irq": 0.00, "soft": 0.00, "steal": 0.00, "guest": 0.00, "gnice": 0.00, "idle": 100.00},
						{"cpu": "12", "usr": 0.00, "nice": 0.00, "sys": 0.50, "iowait": 0.00, "irq": 0.00, "soft": 0.00, "steal": 0.00, "guest": 0.00, "gnice": 0.00, "idle": 99.50},
						{"cpu": "13", "usr": 0.00, "nice": 0.00, "sys": 0.00, "iowait": 0.00, "irq": 0.00, "soft": 0.00, "steal": 0.00, "guest": 0.00, "gnice": 0.00, "idle": 100.00},
						{"cpu": "14", "usr": 0.00, "nice": 0.00, "sys": 0.00, "iowait": 0.00, "irq": 0.00, "soft": 0.00, "steal": 0.00, "guest": 0.00, "gnice": 0.00, "idle": 100.00},
						{"cpu": "15", "usr": 0.00, "nice": 0.00, "sys": 0.00, "iowait": 0.00, "irq": 0.00, "soft": 0.00, "steal": 0.00, "guest": 0.00, "gnice": 0.00, "idle": 100.00}
					]
				},
				{
					"timestamp": "03:00:22 PM",
					"cpu-load": [
						{"cpu": "0", "usr": 0.00, "nice": 0.00, "sys": 0.00, "iowait": 0.00, "irq": 0.00, "soft": 0.50, "steal": 0.00, "guest": 0.00, "gnice": 0.00, "idle": 99.50},
						{"cpu": "1", "usr": 0.00, "nice": 0.00, "sys": 0.00, "iowait": 0.00, "irq": 0.00, "soft": 0.00, "steal": 0.00, "guest": 0.00, "gnice": 0.00, "idle": 100.00},
						{"cpu": "2", "usr": 0.00, "nice": 0.00, "sys": 0.00, "iowait": 0.00, "irq": 0.00, "soft": 0.00, "steal": 0.00, "guest": 0.00, "gnice": 0.00, "idle": 100.00},
						{"cpu": "3", "usr": 0.00, "nice": 0.00, "sys": 0.00, "iowait": 0.00, "irq": 0.00, "soft": 27.97, "steal": 0.00, "guest": 0.00, "gnice": 0.00, "idle": 72.03},
						{"cpu": "4", "usr": 0.00, "nice": 0.00, "sys": 0.00, "iowait": 0.00, "irq": 0.00, "soft": 0.00, "steal": 0.00, "guest": 0.00, "gnice": 0.00, "idle": 100.00},
						{"cpu": "5", "usr": 0.00, "nice": 0.00, "sys": 0.00, "iowait": 0.00, "irq": 0.00, "soft": 0.00, "steal": 0.00, "guest": 0.00, "gnice": 0.00, "idle": 100.00},
						{"cpu": "6", "usr": 0.00, "nice": 0.00, "sys": 0.00, "iowait": 0.00, "irq": 0.00, "soft": 0.00, "steal": 0.00, "guest": 0.00, "gnice": 0.00, "idle": 100.00},
						{"cpu": "7", "usr": 0.00, "nice": 0.00, "sys": 0.00, "iowait": 0.00, "irq": 0.00, "soft": 0.00, "steal": 0.00, "guest": 0.00, "gnice": 0.00, "idle": 100.00},
						{"cpu": "8", "usr": 0.00, "nice": 0.00, "sys": 0.00, "iowait": 0.00, "irq": 0.00, "soft": 0.00, "steal": 0.00, "guest": 0.00, "gnice": 0.00, "idle": 100.00},
						{"cpu": "9", "usr": 0.00, "nice": 0.00, "sys": 0.00, "iowait": 0.00, "irq": 0.00, "soft": 0.00, "steal": 0.00, "guest": 0.00, "gnice": 0.00, "idle": 100.00},
						{"cpu": "10", "usr": 0.50, "nice": 0.00, "sys": 99.50, "iowait": 0.00, "irq": 0.00, "soft": 0.00, "steal": 0.00, "guest": 0.00, "gnice": 0.00, "idle": 0.00},
						{"cpu": "11", "usr": 0.00, "nice": 0.00, "sys": 0.00, "iowait": 0.00, "irq": 0.00, "soft": 0.00, "steal": 0.00, "guest": 0.00, "gnice": 0.00, "idle": 100.00},
						{"cpu": "12", "usr": 0.50, "nice": 0.00, "sys": 0.50, "iowait": 0.00, "irq": 0.00, "soft": 0.00, "steal": 0.00, "guest": 0.00, "gnice": 0.00, "idle": 99.00},
						{"cpu": "13", "usr": 0.00, "nice": 0.00, "sys": 0.00, "iowait": 0.00, "irq": 0.00, "soft": 0.00, "steal": 0.00, "guest": 0.00, "gnice": 0.00, "idle": 100.00},
						{"cpu": "14", "usr": 0.00, "nice": 0.00, "sys": 0.00, "iowait": 0.00, "irq": 0.00, "soft": 0.00, "steal": 0.00, "guest": 0.00, "gnice": 0.00, "idle": 100.00},
						{"cpu": "15", "usr": 0.50, "nice": 0.00, "sys": 0.00, "iowait": 0.00, "irq": 0.00, "soft": 0.00, "steal": 0.00, "guest": 0.00, "gnice": 0.00, "idle": 99.50}
					]
				},
				{
					"timestamp": "03:00:24 PM",
					"cpu-load": [
						{"cpu": "0", "usr": 0.00, "nice": 0.00, "sys": 0.00, "iowait": 0.00, "irq": 0.00, "soft": 0.00, "steal": 0.00, "guest": 0.00, "gnice": 0.00, "idle": 100.00},
						{"cpu": "1", "usr": 0.00, "nice": 0.00, "sys": 0.00, "iowait": 0.00, "irq": 0.00, "soft": 0.00, "steal": 0.00, "guest": 0.00, "gnice": 0.00, "idle": 100.00},
						{"cpu": "2", "usr": 0.00, "nice": 0.00, "sys": 0.00, "iowait": 0.00, "irq": 0.00, "soft": 0.52, "steal": 0.00, "guest": 0.00, "gnice": 0.00, "idle": 99.48},
						{"cpu": "3", "usr": 0.00, "nice": 0.00, "sys": 0.88, "iowait": 0.00, "irq": 0.00, "soft": 23.89, "steal": 0.00, "guest": 0.00, "gnice": 0.00, "idle": 75.22},
						{"cpu": "4", "usr": 0.00, "nice": 0.00, "sys": 0.00, "iowait": 0.00, "irq": 0.00, "soft": 0.00, "steal": 0.00, "guest": 0.00, "gnice": 0.00, "idle": 100.00},
						{"cpu": "5", "usr": 0.00, "nice": 0.00, "sys": 0.00, "iowait": 0.00, "irq": 0.00, "soft": 0.00, "steal": 0.00, "guest": 0.00, "gnice": 0.00, "idle": 100.00},
						{"cpu": "6", "usr": 0.00, "nice": 0.00, "sys": 0.00, "iowait": 0.00, "irq": 0.00, "soft": 0.00, "steal": 0.00, "guest": 0.00, "gnice": 0.00, "idle": 100.00},
						{"cpu": "7", "usr": 0.00, "nice": 0.00, "sys": 0.00, "iowait": 0.00, "irq": 0.00, "soft": 0.00, "steal": 0.00, "guest": 0.00, "gnice": 0.00, "idle": 100.00},
						{"cpu": "8", "usr": 0.00, "nice": 0.00, "sys": 0.00, "iowait": 0.00, "irq": 0.00, "soft": 0.00, "steal": 0.00, "guest": 0.00, "gnice": 0.00, "idle": 100.00},
						{"cpu": "9", "usr": 0.00, "nice": 0.00, "sys": 0.00, "iowait": 0.00, "irq": 0.00, "soft": 0.00, "steal": 0.00, "guest": 0.00, "gnice": 0.00, "idle": 100.00},
						{"cpu": "10", "usr": 1.00, "nice": 0.00, "sys": 99.00, "iowait": 0.00, "irq": 0.00, "soft": 0.00, "steal": 0.00, "guest": 0.00, "gnice": 0.00, "idle": 0.00},
						{"cpu": "11", "usr": 0.00, "nice": 0.00, "sys": 0.00, "iowait": 0.00, "irq": 0.00, "soft": 0.00, "steal": 0.00, "guest": 0.00, "gnice": 0.00, "idle": 100.00},
						{"cpu": "12", "usr": 0.50, "nice": 0.00, "sys": 0.50, "iowait": 0.00, "irq": 0.00, "soft": 0.00, "steal": 0.00, "guest": 0.00, "gnice": 0.00, "idle": 99.00},
						{"cpu": "13", "usr": 0.00, "nice": 0.00, "sys": 0.00, "iowait": 0.00, "irq": 0.00, "soft": 0.00, "steal": 0.00, "guest": 0.00, "gnice": 0.00, "idle": 100.00},
						{"cpu": "14", "usr": 0.00, "nice": 0.00, "sys": 0.00, "iowait": 0.00, "irq": 0.00, "soft": 0.00, "steal": 0.00, "guest": 0.00, "gnice": 0.00, "idle": 100.00},
						{"cpu": "15", "usr": 0.00, "nice": 0.00, "sys": 0.50, "iowait": 0.00, "irq": 0.00, "soft": 0.00, "steal": 0.00, "guest": 0.00, "gnice": 0.00, "idle": 99.50}
					]
				},
				{
					"timestamp": "03:00:26 PM",
					"cpu-load": [
						{"cpu": "0", "usr": 0.00, "nice": 0.00, "sys": 0.00, "iowait": 0.00, "irq": 0.00, "soft": 0.00, "steal": 0.00, "guest": 0.00, "gnice": 0.00, "idle": 100.00},
						{"cpu": "1", "usr": 0.00, "nice": 0.00, "sys": 0.00, "iowait": 0.00, "irq": 0.00, "soft": 0.00, "steal": 0.00, "guest": 0.00, "gnice": 0.00, "idle": 100.00},
						{"cpu": "2", "usr": 0.00, "nice": 0.00, "sys": 0.52, "iowait": 0.00, "irq": 0.00, "soft": 0.52, "steal": 0.00, "guest": 0.00, "gnice": 0.00, "idle": 98.97},
						{"cpu": "3", "usr": 0.00, "nice": 0.00, "sys": 0.00, "iowait": 0.00, "irq": 0.00, "soft": 27.97, "steal": 0.00, "guest": 0.00, "gnice": 0.00, "idle": 72.03},
						{"cpu": "4", "usr": 0.00, "nice": 0.00, "sys": 0.00, "iowait": 0.00, "irq": 0.00, "soft": 0.00, "steal": 0.00, "guest": 0.00, "gnice": 0.00, "idle": 100.00},
						{"cpu": "5", "usr": 0.00, "nice": 0.00, "sys": 0.00, "iowait": 0.00, "irq": 0.00, "soft": 0.00, "steal": 0.00, "guest": 0.00, "gnice": 0.00, "idle": 100.00},
						{"cpu": "6", "usr": 0.00, "nice": 0.00, "sys": 0.00, "iowait": 0.00, "irq": 0.00, "soft": 0.00, "steal": 0.00, "guest": 0.00, "gnice": 0.00, "idle": 100.00},
						{"cpu": "7", "usr": 0.00, "nice": 0.00, "sys": 0.00, "iowait": 0.00, "irq": 0.00, "soft": 0.00, "steal": 0.00, "guest": 0.00, "gnice": 0.00, "idle": 100.00},
						{"cpu": "8", "usr": 0.00, "nice": 0.00, "sys": 0.00, "iowait": 0.00, "irq": 0.00, "soft": 0.00, "steal": 0.00, "guest": 0.00, "gnice": 0.00, "idle": 100.00},
						{"cpu": "9", "usr": 0.00, "nice": 0.00, "sys": 0.00, "iowait": 0.00, "irq": 0.00, "soft": 0.00, "steal": 0.00, "guest": 0.00, "gnice": 0.00, "idle": 100.00},
						{"cpu": "10", "usr": 1.00, "nice": 0.00, "sys": 99.00, "iowait": 0.00, "irq": 0.00, "soft": 0.00, "steal": 0.00, "guest": 0.00, "gnice": 0.00, "idle": 0.00},
						{"cpu": "11", "usr": 0.00, "nice": 0.00, "sys": 0.00, "iowait": 0.00, "irq": 0.00, "soft": 0.00, "steal": 0.00, "guest": 0.00, "gnice": 0.00, "idle": 100.00},
						{"cpu": "12", "usr": 0.00, "nice": 0.00, "sys": 0.50, "iowait": 0.00, "irq": 0.00, "soft": 0.00, "steal": 0.00, "guest": 0.00, "gnice": 0.00, "idle": 99.50},
						{"cpu": "13", "usr": 0.00, "nice": 0.00, "sys": 0.00, "iowait": 0.00, "irq": 0.00, "soft": 0.00, "steal": 0.00, "guest": 0.00, "gnice": 0.00, "idle": 100.00},
						{"cpu": "14", "usr": 0.00, "nice": 0.00, "sys": 0.00, "iowait": 0.00, "irq": 0.00, "soft": 0.00, "steal": 0.00, "guest": 0.00, "gnice": 0.00, "idle": 100.00},
						{"cpu": "15", "usr": 0.00, "nice": 0.00, "sys": 0.00, "iowait": 0.00, "irq": 0.00, "soft": 0.00, "steal": 0.00, "guest": 0.00, "gnice": 0.00, "idle": 100.00}
					]
				},
				{
					"timestamp": "03:00:28 PM",
					"cpu-load": [
						{"cpu": "0", "usr": 0.00, "nice": 0.00, "sys": 0.00, "iowait": 0.00, "irq": 0.00, "soft": 0.50, "steal": 0.00, "guest": 0.00, "gnice": 0.00, "idle": 99.50},
						{"cpu": "1", "usr": 0.00, "nice": 0.00, "sys": 0.00, "iowait": 0.00, "irq": 0.00, "soft": 0.00, "steal": 0.00, "guest": 0.00, "gnice": 0.00, "idle": 100.00},
						{"cpu": "2", "usr": 0.00, "nice": 0.00, "sys": 0.00, "iowait": 0.00, "irq": 0.00, "soft": 0.00, "steal": 0.00, "guest": 0.00, "gnice": 0.00, "idle": 100.00},
						{"cpu": "3", "usr": 0.00, "nice": 0.00, "sys": 0.00, "iowait": 0.00, "irq": 0.00, "soft": 26.50, "steal": 0.00, "guest": 0.00, "gnice": 0.00, "idle": 73.50},
						{"cpu": "4", "usr": 0.00, "nice": 0.00, "sys": 0.00, "iowait": 0.00, "irq": 0.00, "soft": 0.00, "steal": 0.00, "guest": 0.00, "gnice": 0.00, "idle": 100.00},
						{"cpu": "5", "usr": 0.00, "nice": 0.00, "sys": 0.00, "iowait": 0.00, "irq": 0.00, "soft": 0.00, "steal": 0.00, "guest": 0.00, "gnice": 0.00, "idle": 100.00},
						{"cpu": "6", "usr": 0.00, "nice": 0.00, "sys": 0.00, "iowait": 0.00, "irq": 0.00, "soft": 0.00, "steal": 0.00, "guest": 0.00, "gnice": 0.00, "idle": 100.00},
						{"cpu": "7", "usr": 0.00, "nice": 0.00, "sys": 0.00, "iowait": 0.00, "irq": 0.00, "soft": 0.00, "steal": 0.00, "guest": 0.00, "gnice": 0.00, "idle": 100.00},
						{"cpu": "8", "usr": 0.00, "nice": 0.00, "sys": 0.00, "iowait": 0.00, "irq": 0.00, "soft": 0.00, "steal": 0.00, "guest": 0.00, "gnice": 0.00, "idle": 100.00},
						{"cpu": "9", "usr": 0.00, "nice": 0.00, "sys": 0.00, "iowait": 0.00, "irq": 0.00, "soft": 0.00, "steal": 0.00, "guest": 0.00, "gnice": 0.00, "idle": 100.00},
						{"cpu": "10", "usr": 0.50, "nice": 0.00, "sys": 99.50, "iowait": 0.00, "irq": 0.00, "soft": 0.00, "steal": 0.00, "guest": 0.00, "gnice": 0.00, "idle": 0.00},
						{"cpu": "11", "usr": 0.00, "nice": 0.00, "sys": 0.00, "iowait": 0.00, "irq": 0.00, "soft": 0.00, "steal": 0.00, "guest": 0.00, "gnice": 0.00, "idle": 100.00},
						{"cpu": "12", "usr": 0.50, "nice": 0.00, "sys": 0.50, "iowait": 0.00, "irq": 0.00, "soft": 0.00, "steal": 0.00, "guest": 0.00, "gnice": 0.00, "idle": 99.00},
						{"cpu": "13", "usr": 0.00, "nice": 0.00, "sys": 0.00, "iowait": 0.00, "irq": 0.00, "soft": 0.00, "steal": 0.00, "guest": 0.00, "gnice": 0.00, "idle": 100.00},
						{"cpu": "14", "usr": 0.00, "nice": 0.00, "sys": 0.00, "iowait": 0.00, "irq": 0.00, "soft": 0.00, "steal": 0.00, "guest": 0.00, "gnice": 0.00, "idle": 100.00},
						{"cpu": "15", "usr": 0.00, "nice": 0.00, "sys": 0.00, "iowait": 0.00, "irq": 0.00, "soft": 0.00, "steal": 0.00, "guest": 0.00, "gnice": 0.00, "idle": 100.00}
					]
				}
			]
		}
	]
}}
