{"sysstat": {
	"hosts": [
		{
			"nodename": "lbnl-dtn2.testbed100.es.net",
			"sysname": "Linux",
			"release": "5.15.0-117-generic",
			"machine": "x86_64",
			"number-of-cpus": 32,
			"date": "07/29/2024",
			"statistics": [
				{
					"timestamp": "09:59:02 PM",
					"cpu-load": [
						{"cpu": "0", "usr": 0.00, "nice": 0.00, "sys": 0.00, "iowait": 0.00, "irq": 0.00, "soft": 0.00, "steal": 0.00, "guest": 0.00, "gnice": 0.00, "idle": 100.00},
						{"cpu": "1", "usr": 0.00, "nice": 0.00, "sys": 0.00, "iowait": 0.00, "irq": 0.00, "soft": 0.00, "steal": 0.00, "guest": 0.00, "gnice": 0.00, "idle": 100.00},
						{"cpu": "2", "usr": 0.00, "nice": 0.00, "sys": 0.00, "iowait": 0.00, "irq": 0.00, "soft": 0.00, "steal": 0.00, "guest": 0.00, "gnice": 0.00, "idle": 100.00},
						{"cpu": "3", "usr": 0.00, "nice": 0.00, "sys": 0.00, "iowait": 0.00, "irq": 0.00, "soft": 0.00, "steal": 0.00, "guest": 0.00, "gnice": 0.00, "idle": 100.00},
						{"cpu": "4", "usr": 0.00, "nice": 0.00, "sys": 0.00, "iowait": 0.00, "irq": 0.00, "soft": 0.00, "steal": 0.00, "guest": 0.00, "gnice": 0.00, "idle": 100.00},
						{"cpu": "5", "usr": 0.00, "nice": 0.00, "sys": 0.00, "iowait": 0.00, "irq": 0.00, "soft": 0.00, "steal": 0.00, "guest": 0.00, "gnice": 0.00, "idle": 100.00},
						{"cpu": "6", "usr": 0.00, "nice": 0.00, "sys": 0.00, "iowait": 0.00, "irq": 0.00, "soft": 0.00, "steal": 0.00, "guest": 0.00, "gnice": 0.00, "idle": 100.00},
						{"cpu": "7", "usr": 0.00, "nice": 0.00, "sys": 0.00, "iowait": 0.00, "irq": 0.00, "soft": 0.00, "steal": 0.00, "guest": 0.00, "gnice": 0.00, "idle": 100.00},
						{"cpu": "8", "usr": 0.00, "nice": 0.00, "sys": 0.00, "iowait": 0.00, "irq": 0.00, "soft": 0.00, "steal": 0.00, "guest": 0.00, "gnice": 0.00, "idle": 100.00},
						{"cpu": "9", "usr": 0.00, "nice": 0.00, "sys": 0.00, "iowait": 0.00, "irq": 0.00, "soft": 0.00, "steal": 0.00, "guest": 0.00, "gnice": 0.00, "idle": 100.00},
						{"cpu": "10", "usr": 0.00, "nice": 0.00, "sys": 0.00, "iowait": 0.00, "irq": 0.00, "soft": 0.00, "steal": 0.00, "guest": 0.00, "gnice": 0.00, "idle": 100.00},
						{"cpu": "11", "usr": 0.00, "nice": 0.00, "sys": 0.00, "iowait": 0.00, "irq": 0.00, "soft": 0.00, "steal": 0.00, "guest": 0.00, "gnice": 0.00, "idle": 100.00},
						{"cpu": "12", "usr": 0.00, "nice": 0.00, "sys": 0.00, "iowait": 0.00, "irq": 0.00, "soft": 0.00, "steal": 0.00, "guest": 0.00, "gnice": 0.00, "idle": 100.00},
						{"cpu": "13", "usr": 0.00, "nice": 0.00, "sys": 0.00, "iowait": 0.00, "irq": 0.00, "soft": 0.00, "steal": 0.00, "guest": 0.00, "gnice": 0.00, "idle": 100.00},
						{"cpu": "14", "usr": 0.00, "nice": 0.00, "sys": 0.00, "iowait": 0.00, "irq": 0.00, "soft": 0.00, "steal": 0.00, "guest": 0.00, "gnice": 0.00, "idle": 100.00},
						{"cpu": "15", "usr": 0.00, "nice": 0.00, "sys": 0.00, "iowait": 0.00, "irq": 0.00, "soft": 0.00, "steal": 0.00, "guest": 0.00, "gnice": 0.00, "idle": 100.00}
					]
				},
				{
					"timestamp": "09:59:04 PM",
					"cpu-load": [
						{"cpu": "0", "usr": 0.00, "nice": 0.00, "sys": 0.00, "iowait": 0.00, "irq": 0.00, "soft": 0.00, "steal": 0.00, "guest": 0.00, "gnice": 0.00, "idle": 100.00},
						{"cpu": "1", "usr": 0.00, "nice": 0.00, "sys": 0.00, "iowait": 0.00, "irq": 0.00, "soft": 0.00, "steal": 0.00, "guest": 0.00, "gnice": 0.00, "idle": 100.00},
						{"cpu": "2", "usr": 0.00, "nice": 0.00, "sys": 0.00, "iowait": 0.00, "irq": 0.00, "soft": 0.00, "steal": 0.00, "guest": 0.00, "gnice": 0.00, "idle": 100.00},
						{"cpu": "3", "usr": 0.00, "nice": 0.00, "sys": 0.00, "iowait": 0.00, "irq": 0.00, "soft": 0.00, "steal": 0.00, "guest": 0.00, "gnice": 0.00, "idle": 100.00},
						{"cpu": "4", "usr": 0.00, "nice": 0.00, "sys": 0.00, "iowait": 0.00, "irq": 0.00, "soft": 0.00, "steal": 0.00, "guest": 0.00, "gnice": 0.00, "idle": 100.00},
						{"cpu": "5", "usr": 0.00, "nice": 0.00, "sys": 0.00, "iowait": 0.00, "irq": 0.00, "soft": 0.00, "steal": 0.00, "guest": 0.00, "gnice": 0.00, "idle": 100.00},
						{"cpu": "6", "usr": 0.00, "nice": 0.00, "sys": 0.00, "iowait": 0.00, "irq": 0.00, "soft": 0.00, "steal": 0.00, "guest": 0.00, "gnice": 0.00, "idle": 100.00},
						{"cpu": "7", "usr": 0.00, "nice": 0.00, "sys": 0.00, "iowait": 0.00, "irq": 0.00, "soft": 0.00, "steal": 0.00, "guest": 0.00, "gnice": 0.00, "idle": 100.00},
						{"cpu": "8", "usr": 0.00, "nice": 0.00, "sys": 0.00, "iowait": 0.00, "irq": 0.00, "soft": 0.00, "steal": 0.00, "guest": 0.00, "gnice": 0.00, "idle": 100.00},
						{"cpu": "9", "usr": 0.00, "nice": 0.00, "sys": 0.00, "iowait": 0.00, "irq": 0.00, "soft": 0.00, "steal": 0.00, "guest": 0.00, "gnice": 0.00, "idle": 100.00},
						{"cpu": "10", "usr": 0.00, "nice": 0.00, "sys": 0.00, "iowait": 0.00, "irq": 0.00, "soft": 0.00, "steal": 0.00, "guest": 0.00, "gnice": 0.00, "idle": 100.00},
						{"cpu": "11", "usr": 0.00, "nice": 0.00, "sys": 0.00, "iowait": 0.00, "irq": 0.00, "soft": 0.00, "steal": 0.00, "guest": 0.00, "gnice": 0.00, "idle": 100.00},
						{"cpu": "12", "usr": 0.00, "nice": 0.00, "sys": 0.00, "iowait": 0.00, "irq": 0.00, "soft": 0.00, "steal": 0.00, "guest": 0.00, "gnice": 0.00, "idle": 100.00},
						{"cpu": "13", "usr": 0.00, "nice": 0.00, "sys": 0.00, "iowait": 0.00, "irq": 0.00, "soft": 0.00, "steal": 0.00, "guest": 0.00, "gnice": 0.00, "idle": 100.00},
						{"cpu": "14", "usr": 0.00, "nice": 0.00, "sys": 0.00, "iowait": 0.00, "irq": 0.00, "soft": 0.00, "steal": 0.00, "guest": 0.00, "gnice": 0.00, "idle": 100.00},
						{"cpu": "15", "usr": 0.00, "nice": 0.00, "sys": 0.00, "iowait": 0.00, "irq": 0.00, "soft": 0.00, "steal": 0.00, "guest": 0.00, "gnice": 0.00, "idle": 100.00}
					]
				},
				{
					"timestamp": "09:59:06 PM",
					"cpu-load": [
						{"cpu": "0", "usr": 0.00, "nice": 0.00, "sys": 0.00, "iowait": 0.00, "irq": 0.00, "soft": 0.00, "steal": 0.00, "guest": 0.00, "gnice": 0.00, "idle": 100.00},
						{"cpu": "1", "usr": 0.00, "nice": 0.00, "sys": 0.00, "iowait": 0.00, "irq": 0.00, "soft": 0.00, "steal": 0.00, "guest": 0.00, "gnice": 0.00, "idle": 100.00},
						{"cpu": "2", "usr": 0.00, "nice": 0.00, "sys": 0.00, "iowait": 0.00, "irq": 0.00, "soft": 0.00, "steal": 0.00, "guest": 0.00, "gnice": 0.00, "idle": 100.00},
						{"cpu": "3", "usr": 0.00, "nice": 0.00, "sys": 0.00, "iowait": 0.00, "irq": 0.00, "soft": 0.00, "steal": 0.00, "guest": 0.00, "gnice": 0.00, "idle": 100.00},
						{"cpu": "4", "usr": 0.00, "nice": 0.00, "sys": 0.00, "iowait": 0.00, "irq": 0.00, "soft": 0.00, "steal": 0.00, "guest": 0.00, "gnice": 0.00, "idle": 100.00},
						{"cpu": "5", "usr": 0.00, "nice": 0.00, "sys": 0.00, "iowait": 0.00, "irq": 0.00, "soft": 0.00, "steal": 0.00, "guest": 0.00, "gnice": 0.00, "idle": 100.00},
						{"cpu": "6", "usr": 0.00, "nice": 0.00, "sys": 0.00, "iowait": 0.00, "irq": 0.00, "soft": 0.00, "steal": 0.00, "guest": 0.00, "gnice": 0.00, "idle": 100.00},
						{"cpu": "7", "usr": 0.00, "nice": 0.00, "sys": 0.00, "iowait": 0.00, "irq": 0.00, "soft": 0.00, "steal": 0.00, "guest": 0.00, "gnice": 0.00, "idle": 100.00},
						{"cpu": "8", "usr": 0.00, "nice": 0.00, "sys": 0.00, "iowait": 0.00, "irq": 0.00, "soft": 0.00, "steal": 0.00, "guest": 0.00, "gnice": 0.00, "idle": 100.00},
						{"cpu": "9", "usr": 0.00, "nice": 0.00, "sys": 0.00, "iowait": 0.00, "irq": 0.00, "soft": 0.00, "steal": 0.00, "guest": 0.00, "gnice": 0.00, "idle": 100.00},
						{"cpu": "10", "usr": 0.00, "nice": 0.00, "sys": 0.00, "iowait": 0.00, "irq": 0.00, "soft": 0.00, "steal": 0.00, "guest": 0.00, "gnice": 0.00, "idle": 100.00},
						{"cpu": "11", "usr": 0.00, "nice": 0.00, "sys": 0.00, "iowait": 0.00, "irq": 0.00, "soft": 0.00, "steal": 0.00, "guest": 0.00, "gnice": 0.00, "idle": 100.00},
						{"cpu": "12", "usr": 0.00, "nice": 0.00, "sys": 0.00, "iowait": 0.00, "irq": 0.00, "soft": 0.00, "steal": 0.00, "guest": 0.00, "gnice": 0.00, "idle": 100.00},
						{"cpu": "13", "usr": 0.00, "nice": 0.00, "sys": 0.00, "iowait": 0.00, "irq": 0.00, "soft": 0.00, "steal": 0.00, "guest": 0.00, "gnice": 0.00, "idle": 100.00},
						{"cpu": "14", "usr": 0.00, "nice": 0.00, "sys": 0.00, "iowait": 0.00, "irq": 0.00, "soft": 0.00, "steal": 0.00, "guest": 0.00, "gnice": 0.00, "idle": 100.00},
						{"cpu": "15", "usr": 0.00, "nice": 0.00, "sys": 0.00, "iowait": 0.00, "irq": 0.00, "soft": 0.00, "steal": 0.00, "guest": 0.00, "gnice": 0.00, "idle": 100.00}
					]
				},
				{
					"timestamp": "09:59:08 PM",
					"cpu-load": [
						{"cpu": "0", "usr": 0.00, "nice": 0.00, "sys": 0.00, "iowait": 0.00, "irq": 0.00, "soft": 0.56, "steal": 0.00, "guest": 0.00, "gnice": 0.00, "idle": 99.44},
						{"cpu": "1", "usr": 0.00, "nice": 0.00, "sys": 0.00, "iowait": 0.00, "irq": 0.00, "soft": 0.00, "steal": 0.00, "guest": 0.00, "gnice": 0.00, "idle": 100.00},
						{"cpu": "2", "usr": 0.00, "nice": 0.00, "sys": 0.00, "iowait": 0.00, "irq": 0.00, "soft": 0.00, "steal": 0.00, "guest": 0.00, "gnice": 0.00, "idle": 100.00},
						{"cpu": "3", "usr": 0.00, "nice": 0.00, "sys": 0.00, "iowait": 0.00, "irq": 0.00, "soft": 0.00, "steal": 0.00, "guest": 0.00, "gnice": 0.00, "idle": 100.00},
						{"cpu": "4", "usr": 0.00, "nice": 0.00, "sys": 0.00, "iowait": 0.00, "irq": 0.00, "soft": 0.00, "steal": 0.00, "guest": 0.00, "gnice": 0.00, "idle": 100.00},
						{"cpu": "5", "usr": 0.00, "nice": 0.00, "sys": 0.00, "iowait": 0.00, "irq": 0.00, "soft": 0.00, "steal": 0.00, "guest": 0.00, "gnice": 0.00, "idle": 100.00},
						{"cpu": "6", "usr": 0.00, "nice": 0.00, "sys": 0.00, "iowait": 0.00, "irq": 0.00, "soft": 0.00, "steal": 0.00, "guest": 0.00, "gnice": 0.00, "idle": 100.00},
						{"cpu": "7", "usr": 0.00, "nice": 0.00, "sys": 0.00, "iowait": 0.00, "irq": 0.00, "soft": 0.00, "steal": 0.00, "guest": 0.00, "gnice": 0.00, "idle": 100.00},
						{"cpu": "8", "usr": 0.00, "nice": 0.00, "sys": 0.00, "iowait": 0.00, "irq": 0.00, "soft": 0.00, "steal": 0.00, "guest": 0.00, "gnice": 0.00, "idle": 100.00},
						{"cpu": "9", "usr": 0.00, "nice": 0.00, "sys": 0.00, "iowait": 0.00, "irq": 0.00, "soft": 0.00, "steal": 0.00, "guest": 0.00, "gnice": 0.00, "idle": 100.00},
						{"cpu": "10", "usr": 0.63, "nice": 0.00, "sys": 9.43, "iowait": 0.00, "irq": 0.00, "soft": 0.00, "steal": 0.00, "guest": 0.00, "gnice": 0.00, "idle": 89.94},
						{"cpu": "11", "usr": 0.00, "nice": 0.00, "sys": 0.00, "iowait": 0.00, "irq": 0.00, "soft": 0.00, "steal": 0.00, "guest": 0.00, "gnice": 0.00, "idle": 100.00},
						{"cpu": "12", "usr": 0.00, "nice": 0.00, "sys": 0.00, "iowait": 0.00, "irq": 0.00, "soft": 0.00, "steal": 0.00, "guest": 0.00, "gnice": 0.00, "idle": 100.00},
						{"cpu": "13", "usr": 0.00, "nice": 0.00, "sys": 0.00, "iowait": 0.00, "irq": 0.00, "soft": 0.00, "steal": 0.00, "guest": 0.00, "gnice": 0.00, "idle": 100.00},
						{"cpu": "14", "usr": 0.00, "nice": 0.00, "sys": 0.00, "iowait": 0.00, "irq": 0.00, "soft": 0.00, "steal": 0.00, "guest": 0.00, "gnice": 0.00, "idle": 100.00},
						{"cpu": "15", "usr": 0.00, "nice": 0.00, "sys": 0.00, "iowait": 0.00, "irq": 0.00, "soft": 0.00, "steal": 0.00, "guest": 0.00, "gnice": 0.00, "idle": 100.00}
					]
				},
				{
					"timestamp": "09:59:10 PM",
					"cpu-load": [
						{"cpu": "0", "usr": 0.00, "nice": 0.00, "sys": 0.00, "iowait": 0.00, "irq": 0.00, "soft": 1.11, "steal": 0.00, "guest": 0.00, "gnice": 0.00, "idle": 98.89},
						{"cpu": "1", "usr": 0.00, "nice": 0.00, "sys": 0.00, "iowait": 0.00, "irq": 0.00, "soft": 0.00, "steal": 0.00, "guest": 0.00, "gnice": 0.00, "idle": 100.00},
						{"cpu": "2", "usr": 0.00, "nice": 0.00, "sys": 0.00, "iowait": 0.00, "irq": 0.00, "soft": 0.52, "steal": 0.00, "guest": 0.00, "gnice": 0.00, "idle": 99.48},
						{"cpu": "3", "usr": 0.00, "nice": 0.00, "sys": 0.00, "iowait": 0.00, "irq": 0.00, "soft": 0.00, "steal": 0.00, "guest": 0.00, "gnice": 0.00, "idle": 100.00},
						{"cpu": "4", "usr": 0.00, "nice": 0.00, "sys": 0.00, "iowait": 0.00, "irq": 0.00, "soft": 0.00, "steal": 0.00, "guest": 0.00, "gnice": 0.00, "idle": 100.00},
						{"cpu": "5", "usr": 0.00, "nice": 0.00, "sys": 0.50, "iowait": 0.00, "irq": 0.00, "soft": 0.00, "steal": 0.00, "guest": 0.00, "gnice": 0.00, "idle": 99.50},
						{"cpu": "6", "usr": 0.00, "nice": 0.00, "sys": 0.00, "iowait": 0.00, "irq": 0.00, "soft": 0.00, "steal": 0.00, "guest": 0.00, "gnice": 0.00, "idle": 100.00},
						{"cpu": "7", "usr": 0.00, "nice": 0.00, "sys": 0.00, "iowait": 0.00, "irq": 0.00, "soft": 0.00, "steal": 0.00, "guest": 0.00, "gnice": 0.00, "idle": 100.00},
						{"cpu": "8", "usr": 0.00, "nice": 0.00, "sys": 0.00, "iowait": 0.00, "irq": 0.00, "soft": 0.00, "steal": 0.00, "guest": 0.00, "gnice": 0.00, "idle": 100.00},
						{"cpu": "9", "usr": 0.00, "nice": 0.00, "sys": 0.00, "iowait": 0.00, "irq": 0.00, "soft": 0.00, "steal": 0.00, "guest": 0.00, "gnice": 0.00, "idle": 100.00},
						{"cpu": "10", "usr": 0.00, "nice": 0.00, "sys": 11.25, "iowait": 0.00, "irq": 0.00, "soft": 0.62, "steal": 0.00, "guest": 0.00, "gnice": 0.00, "idle": 88.12},
						{"cpu": "11", "usr": 0.00, "nice": 0.00, "sys": 0.00, "iowait": 0.00, "irq": 0.00, "soft": 0.00, "steal": 0.00, "guest": 0.00, "gnice": 0.00, "idle": 100.00},
						{"cpu": "12", "usr": 0.00, "nice": 0.00, "sys": 0.00, "iowait": 0.00, "irq": 0.00, "soft": 0.00, "steal": 0.00, "guest": 0.00, "gnice": 0.00, "idle": 100.00},
						{"cpu": "13", "usr": 0.00, "nice": 0.00, "sys": 0.00, "iowait": 0.00, "irq": 0.00, "soft": 0.00, "steal": 0.00, "guest": 0.00, "gnice": 0.00, "idle": 100.00},
						{"cpu": "14", "usr": 0.00, "nice": 0.00, "sys": 0.00, "iowait": 0.00, "irq": 0.00, "soft": 0.00, "steal": 0.00, "guest": 0.00, "gnice": 0.00, "idle": 100.00},
						{"cpu": "15", "usr": 0.00, "nice": 0.00, "sys": 0.00, "iowait": 0.00, "irq": 0.00, "soft": 0.00, "steal": 0.00, "guest": 0.00, "gnice": 0.00, "idle": 100.00}
					]
				},
				{
					"timestamp": "09:59:12 PM",
					"cpu-load": [
						{"cpu": "0", "usr": 0.00, "nice": 0.00, "sys": 0.00, "iowait": 0.00, "irq": 0.00, "soft": 0.00, "steal": 0.00, "guest": 0.00, "gnice": 0.00, "idle": 100.00},
						{"cpu": "1", "usr": 0.00, "nice": 0.00, "sys": 0.00, "iowait": 0.00, "irq": 0.00, "soft": 0.00, "steal": 0.00, "guest": 0.00, "gnice": 0.00, "idle": 100.00},
						{"cpu": "2", "usr": 0.00, "nice": 0.00, "sys": 0.00, "iowait": 0.00, "irq": 0.00, "soft": 0.00, "steal": 0.00, "guest": 0.00, "gnice": 0.00, "idle": 100.00},
						{"cpu": "3", "usr": 0.00, "nice": 0.00, "sys": 0.00, "iowait": 0.00, "irq": 0.00, "soft": 0.00, "steal": 0.00, "guest": 0.00, "gnice": 0.00, "idle": 100.00},
						{"cpu": "4", "usr": 0.00, "nice": 0.00, "sys": 0.00, "iowait": 0.00, "irq": 0.00, "soft": 0.00, "steal": 0.00, "guest": 0.00, "gnice": 0.00, "idle": 100.00},
						{"cpu": "5", "usr": 0.00, "nice": 0.00, "sys": 0.00, "iowait": 0.00, "irq": 0.00, "soft": 0.00, "steal": 0.00, "guest": 0.00, "gnice": 0.00, "idle": 100.00},
						{"cpu": "6", "usr": 0.00, "nice": 0.00, "sys": 0.00, "iowait": 0.00, "irq": 0.00, "soft": 0.00, "steal": 0.00, "guest": 0.00, "gnice": 0.00, "idle": 100.00},
						{"cpu": "7", "usr": 0.00, "nice": 0.00, "sys": 0.00, "iowait": 0.00, "irq": 0.00, "soft": 0.00, "steal": 0.00, "guest": 0.00, "gnice": 0.00, "idle": 100.00},
						{"cpu": "8", "usr": 0.00, "nice": 0.00, "sys": 0.00, "iowait": 0.00, "irq": 0.00, "soft": 0.00, "steal": 0.00, "guest": 0.00, "gnice": 0.00, "idle": 100.00},
						{"cpu": "9", "usr": 0.00, "nice": 0.00, "sys": 0.00, "iowait": 0.00, "irq": 0.00, "soft": 0.00, "steal": 0.00, "guest": 0.00, "gnice": 0.00, "idle": 100.00},
						{"cpu": "10", "usr": 0.00, "nice": 0.00, "sys": 12.50, "iowait": 0.00, "irq": 0.00, "soft": 0.00, "steal": 0.00, "guest": 0.00, "gnice": 0.00, "idle": 87.50},
						{"cpu": "11", "usr": 0.00, "nice": 0.00, "sys": 0.00, "iowait": 0.00, "irq": 0.00, "soft": 0.00, "steal": 0.00, "guest": 0.00, "gnice": 0.00, "idle": 100.00},
						{"cpu": "12", "usr": 0.00, "nice": 0.00, "sys": 0.00, "iowait": 0.00, "irq": 0.00, "soft": 0.00, "steal": 0.00, "guest": 0.00, "gnice": 0.00, "idle": 100.00},
						{"cpu": "13", "usr": 0.00, "nice": 0.00, "sys": 0.00, "iowait": 0.00, "irq": 0.00, "soft": 0.00, "steal": 0.00, "guest": 0.00, "gnice": 0.00, "idle": 100.00},
						{"cpu": "14", "usr": 0.00, "nice": 0.00, "sys": 0.00, "iowait": 0.00, "irq": 0.00, "soft": 0.00, "steal": 0.00, "guest": 0.00, "gnice": 0.00, "idle": 100.00},
						{"cpu": "15", "usr": 0.00, "nice": 0.00, "sys": 0.00, "iowait": 0.00, "irq": 0.00, "soft": 0.00, "steal": 0.00, "guest": 0.00, "gnice": 0.00, "idle": 100.00}
					]
				},
				{
					"timestamp": "09:59:14 PM",
					"cpu-load": [
						{"cpu": "0", "usr": 0.00, "nice": 0.00, "sys": 0.00, "iowait": 0.00, "irq": 0.00, "soft": 0.00, "steal": 0.00, "guest": 0.00, "gnice": 0.00, "idle": 100.00},
						{"cpu": "1", "usr": 0.00, "nice": 0.00, "sys": 0.00, "iowait": 0.00, "irq": 0.00, "soft": 0.00, "steal": 0.00, "guest": 0.00, "gnice": 0.00, "idle": 100.00},
						{"cpu": "2", "usr": 0.00, "nice": 0.00, "sys": 0.00, "iowait": 0.00, "irq": 0.00, "soft": 0.52, "steal": 0.00, "guest": 0.00, "gnice": 0.00, "idle": 99.48},
						{"cpu": "3", "usr": 0.00, "nice": 0.00, "sys": 0.00, "iowait": 0.00, "irq": 0.00, "soft": 0.00, "steal": 0.00, "guest": 0.00, "gnice": 0.00, "idle": 100.00},
						{"cpu": "4", "usr": 0.00, "nice": 0.00, "sys": 0.00, "iowait": 0.00, "irq": 0.00, "soft": 0.00, "steal": 0.00, "guest": 0.00, "gnice": 0.00, "idle": 100.00},
						{"cpu": "5", "usr": 0.00, "nice": 0.00, "sys": 0.00, "iowait": 0.00, "irq": 0.00, "soft": 0.00, "steal": 0.00, "guest": 0.00, "gnice": 0.00, "idle": 100.00},
						{"cpu": "6", "usr": 0.00, "nice": 0.00, "sys": 0.00, "iowait": 0.00, "irq": 0.00, "soft": 0.00, "steal": 0.00, "guest": 0.00, "gnice": 0.00, "idle": 100.00},
						{"cpu": "7", "usr": 0.00, "nice": 0.00, "sys": 0.00, "iowait": 0.00, "irq": 0.00, "soft": 0.00, "steal": 0.00, "guest": 0.00, "gnice": 0.00, "idle": 100.00},
						{"cpu": "8", "usr": 0.00, "nice": 0.00, "sys": 0.00, "iowait": 0.00, "irq": 0.00, "soft": 0.00, "steal": 0.00, "guest": 0.00, "gnice": 0.00, "idle": 100.00},
						{"cpu": "9", "usr": 0.00, "nice": 0.00, "sys": 0.00, "iowait": 0.00, "irq": 0.00, "soft": 0.00, "steal": 0.00, "guest": 0.00, "gnice": 0.00, "idle": 100.00},
						{"cpu": "10", "usr": 0.63, "nice": 0.00, "sys": 8.81, "iowait": 0.00, "irq": 0.00, "soft": 1.26, "steal": 0.00, "guest": 0.00, "gnice": 0.00, "idle": 89.31},
						{"cpu": "11", "usr": 0.00, "nice": 0.00, "sys": 0.00, "iowait": 0.00, "irq": 0.00, "soft": 0.00, "steal": 0.00, "guest": 0.00, "gnice": 0.00, "idle": 100.00},
						{"cpu": "12", "usr": 0.00, "nice": 0.00, "sys": 0.00, "iowait": 0.00, "irq": 0.00, "soft": 0.00, "steal": 0.00, "guest": 0.00, "gnice": 0.00, "idle": 100.00},
						{"cpu": "13", "usr": 0.00, "nice": 0.00, "sys": 0.00, "iowait": 0.00, "irq": 0.00, "soft": 0.00, "steal": 0.00, "guest": 0.00, "gnice": 0.00, "idle": 100.00},
						{"cpu": "14", "usr": 0.00, "nice": 0.00, "sys": 0.00, "iowait": 0.00, "irq": 0.00, "soft": 0.00, "steal": 0.00, "guest": 0.00, "gnice": 0.00, "idle": 100.00},
						{"cpu": "15", "usr": 0.00, "nice": 0.00, "sys": 0.00, "iowait": 0.00, "irq": 0.00, "soft": 0.00, "steal": 0.00, "guest": 0.00, "gnice": 0.00, "idle": 100.00}
					]
				},
				{
					"timestamp": "09:59:16 PM",
					"cpu-load": [
						{"cpu": "0", "usr": 0.00, "nice": 0.00, "sys": 0.00, "iowait": 0.00, "irq": 0.00, "soft": 0.56, "steal": 0.00, "guest": 0.00, "gnice": 0.00, "idle": 99.44},
						{"cpu": "1", "usr": 0.00, "nice": 0.00, "sys": 0.00, "iowait": 0.00, "irq": 0.00, "soft": 0.00, "steal": 0.00, "guest": 0.00, "gnice": 0.00, "idle": 100.00},
						{"cpu": "2", "usr": 0.00, "nice": 0.00, "sys": 0.00, "iowait": 0.00, "irq": 0.00, "soft": 0.00, "steal": 0.00, "guest": 0.00, "gnice": 0.00, "idle": 100.00},
						{"cpu": "3", "usr": 0.00, "nice": 0.00, "sys": 0.50, "iowait": 0.00, "irq": 0.00, "soft": 0.00, "steal": 0.00, "guest": 0.00, "gnice": 0.00, "idle": 99.50},
						{"cpu": "4", "usr": 0.00, "nice": 0.00, "sys": 0.00, "iowait": 0.00, "irq": 0.00, "soft": 0.00, "steal": 0.00, "guest": 0.00, "gnice": 0.00, "idle": 100.00},
						{"cpu": "5", "usr": 0.00, "nice": 0.00, "sys": 0.00, "iowait": 0.00, "irq": 0.00, "soft": 0.00, "steal": 0.00, "guest": 0.00, "gnice": 0.00, "idle": 100.00},
						{"cpu": "6", "usr": 0.00, "nice": 0.00, "sys": 0.00, "iowait": 0.00, "irq": 0.00, "soft": 0.00, "steal": 0.00, "guest": 0.00, "gnice": 0.00, "idle": 100.00},
						{"cpu": "7", "usr": 0.00, "nice": 0.00, "sys": 0.00, "iowait": 0.00, "irq": 0.00, "soft": 0.00, "steal": 0.00, "guest": 0.00, "gnice": 0.00, "idle": 100.00},
						{"cpu": "8", "usr": 0.00, "nice": 0.00, "sys": 0.00, "iowait": 0.00, "irq": 0.00, "soft": 0.00, "steal": 0.00, "guest": 0.00, "gnice": 0.00, "idle": 100.00},
						{"cpu": "9", "usr": 0.00, "nice": 0.00, "sys": 0.00, "iowait": 0.00, "irq": 0.00, "soft": 0.00, "steal": 0.00, "guest": 0.00, "gnice": 0.00, "idle": 100.00},
						{"cpu": "10", "usr": 0.00, "nice": 0.00, "sys": 10.13, "iowait": 0.00, "irq": 0.00, "soft": 0.63, "steal": 0.00, "guest": 0.00, "gnice": 0.00, "idle": 89.24},
						{"cpu": "11", "usr": 0.00, "nice": 0.00, "sys": 0.00, "iowait": 0.00, "irq": 0.00, "soft": 0.00, "steal": 0.00, "guest": 0.00, "gnice": 0.00, "idle": 100.00},
						{"cpu": "12", "usr": 0.00, "nice": 0.00, "sys": 0.00, "iowait": 0.00, "irq": 0.00, "soft": 0.00, "steal": 0.00, "guest": 0.00, "gnice": 0.00, "idle": 100.00},
						{"cpu": "13", "usr": 0.00, "nice": 0.00, "sys": 0.00, "iowait": 0.00, "irq": 0.00, "soft": 0.00, "steal": 0.00, "guest": 0.00, "gnice": 0.00, "idle": 100.00},
						{"cpu": "14", "usr": 0.00, "nice": 0.00, "sys": 0.00, "iowait": 0.00, "irq": 0.00, "soft": 0.00, "steal": 0.00, "guest": 0.00, "gnice": 0.00, "idle": 100.00},
						{"cpu": "15", "usr": 0.50, "nice": 0.00, "sys": 0.00, "iowait": 0.00, "irq": 0.00, "soft": 0.00, "steal": 0.00, "guest": 0.00, "gnice": 0.00, "idle": 99.50}
					]
				},
				{
					"timestamp": "09:59:18 PM",
					"cpu-load": [
						{"cpu": "0", "usr": 0.00, "nice": 0.00, "sys": 0.00, "iowait": 0.00, "irq": 0.00, "soft": 1.10, "steal": 0.00, "guest": 0.00, "gnice": 0.00, "idle": 98.90},
						{"cpu": "1", "usr": 0.00, "nice": 0.00, "sys": 0.50, "iowait": 0.00, "irq": 0.00, "soft": 0.00, "steal": 0.00, "guest": 0.00, "gnice": 0.00, "idle": 99.50},
						{"cpu": "2", "usr": 0.00, "nice": 0.00, "sys": 0.00, "iowait": 0.00, "irq": 0.00, "soft": 0.00, "steal": 0.00, "guest": 0.00, "gnice": 0.00, "idle": 100.00},
						{"cpu": "3", "usr": 0.00, "nice": 0.00, "sys": 0.00, "iowait": 0.00, "irq": 0.00, "soft": 0.00, "steal": 0.00, "guest": 0.00, "gnice": 0.00, "idle": 100.00},
						{"cpu": "4", "usr": 0.00, "nice": 0.00, "sys": 0.00, "iowait": 0.00, "irq": 0.00, "soft": 0.00, "steal": 0.00, "guest": 0.00, "gnice": 0.00, "idle": 100.00},
						{"cpu": "5", "usr": 0.00, "nice": 0.00, "sys": 0.00, "iowait": 0.00, "irq": 0.00, "soft": 0.00, "steal": 0.00, "guest": 0.00, "gnice": 0.00, "idle": 100.00},
						{"cpu": "6", "usr": 0.00, "nice": 0.00, "sys": 0.00, "iowait": 0.00, "irq": 0.00, "soft": 0.00, "steal": 0.00, "guest": 0.00, "gnice": 0.00, "idle": 100.00},
						{"cpu": "7", "usr": 0.00, "nice": 0.00, "sys": 0.00, "iowait": 0.00, "irq": 0.00, "soft": 0.00, "steal": 0.00, "guest": 0.00, "gnice": 0.00, "idle": 100.00},
						{"cpu": "8", "usr": 0.00, "nice": 0.00, "sys": 0.00, "iowait": 0.00, "irq": 0.00, "soft": 0.00, "steal": 0.00, "guest": 0.00, "gnice": 0.00, "idle": 100.00},
						{"cpu": "9", "usr": 0.00, "nice": 0.00, "sys": 0.00, "iowait": 0.00, "irq": 0.00, "soft": 0.00, "steal": 0.00, "guest": 0.00, "gnice": 0.00, "idle": 100.00},
						{"cpu": "10", "usr": 0.00, "nice": 0.00, "sys": 8.92, "iowait": 0.00, "irq": 0.00, "soft": 0.64, "steal": 0.00, "guest": 0.00, "gnice": 0.00, "idle": 90.45},
						{"cpu": "11", "usr": 0.00, "nice": 0.00, "sys": 0.00, "iowait": 0.00, "irq": 0.00, "soft": 0.00, "steal": 0.00, "guest": 0.00, "gnice": 0.00, "idle": 100.00},
						{"cpu": "12", "usr": 0.00, "nice": 0.00, "sys": 0.00, "iowait": 0.00, "irq": 0.00, "soft": 0.00, "steal": 0.00, "guest": 0.00, "gnice": 0.00, "idle": 100.00},
						{"cpu": "13", "usr": 0.00, "nice": 0.00, "sys": 0.00, "iowait": 0.00, "irq": 0.00, "soft": 0.00, "steal": 0.00, "guest": 0.00, "gnice": 0.00, "idle": 100.00},
						{"cpu": "14", "usr": 0.00, "nice": 0.00, "sys": 0.00, "iowait": 0.00, "irq": 0.00, "soft": 0.00, "steal": 0.00, "guest": 0.00, "gnice": 0.00, "idle": 100.00},
						{"cpu": "15", "usr": 0.00, "nice": 0.00, "sys": 0.00, "iowait": 0.00, "irq": 0.00, "soft": 0.00, "steal": 0.00, "guest": 0.00, "gnice": 0.00, "idle": 100.00}
					]
				},
				{
					"timestamp": "09:59:20 PM",
					"cpu-load": [
						{"cpu": "0", "usr": 0.00, "nice": 0.00, "sys": 0.00, "iowait": 0.00, "irq": 0.00, "soft": 0.56, "steal": 0.00, "guest": 0.00, "gnice": 0.00, "idle": 99.44},
						{"cpu": "1", "usr": 0.00, "nice": 0.00, "sys": 0.00, "iowait": 0.00, "irq": 0.00, "soft": 0.00, "steal": 0.00, "guest": 0.00, "gnice": 0.00, "idle": 100.00},
						{"cpu": "2", "usr": 0.00, "nice": 0.00, "sys": 0.00, "iowait": 0.00, "irq": 0.00, "soft": 0.00, "steal": 0.00, "guest": 0.00, "gnice": 0.00, "idle": 100.00},
						{"cpu": "3", "usr": 0.00, "nice": 0.00, "sys": 0.00, "iowait": 0.00, "irq": 0.00, "soft": 0.00, "steal": 0.00, "guest": 0.00, "gnice": 0.00, "idle": 100.00},
						{"cpu": "4", "usr": 0.00, "nice": 0.00, "sys": 0.00, "iowait": 0.00, "irq": 0.00, "soft": 0.00, "steal": 0.00, "guest": 0.00, "gnice": 0.00, "idle": 100.00},
						{"cpu": "5", "usr": 0.00, "nice": 0.00, "sys": 0.00, "iowait": 0.00, "irq": 0.00, "soft": 0.00, "steal": 0.00, "guest": 0.00, "gnice": 0.00, "idle": 100.00},
						{"cpu": "6", "usr": 0.00, "nice": 0.00, "sys": 0.00, "iowait": 0.00, "irq": 0.00, "soft": 0.00, "steal": 0.00, "guest": 0.00, "gnice": 0.00, "idle": 100.00},
						{"cpu": "7", "usr": 0.00, "nice": 0.00, "sys": 0.00, "iowait": 0.00, "irq": 0.00, "soft": 0.00, "steal": 0.00, "guest": 0.00, "gnice": 0.00, "idle": 100.00},
						{"cpu": "8", "usr": 0.00, "nice": 0.00, "sys": 0.00, "iowait": 0.00, "irq": 0.00, "soft": 0.00, "steal": 0.00, "guest": 0.00, "gnice": 0.00, "idle": 100.00},
						{"cpu": "9", "usr": 0.00, "nice": 0.00, "sys": 0.00, "iowait": 0.00, "irq": 0.00, "soft": 0.00, "steal": 0.00, "guest": 0.00, "gnice": 0.00, "idle": 100.00},
						{"cpu": "10", "usr": 0.62, "nice": 0.00, "sys": 10.49, "iowait": 0.00, "irq": 0.00, "soft": 0.62, "steal": 0.00, "guest": 0.00, "gnice": 0.00, "idle": 88.27},
						{"cpu": "11", "usr": 0.00, "nice": 0.00, "sys": 0.00, "iowait": 0.00, "irq": 0.00, "soft": 0.00, "steal": 0.00, "guest": 0.00, "gnice": 0.00, "idle": 100.00},
						{"cpu": "12", "usr": 0.00, "nice": 0.00, "sys": 0.00, "iowait": 0.00, "irq": 0.00, "soft": 0.00, "steal": 0.00, "guest": 0.00, "gnice": 0.00, "idle": 100.00},
						{"cpu": "13", "usr": 0.00, "nice": 0.00, "sys": 0.00, "iowait": 0.00, "irq": 0.00, "soft": 0.00, "steal": 0.00, "guest": 0.00, "gnice": 0.00, "idle": 100.00},
						{"cpu": "14", "usr": 0.00, "nice": 0.00, "sys": 0.00, "iowait": 0.00, "irq": 0.00, "soft": 0.00, "steal": 0.00, "guest": 0.00, "gnice": 0.00, "idle": 100.00},
						{"cpu": "15", "usr": 0.00, "nice": 0.00, "sys": 0.00, "iowait": 0.00, "irq": 0.00, "soft": 0.00, "steal": 0.00, "guest": 0.00, "gnice": 0.00, "idle": 100.00}
					]
				},
				{
					"timestamp": "09:59:22 PM",
					"cpu-load": [
						{"cpu": "0", "usr": 0.00, "nice": 0.00, "sys": 0.00, "iowait": 0.00, "irq": 0.00, "soft": 1.10, "steal": 0.00, "guest": 0.00, "gnice": 0.00, "idle": 98.90},
						{"cpu": "1", "usr": 0.00, "nice": 0.00, "sys": 0.00, "iowait": 0.00, "irq": 0.00, "soft": 0.00, "steal": 0.00, "guest": 0.00, "gnice": 0.00, "idle": 100.00},
						{"cpu": "2", "usr": 0.00, "nice": 0.00, "sys": 0.00, "iowait": 0.00, "irq": 0.00, "soft": 0.00, "steal": 0.00, "guest": 0.00, "gnice": 0.00, "idle": 100.00},
						{"cpu": "3", "usr": 0.00, "nice": 0.00, "sys": 0.50, "iowait": 0.00, "irq": 0.00, "soft": 0.00, "steal": 0.00, "guest": 0.00, "gnice": 0.00, "idle": 99.50},
						{"cpu": "4", "usr": 0.00, "nice": 0.00, "sys": 0.00, "iowait": 0.00, "irq": 0.00, "soft": 0.00, "steal": 0.00, "guest": 0.00, "gnice": 0.00, "idle": 100.00},
						{"cpu": "5", "usr": 0.00, "nice": 0.00, "sys": 0.00, "iowait": 0.00, "irq": 0.00, "soft": 0.00, "steal": 0.00, "guest": 0.00, "gnice": 0.00, "idle": 100.00},
						{"cpu": "6", "usr": 0.00, "nice": 0.00, "sys": 0.00, "iowait": 0.00, "irq": 0.00, "soft": 0.00, "steal": 0.00, "guest": 0.00, "gnice": 0.00, "idle": 100.00},
						{"cpu": "7", "usr": 0.00, "nice": 0.00, "sys": 0.00, "iowait": 0.00, "irq": 0.00, "soft": 0.00, "steal": 0.00, "guest": 0.00, "gnice": 0.00, "idle": 100.00},
						{"cpu": "8", "usr": 0.00, "nice": 0.00, "sys": 0.00, "iowait": 0.00, "irq": 0.00, "soft": 0.00, "steal": 0.00, "guest": 0.00, "gnice": 0.00, "idle": 100.00},
						{"cpu": "9", "usr": 0.00, "nice": 0.00, "sys": 0.00, "iowait": 0.00, "irq": 0.00, "soft": 0.00, "steal": 0.00, "guest": 0.00, "gnice": 0.00, "idle": 100.00},
						{"cpu": "10", "usr": 0.00, "nice": 0.00, "sys": 9.88, "iowait": 0.00, "irq": 0.00, "soft": 1.23, "steal": 0.00, "guest": 0.00, "gnice": 0.00, "idle": 88.89},
						{"cpu": "11", "usr": 0.00, "nice": 0.00, "sys": 0.00, "iowait": 0.00, "irq": 0.00, "soft": 0.00, "steal": 0.00, "guest": 0.00, "gnice": 0.00, "idle": 100.00},
						{"cpu": "12", "usr": 0.00, "nice": 0.00, "sys": 0.00, "iowait": 0.00, "irq": 0.00, "soft": 0.00, "steal": 0.00, "guest": 0.00, "gnice": 0.00, "idle": 100.00},
						{"cpu": "13", "usr": 0.00, "nice": 0.00, "sys": 0.00, "iowait": 0.00, "irq": 0.00, "soft": 0.00, "steal": 0.00, "guest": 0.00, "gnice": 0.00, "idle": 100.00},
						{"cpu": "14", "usr": 0.00, "nice": 0.00, "sys": 0.00, "iowait": 0.00, "irq": 0.00, "soft": 0.00, "steal": 0.00, "guest": 0.00, "gnice": 0.00, "idle": 100.00},
						{"cpu": "15", "usr": 0.00, "nice": 0.00, "sys": 0.00, "iowait": 0.00, "irq": 0.00, "soft": 0.00, "steal": 0.00, "guest": 0.00, "gnice": 0.00, "idle": 100.00}
					]
				},
				{
					"timestamp": "09:59:24 PM",
					"cpu-load": [
						{"cpu": "0", "usr": 0.00, "nice": 0.00, "sys": 0.00, "iowait": 0.00, "irq": 0.00, "soft": 0.00, "steal": 0.00, "guest": 0.00, "gnice": 0.00, "idle": 100.00},
						{"cpu": "1", "usr": 0.00, "nice": 0.00, "sys": 0.00, "iowait": 0.00, "irq": 0.00, "soft": 0.00, "steal": 0.00, "guest": 0.00, "gnice": 0.00, "idle": 100.00},
						{"cpu": "2", "usr": 0.00, "nice": 0.00, "sys": 0.00, "iowait": 0.00, "irq": 0.00, "soft": 0.00, "steal": 0.00, "guest": 0.00, "gnice": 0.00, "idle": 100.00},
						{"cpu": "3", "usr": 0.00, "nice": 0.00, "sys": 0.00, "iowait": 0.00, "irq": 0.00, "soft": 0.00, "steal": 0.00, "guest": 0.00, "gnice": 0.00, "idle": 100.00},
						{"cpu": "4", "usr": 0.00, "nice": 0.00, "sys": 0.00, "iowait": 0.00, "irq": 0.00, "soft": 0.00, "steal": 0.00, "guest": 0.00, "gnice": 0.00, "idle": 100.00},
						{"cpu": "5", "usr": 0.00, "nice": 0.00, "sys": 0.00, "iowait": 0.00, "irq": 0.00, "soft": 0.00, "steal": 0.00, "guest": 0.00, "gnice": 0.00, "idle": 100.00},
						{"cpu": "6", "usr": 0.00, "nice": 0.00, "sys": 0.00, "iowait": 0.00, "irq": 0.00, "soft": 0.00, "steal": 0.00, "guest": 0.00, "gnice": 0.00, "idle": 100.00},
						{"cpu": "7", "usr": 0.00, "nice": 0.00, "sys": 0.00, "iowait": 0.00, "irq": 0.00, "soft": 0.00, "steal": 0.00, "guest": 0.00, "gnice": 0.00, "idle": 100.00},
						{"cpu": "8", "usr": 0.00, "nice": 0.00, "sys": 0.00, "iowait": 0.00, "irq": 0.00, "soft": 0.00, "steal": 0.00, "guest": 0.00, "gnice": 0.00, "idle": 100.00},
						{"cpu": "9", "usr": 0.00, "nice": 0.00, "sys": 0.00, "iowait": 0.00, "irq": 0.00, "soft": 0.00, "steal": 0.00, "guest": 0.00, "gnice": 0.00, "idle": 100.00},
						{"cpu": "10", "usr": 0.62, "nice": 0.00, "sys": 10.49, "iowait": 0.00, "irq": 0.00, "soft": 0.62, "steal": 0.00, "guest": 0.00, "gnice": 0.00, "idle": 88.27},
						{"cpu": "11", "usr": 0.00, "nice": 0.00, "sys": 0.00, "iowait": 0.00, "irq": 0.00, "soft": 0.00, "steal": 0.00, "guest": 0.00, "gnice": 0.00, "idle": 100.00},
						{"cpu": "12", "usr": 0.00, "nice": 0.00, "sys": 0.00, "iowait": 0.00, "irq": 0.00, "soft": 0.00, "steal": 0.00, "guest": 0.00, "gnice": 0.00, "idle": 100.00},
						{"cpu": "13", "usr": 0.00, "nice": 0.00, "sys": 0.00, "iowait": 0.00, "irq": 0.00, "soft": 0.00, "steal": 0.00, "guest": 0.00, "gnice": 0.00, "idle": 100.00},
						{"cpu": "14", "usr": 0.00, "nice": 0.00, "sys": 0.00, "iowait": 0.00, "irq": 0.00, "soft": 0.00, "steal": 0.00, "guest": 0.00, "gnice": 0.00, "idle": 100.00},
						{"cpu": "15", "usr": 0.00, "nice": 0.00, "sys": 0.00, "iowait": 0.00, "irq": 0.00, "soft": 0.00, "steal": 0.00, "guest": 0.00, "gnice": 0.00, "idle": 100.00}
					]
				},
				{
					"timestamp": "09:59:26 PM",
					"cpu-load": [
						{"cpu": "0", "usr": 0.00, "nice": 0.00, "sys": 0.00, "iowait": 0.00, "irq": 0.00, "soft": 0.56, "steal": 0.00, "guest": 0.00, "gnice": 0.00, "idle": 99.44},
						{"cpu": "1", "usr": 0.00, "nice": 0.00, "sys": 0.00, "iowait": 0.00, "irq": 0.00, "soft": 0.00, "steal": 0.00, "guest": 0.00, "gnice": 0.00, "idle": 100.00},
						{"cpu": "2", "usr": 0.00, "nice": 0.00, "sys": 0.00, "iowait": 0.00, "irq": 0.00, "soft": 0.00, "steal": 0.00, "guest": 0.00, "gnice": 0.00, "idle": 100.00},
						{"cpu": "3", "usr": 0.00, "nice": 0.00, "sys": 0.00, "iowait": 0.00, "irq": 0.00, "soft": 0.00, "steal": 0.00, "guest": 0.00, "gnice": 0.00, "idle": 100.00},
						{"cpu": "4", "usr": 0.00, "nice": 0.00, "sys": 0.00, "iowait": 0.00, "irq": 0.00, "soft": 0.00, "steal": 0.00, "guest": 0.00, "gnice": 0.00, "idle": 100.00},
						{"cpu": "5", "usr": 0.00, "nice": 0.00, "sys": 0.00, "iowait": 0.00, "irq": 0.00, "soft": 0.00, "steal": 0.00, "guest": 0.00, "gnice": 0.00, "idle": 100.00},
						{"cpu": "6", "usr": 0.00, "nice": 0.00, "sys": 0.00, "iowait": 0.00, "irq": 0.00, "soft": 0.00, "steal": 0.00, "guest": 0.00, "gnice": 0.00, "idle": 100.00},
						{"cpu": "7", "usr": 0.00, "nice": 0.00, "sys": 0.00, "iowait": 0.00, "irq": 0.00, "soft": 0.00, "steal": 0.00, "guest": 0.00, "gnice": 0.00, "idle": 100.00},
						{"cpu": "8", "usr": 0.00, "nice": 0.00, "sys": 0.00, "iowait": 0.00, "irq": 0.00, "soft": 0.00, "steal": 0.00, "guest": 0.00, "gnice": 0.00, "idle": 100.00},
						{"cpu": "9", "usr": 0.00, "nice": 0.00, "sys": 0.00, "iowait": 0.00, "irq": 0.00, "soft": 0.00, "steal": 0.00, "guest": 0.00, "gnice": 0.00, "idle": 100.00},
						{"cpu": "10", "usr": 0.00, "nice": 0.00, "sys": 11.18, "iowait": 0.00, "irq": 0.00, "soft": 1.24, "steal": 0.00, "guest": 0.00, "gnice": 0.00, "idle": 87.58},
						{"cpu": "11", "usr": 0.00, "nice": 0.00, "sys": 0.00, "iowait": 0.00, "irq": 0.00, "soft": 0.00, "steal": 0.00, "guest": 0.00, "gnice": 0.00, "idle": 100.00},
						{"cpu": "12", "usr": 0.00, "nice": 0.00, "sys": 0.00, "iowait": 0.00, "irq": 0.00, "soft": 0.00, "steal": 0.00, "guest": 0.00, "gnice": 0.00, "idle": 100.00},
						{"cpu": "13", "usr": 0.00, "nice": 0.00, "sys": 0.00, "iowait": 0.00, "irq": 0.00, "soft": 0.00, "steal": 0.00, "guest": 0.00, "gnice": 0.00, "idle": 100.00},
						{"cpu": "14", "usr": 0.00, "nice": 0.00, "sys": 0.00, "iowait": 0.00, "irq": 0.00, "soft": 0.00, "steal": 0.00, "guest": 0.00, "gnice": 0.00, "idle": 100.00},
						{"cpu": "15", "usr": 0.00, "nice": 0.00, "sys": 0.00, "iowait": 0.00, "irq": 0.00, "soft": 0.00, "steal": 0.00, "guest": 0.00, "gnice": 0.00, "idle": 100.00}
					]
				},
				{
					"timestamp": "09:59:28 PM",
					"cpu-load": [
						{"cpu": "0", "usr": 0.00, "nice": 0.00, "sys": 0.00, "iowait": 0.00, "irq": 0.00, "soft": 1.66, "steal": 0.00, "guest": 0.00, "gnice": 0.00, "idle": 98.34},
						{"cpu": "1", "usr": 0.00, "nice": 0.00, "sys": 0.00, "iowait": 0.00, "irq": 0.00, "soft": 0.00, "steal": 0.00, "guest": 0.00, "gnice": 0.00, "idle": 100.00},
						{"cpu": "2", "usr": 0.00, "nice": 0.00, "sys": 0.00, "iowait": 0.00, "irq": 0.00, "soft": 0.52, "steal": 0.00, "guest": 0.00, "gnice": 0.00, "idle": 99.48},
						{"cpu": "3", "usr": 0.00, "nice": 0.00, "sys": 0.00, "iowait": 0.00, "irq": 0.00, "soft": 0.00, "steal": 0.00, "guest": 0.00, "gnice": 0.00, "idle": 100.00},
						{"cpu": "4", "usr": 0.00, "nice": 0.00, "sys": 0.00, "iowait": 0.00, "irq": 0.00, "soft": 0.00, "steal": 0.00, "guest": 0.00, "gnice": 0.00, "idle": 100.00},
						{"cpu": "5", "usr": 0.00, "nice": 0.00, "sys": 0.00, "iowait": 0.00, "irq": 0.00, "soft": 0.00, "steal": 0.00, "guest": 0.00, "gnice": 0.00, "idle": 100.00},
						{"cpu": "6", "usr": 0.00, "nice": 0.00, "sys": 0.00, "iowait": 0.00, "irq": 0.00, "soft": 0.00, "steal": 0.00, "guest": 0.00, "gnice": 0.00, "idle": 100.00},
						{"cpu": "7", "usr": 0.00, "nice": 0.00, "sys": 0.00, "iowait": 0.00, "irq": 0.00, "soft": 0.00, "steal": 0.00, "guest": 0.00, "gnice": 0.00, "idle": 100.00},
						{"cpu": "8", "usr": 0.00, "nice": 0.00, "sys": 0.00, "iowait": 0.00, "irq": 0.00, "soft": 0.00, "steal": 0.00, "guest": 0.00, "gnice": 0.00, "idle": 100.00},
						{"cpu": "9", "usr": 0.00, "nice": 0.00, "sys": 0.00, "iowait": 0.00, "irq": 0.00, "soft": 0.00, "steal": 0.00, "guest": 0.00, "gnice": 0.00, "idle": 100.00},
						{"cpu": "10", "usr": 0.00, "nice": 0.00, "sys": 11.32, "iowait": 0.00, "irq": 0.00, "soft": 0.00, "steal": 0.00, "guest": 0.00, "gnice": 0.00, "idle": 88.68},
						{"cpu": "11", "usr": 0.00, "nice": 0.00, "sys": 0.00, "iowait": 0.00, "irq": 0.00, "soft": 0.00, "steal": 0.00, "guest": 0.00, "gnice": 0.00, "idle": 100.00},
						{"cpu": "12", "usr": 0.00, "nice": 0.00, "sys": 0.00, "iowait": 0.00, "irq": 0.00, "soft": 0.00, "steal": 0.00, "guest": 0.00, "gnice": 0.00, "idle": 100.00},
						{"cpu": "13", "usr": 0.00, "nice": 0.00, "sys": 0.00, "iowait": 0.00, "irq": 0.00, "soft": 0.00, "steal": 0.00, "guest": 0.00, "gnice": 0.00, "idle": 100.00},
						{"cpu": "14", "usr": 0.00, "nice": 0.00, "sys": 0.00, "iowait": 0.00, "irq": 0.00, "soft": 0.00, "steal": 0.00, "guest": 0.00, "gnice": 0.00, "idle": 100.00},
						{"cpu": "15", "usr": 0.00, "nice": 0.00, "sys": 0.00, "iowait": 0.00, "irq": 0.00, "soft": 0.00, "steal": 0.00, "guest": 0.00, "gnice": 0.00, "idle": 100.00}
					]
				},
				{
					"timestamp": "09:59:30 PM",
					"cpu-load": [
						{"cpu": "0", "usr": 0.00, "nice": 0.00, "sys": 0.00, "iowait": 0.00, "irq": 0.00, "soft": 1.10, "steal": 0.00, "guest": 0.00, "gnice": 0.00, "idle": 98.90},
						{"cpu": "1", "usr": 0.00, "nice": 0.00, "sys": 0.00, "iowait": 0.00, "irq": 0.00, "soft": 0.00, "steal": 0.00, "guest": 0.00, "gnice": 0.00, "idle": 100.00},
						{"cpu": "2", "usr": 0.00, "nice": 0.00, "sys": 0.00, "iowait": 0.00, "irq": 0.00, "soft": 0.00, "steal": 0.00, "guest": 0.00, "gnice": 0.00, "idle": 100.00},
						{"cpu": "3", "usr": 0.00, "nice": 0.00, "sys": 0.00, "iowait": 0.00, "irq": 0.00, "soft": 0.00, "steal": 0.00, "guest": 0.00, "gnice": 0.00, "idle": 100.00},
						{"cpu": "4", "usr": 0.00, "nice": 0.00, "sys": 0.00, "iowait": 0.00, "irq": 0.00, "soft": 0.00, "steal": 0.00, "guest": 0.00, "gnice": 0.00, "idle": 100.00},
						{"cpu": "5", "usr": 0.00, "nice": 0.00, "sys": 0.00, "iowait": 0.00, "irq": 0.00, "soft": 0.00, "steal": 0.00, "guest": 0.00, "gnice": 0.00, "idle": 100.00},
						{"cpu": "6", "usr": 0.00, "nice": 0.00, "sys": 0.00, "iowait": 0.00, "irq": 0.00, "soft": 0.00, "steal": 0.00, "guest": 0.00, "gnice": 0.00, "idle": 100.00},
						{"cpu": "7", "usr": 0.00, "nice": 0.00, "sys": 0.00, "iowait": 0.00, "irq": 0.00, "soft": 0.00, "steal": 0.00, "guest": 0.00, "gnice": 0.00, "idle": 100.00},
						{"cpu": "8", "usr": 0.00, "nice": 0.00, "sys": 0.00, "iowait": 0.00, "irq": 0.00, "soft": 0.00, "steal": 0.00, "guest": 0.00, "gnice": 0.00, "idle": 100.00},
						{"cpu": "9", "usr": 0.00, "nice": 0.00, "sys": 0.00, "iowait": 0.00, "irq": 0.00, "soft": 0.00, "steal": 0.00, "guest": 0.00, "gnice": 0.00, "idle": 100.00},
						{"cpu": "10", "usr": 0.00, "nice": 0.00, "sys": 8.92, "iowait": 0.00, "irq": 0.00, "soft": 0.64, "steal": 0.00, "guest": 0.00, "gnice": 0.00, "idle": 90.45},
						{"cpu": "11", "usr": 0.00, "nice": 0.00, "sys": 0.00, "iowait": 0.00, "irq": 0.00, "soft": 0.00, "steal": 0.00, "guest": 0.00, "gnice": 0.00, "idle": 100.00},
						{"cpu": "12", "usr": 0.00, "nice": 0.00, "sys": 0.00, "iowait": 0.00, "irq": 0.00, "soft": 0.00, "steal": 0.00, "guest": 0.00, "gnice": 0.00, "idle": 100.00},
						{"cpu": "13", "usr": 0.00, "nice": 0.00, "sys": 0.00, "iowait": 0.00, "irq": 0.00, "soft": 0.00, "steal": 0.00, "guest": 0.00, "gnice": 0.00, "idle": 100.00},
						{"cpu": "14", "usr": 0.00, "nice": 0.00, "sys": 0.00, "iowait": 0.00, "irq": 0.00, "soft": 0.00, "steal": 0.00, "guest": 0.00, "gnice": 0.00, "idle": 100.00},
						{"cpu": "15", "usr": 0.00, "nice": 0.00, "sys": 0.00, "iowait": 0.00, "irq": 0.00, "soft": 0.00, "steal": 0.00, "guest": 0.00, "gnice": 0.00, "idle": 100.00}
					]
				},
				{
					"timestamp": "09:59:32 PM",
					"cpu-load": [
						{"cpu": "0", "usr": 0.00, "nice": 0.00, "sys": 0.00, "iowait": 0.00, "irq": 0.00, "soft": 0.56, "steal": 0.00, "guest": 0.00, "gnice": 0.00, "idle": 99.44},
						{"cpu": "1", "usr": 0.00, "nice": 0.00, "sys": 0.00, "iowait": 0.00, "irq": 0.00, "soft": 0.00, "steal": 0.00, "guest": 0.00, "gnice": 0.00, "idle": 100.00},
						{"cpu": "2", "usr": 0.00, "nice": 0.00, "sys": 0.00, "iowait": 0.00, "irq": 0.00, "soft": 0.52, "steal": 0.00, "guest": 0.00, "gnice": 0.00, "idle": 99.48},
						{"cpu": "3", "usr": 0.00, "nice": 0.00, "sys": 0.00, "iowait": 0.00, "irq": 0.00, "soft": 0.00, "steal": 0.00, "guest": 0.00, "gnice": 0.00, "idle": 100.00},
						{"cpu": "4", "usr": 0.00, "nice": 0.00, "sys": 0.00, "iowait": 0.00, "irq": 0.00, "soft": 0.00, "steal": 0.00, "guest": 0.00, "gnice": 0.00, "idle": 100.00},
						{"cpu": "5", "usr": 0.00, "nice": 0.00, "sys": 0.00, "iowait": 0.00, "irq": 0.00, "soft": 0.00, "steal": 0.00, "guest": 0.00, "gnice": 0.00, "idle": 100.00},
						{"cpu": "6", "usr": 0.00, "nice": 0.00, "sys": 0.00, "iowait": 0.00, "irq": 0.00, "soft": 0.00, "steal": 0.00, "guest": 0.00, "gnice": 0.00, "idle": 100.00},
						{"cpu": "7", "usr": 0.00, "nice": 0.00, "sys": 0.00, "iowait": 0.00, "irq": 0.00, "soft": 0.00, "steal": 0.00, "guest": 0.00, "gnice": 0.00, "idle": 100.00},
						{"cpu": "8", "usr": 0.00, "nice": 0.00, "sys": 0.00, "iowait": 0.00, "irq": 0.00, "soft": 0.00, "steal": 0.00, "guest": 0.00, "gnice": 0.00, "idle": 100.00},
						{"cpu": "9", "usr": 0.00, "nice": 0.00, "sys": 0.00, "iowait": 0.00, "irq": 0.00, "soft": 0.00, "steal": 0.00, "guest": 0.00, "gnice": 0.00, "idle": 100.00},
						{"cpu": "10", "usr": 0.62, "nice": 0.00, "sys": 11.73, "iowait": 0.00, "irq": 0.00, "soft": 0.62, "steal": 0.00, "guest": 0.00, "gnice": 0.00, "idle": 87.04},
						{"cpu": "11", "usr": 0.00, "nice": 0.00, "sys": 0.00, "iowait": 0.00, "irq": 0.00, "soft": 0.00, "steal": 0.00, "guest": 0.00, "gnice": 0.00, "idle": 100.00},
						{"cpu": "12", "usr": 0.00, "nice": 0.00, "sys": 0.00, "iowait": 0.00, "irq": 0.00, "soft": 0.00, "steal": 0.00, "guest": 0.00, "gnice": 0.00, "idle": 100.00},
						{"cpu": "13", "usr": 0.00, "nice": 0.00, "sys": 0.00, "iowait": 0.00, "irq": 0.00, "soft": 0.00, "steal": 0.00, "guest": 0.00, "gnice": 0.00, "idle": 100.00},
						{"cpu": "14", "usr": 0.00, "nice": 0.00, "sys": 0.00, "iowait": 0.00, "irq": 0.00, "soft": 0.00, "steal": 0.00, "guest": 0.00, "gnice": 0.00, "idle": 100.00},
						{"cpu": "15", "usr": 0.00, "nice": 0.00, "sys": 0.00, "iowait": 0.00, "irq": 0.00, "soft": 0.00, "steal": 0.00, "guest": 0.00, "gnice": 0.00, "idle": 100.00}
					]
				},
				{
					"timestamp": "09:59:34 PM",
					"cpu-load": [
						{"cpu": "0", "usr": 0.00, "nice": 0.00, "sys": 0.00, "iowait": 0.00, "irq": 0.00, "soft": 0.56, "steal": 0.00, "guest": 0.00, "gnice": 0.00, "idle": 99.44},
						{"cpu": "1", "usr": 0.00, "nice": 0.00, "sys": 0.00, "iowait": 0.00, "irq": 0.00, "soft": 0.00, "steal": 0.00, "guest": 0.00, "gnice": 0.00, "idle": 100.00},
						{"cpu": "2", "usr": 0.00, "nice": 0.00, "sys": 0.00, "iowait": 0.00, "irq": 0.00, "soft": 0.00, "steal": 0.00, "guest": 0.00, "gnice": 0.00, "idle": 100.00},
						{"cpu": "3", "usr": 0.00, "nice": 0.00, "sys": 0.00, "iowait": 0.00, "irq": 0.00, "soft": 0.00, "steal": 0.00, "guest": 0.00, "gnice": 0.00, "idle": 100.00},
						{"cpu": "4", "usr": 0.00, "nice": 0.00, "sys": 0.00, "iowait": 0.00, "irq": 0.00, "soft": 0.00, "steal": 0.00, "guest": 0.00, "gnice": 0.00, "idle": 100.00},
						{"cpu": "5", "usr": 0.00, "nice": 0.00, "sys": 0.00, "iowait": 0.00, "irq": 0.00, "soft": 0.00, "steal": 0.00, "guest": 0.00, "gnice": 0.00, "idle": 100.00},
						{"cpu": "6", "usr": 0.00, "nice": 0.00, "sys": 0.00, "iowait": 0.00, "irq": 0.00, "soft": 0.00, "steal": 0.00, "guest": 0.00, "gnice": 0.00, "idle": 100.00},
						{"cpu": "7", "usr": 0.00, "nice": 0.00, "sys": 0.00, "iowait": 0.00, "irq": 0.00, "soft": 0.00, "steal": 0.00, "guest": 0.00, "gnice": 0.00, "idle": 100.00},
						{"cpu": "8", "usr": 0.00, "nice": 0.00, "sys": 0.00, "iowait": 0.00, "irq": 0.00, "soft": 0.00, "steal": 0.00, "guest": 0.00, "gnice": 0.00, "idle": 100.00},
						{"cpu": "9", "usr": 0.00, "nice": 0.00, "sys": 0.00, "iowait": 0.00, "irq": 0.00, "soft": 0.00, "steal": 0.00, "guest": 0.00, "gnice": 0.00, "idle": 100.00},
						{"cpu": "10", "usr": 0.62, "nice": 0.00, "sys": 10.56, "iowait": 0.00, "irq": 0.00, "soft": 0.62, "steal": 0.00, "guest": 0.00, "gnice": 0.00, "idle": 88.20},
						{"cpu": "11", "usr": 0.00, "nice": 0.00, "sys": 0.00, "iowait": 0.00, "irq": 0.00, "soft": 0.00, "steal": 0.00, "guest": 0.00, "gnice": 0.00, "idle": 100.00},
						{"cpu": "12", "usr": 0.00, "nice": 0.00, "sys": 0.00, "iowait": 0.00, "irq": 0.00, "soft": 0.00, "steal": 0.00, "guest": 0.00, "gnice": 0.00, "idle": 100.00},
						{"cpu": "13", "usr": 0.00, "nice": 0.00, "sys": 0.00, "iowait": 0.00, "irq": 0.00, "soft": 0.00, "steal": 0.00, "guest": 0.00, "gnice": 0.00, "idle": 100.00},
						{"cpu": "14", "usr": 0.00, "nice": 0.00, "sys": 0.00, "iowait": 0.00, "irq": 0.00, "soft": 0.00, "steal": 0.00, "guest": 0.00, "gnice": 0.00, "idle": 100.00},
						{"cpu": "15", "usr": 0.00, "nice": 0.00, "sys": 0.00, "iowait": 0.00, "irq": 0.00, "soft": 0.00, "steal": 0.00, "guest": 0.00, "gnice": 0.00, "idle": 100.00}
					]
				},
				{
					"timestamp": "09:59:36 PM",
					"cpu-load": [
						{"cpu": "0", "usr": 0.00, "nice": 0.00, "sys": 0.00, "iowait": 0.00, "irq": 0.00, "soft": 0.55, "steal": 0.00, "guest": 0.00, "gnice": 0.00, "idle": 99.45},
						{"cpu": "1", "usr": 0.00, "nice": 0.00, "sys": 0.00, "iowait": 0.00, "irq": 0.00, "soft": 0.00, "steal": 0.00, "guest": 0.00, "gnice": 0.00, "idle": 100.00},
						{"cpu": "2", "usr": 0.00, "nice": 0.00, "sys": 0.00, "iowait": 0.00, "irq": 0.00, "soft": 0.00, "steal": 0.00, "guest": 0.00, "gnice": 0.00, "idle": 100.00},
						{"cpu": "3", "usr": 0.00, "nice": 0.00, "sys": 0.00, "iowait": 0.00, "irq": 0.00, "soft": 0.00, "steal": 0.00, "guest": 0.00, "gnice": 0.00, "idle": 100.00},
						{"cpu": "4", "usr": 0.00, "nice": 0.00, "sys": 0.00, "iowait": 0.00, "irq": 0.00, "soft": 0.00, "steal": 0.00, "guest": 0.00, "gnice": 0.00, "idle": 100.00},
						{"cpu": "5", "usr": 0.00, "nice": 0.00, "sys": 0.00, "iowait": 0.00, "irq": 0.00, "soft": 0.00, "steal": 0.00, "guest": 0.00, "gnice": 0.00, "idle": 100.00},
						{"cpu": "6", "usr": 0.00, "nice": 0.00, "sys": 0.00, "iowait": 0.00, "irq": 0.00, "soft": 0.00, "steal": 0.00, "guest": 0.00, "gnice": 0.00, "idle": 100.00},
						{"cpu": "7", "usr": 0.00, "nice": 0.00, "sys": 0.00, "iowait": 0.00, "irq": 0.00, "soft": 0.00, "steal": 0.00, "guest": 0.00, "gnice": 0.00, "idle": 100.00},
						{"cpu": "8", "usr": 0.00, "nice": 0.00, "sys": 0.00, "iowait": 0.00, "irq": 0.00, "soft": 0.00, "steal": 0.00, "guest": 0.00, "gnice": 0.00, "idle": 100.00},
						{"cpu": "9", "usr": 0.00, "nice": 0.00, "sys": 0.00, "iowait": 0.00, "irq": 0.00, "soft": 0.00, "steal": 0.00, "guest": 0.00, "gnice": 0.00, "idle": 100.00},
						{"cpu": "10", "usr": 0.00, "nice": 0.00, "sys": 10.98, "iowait": 0.00, "irq": 0.00, "soft": 1.22, "steal": 0.00, "guest": 0.00, "gnice": 0.00, "idle": 87.80},
						{"cpu": "11", "usr": 0.00, "nice": 0.00, "sys": 0.00, "iowait": 0.00, "irq": 0.00, "soft": 0.00, "steal": 0.00, "guest": 0.00, "gnice": 0.00, "idle": 100.00},
						{"cpu": "12", "usr": 0.00, "nice": 0.00, "sys": 0.00, "iowait": 0.00, "irq": 0.00, "soft": 0.00, "steal": 0.00, "guest": 0.00, "gnice": 0.00, "idle": 100.00},
						{"cpu": "13", "usr": 0.00, "nice": 0.00, "sys": 0.00, "iowait": 0.00, "irq": 0.00, "soft": 0.00, "steal": 0.00, "guest": 0.00, "gnice": 0.00, "idle": 100.00},
						{"cpu": "14", "usr": 0.00, "nice": 0.00, "sys": 0.00, "iowait": 0.00, "irq": 0.00, "soft": 0.00, "steal": 0.00, "guest": 0.00, "gnice": 0.00, "idle": 100.00},
						{"cpu": "15", "usr": 0.00, "nice": 0.00, "sys": 0.50, "iowait": 0.00, "irq": 0.00, "soft": 0.00, "steal": 0.00, "guest": 0.00, "gnice": 0.00, "idle": 99.50}
					]
				},
				{
					"timestamp": "09:59:38 PM",
					"cpu-load": [
						{"cpu": "0", "usr": 0.00, "nice": 0.00, "sys": 0.00, "iowait": 0.00, "irq": 0.00, "soft": 0.56, "steal": 0.00, "guest": 0.00, "gnice": 0.00, "idle": 99.44},
						{"cpu": "1", "usr": 0.00, "nice": 0.00, "sys": 0.00, "iowait": 0.00, "irq": 0.00, "soft": 0.00, "steal": 0.00, "guest": 0.00, "gnice": 0.00, "idle": 100.00},
						{"cpu": "2", "usr": 0.52, "nice": 0.00, "sys": 0.00, "iowait": 0.00, "irq": 0.00, "soft": 0.52, "steal": 0.00, "guest": 0.00, "gnice": 0.00, "idle": 98.97},
						{"cpu": "3", "usr": 0.00, "nice": 0.00, "sys": 0.00, "iowait": 0.00, "irq": 0.00, "soft": 0.00, "steal": 0.00, "guest": 0.00, "gnice": 0.00, "idle": 100.00},
						{"cpu": "4", "usr": 0.00, "nice": 0.00, "sys": 0.00, "iowait": 0.00, "irq": 0.00, "soft": 0.00, "steal": 0.00, "guest": 0.00, "gnice": 0.00, "idle": 100.00},
						{"cpu": "5", "usr": 0.00, "nice": 0.00, "sys": 0.00, "iowait": 0.00, "irq": 0.00, "soft": 0.00, "steal": 0.00, "guest": 0.00, "gnice": 0.00, "idle": 100.00},
						{"cpu": "6", "usr": 0.00, "nice": 0.00, "sys": 0.00, "iowait": 0.00, "irq": 0.00, "soft": 0.00, "steal": 0.00, "guest": 0.00, "gnice": 0.00, "idle": 100.00},
						{"cpu": "7", "usr": 0.00, "nice": 0.00, "sys": 0.00, "iowait": 0.00, "irq": 0.00, "soft": 0.00, "steal": 0.00, "guest": 0.00, "gnice": 0.00, "idle": 100.00},
						{"cpu": "8", "usr": 0.00, "nice": 0.00, "sys": 0.00, "iowait": 0.00, "irq": 0.00, "soft": 0.00, "steal": 0.00, "guest": 0.00, "gnice": 0.00, "idle": 100.00},
						{"cpu": "9", "usr": 0.00, "nice": 0.00, "sys": 0.00, "iowait": 0.00, "irq": 0.00, "soft": 0.00, "steal": 0.00, "guest": 0.00, "gnice": 0.00, "idle": 100.00},
						{"cpu": "10", "usr": 0.62, "nice": 0.00, "sys": 10.49, "iowait": 0.00, "irq": 0.00, "soft": 0.62, "steal": 0.00, "guest": 0.00, "gnice": 0.00, "idle": 88.27},
						{"cpu": "11", "usr": 0.00, "nice": 0.00, "sys": 0.00, "iowait": 0.00, "irq": 0.00, "soft": 0.00, "steal": 0.00, "guest": 0.00, "gnice": 0.00, "idle": 100.00},
						{"cpu": "12", "usr": 0.00, "nice": 0.00, "sys": 0.00, "iowait": 0.00, "irq": 0.00, "soft": 0.00, "steal": 0.00, "guest": 0.00, "gnice": 0.00, "idle": 100.00},
						{"cpu": "13", "usr": 0.00, "nice": 0.00, "sys": 0.00, "iowait": 0.00, "irq": 0.00, "soft": 0.00, "steal": 0.00, "guest": 0.00, "gnice": 0.00, "idle": 100.00},
						{"cpu": "14", "usr": 0.00, "nice": 0.00, "sys": 0.00, "iowait": 0.00, "irq": 0.00, "soft": 0.00, "steal": 0.00, "guest": 0.00, "gnice": 0.00, "idle": 100.00},
						{"cpu": "15", "usr": 0.00, "nice": 0.00, "sys": 0.00, "iowait": 0.00, "irq": 0.00, "soft": 0.00, "steal": 0.00, "guest": 0.00, "gnice": 0.00, "idle": 100.00}
					]
				},
				{
					"timestamp": "09:59:40 PM",
					"cpu-load": [
						{"cpu": "0", "usr": 0.00, "nice": 0.00, "sys": 0.00, "iowait": 0.00, "irq": 0.00, "soft": 0.00, "steal": 0.00, "guest": 0.00, "gnice": 0.00, "idle": 100.00},
						{"cpu": "1", "usr": 0.00, "nice": 0.00, "sys": 0.00, "iowait": 0.00, "irq": 0.00, "soft": 0.00, "steal": 0.00, "guest": 0.00, "gnice": 0.00, "idle": 100.00},
						{"cpu": "2", "usr": 0.00, "nice": 0.00, "sys": 0.00, "iowait": 0.00, "irq": 0.00, "soft": 0.00, "steal": 0.00, "guest": 0.00, "gnice": 0.00, "idle": 100.00},
						{"cpu": "3", "usr": 0.00, "nice": 0.00, "sys": 0.00, "iowait": 0.00, "irq": 0.00, "soft": 0.00, "steal": 0.00, "guest": 0.00, "gnice": 0.00, "idle": 100.00},
						{"cpu": "4", "usr": 0.00, "nice": 0.00, "sys": 0.00, "iowait": 0.00, "irq": 0.00, "soft": 0.00, "steal": 0.00, "guest": 0.00, "gnice": 0.00, "idle": 100.00},
						{"cpu": "5", "usr": 0.00, "nice": 0.00, "sys": 0.50, "iowait": 0.00, "irq": 0.00, "soft": 0.00, "steal": 0.00, "guest": 0.00, "gnice": 0.00, "idle": 99.50},
						{"cpu": "6", "usr": 0.00, "nice": 0.00, "sys": 0.00, "iowait": 0.00, "irq": 0.00, "soft": 0.00, "steal": 0.00, "guest": 0.00, "gnice": 0.00, "idle": 100.00},
						{"cpu": "7", "usr": 0.00, "nice": 0.00, "sys": 0.00, "iowait": 0.00, "irq": 0.00, "soft": 0.00, "steal": 0.00, "guest": 0.00, "gnice": 0.00, "idle": 100.00},
						{"cpu": "8", "usr": 0.00, "nice": 0.00, "sys": 0.00, "iowait": 0.00, "irq": 0.00, "soft": 0.00, "steal": 0.00, "guest": 0.00, "gnice": 0.00, "idle": 100.00},
						{"cpu": "9", "usr": 0.00, "nice": 0.00, "sys": 0.00, "iowait": 0.00, "irq": 0.00, "soft": 0.00, "steal": 0.00, "guest": 0.00, "gnice": 0.00, "idle": 100.00},
						{"cpu": "10", "usr": 0.00, "nice": 0.00, "sys": 10.19, "iowait": 0.00, "irq": 0.00, "soft": 0.64, "steal": 0.00, "guest": 0.00, "gnice": 0.00, "idle": 89.17},
						{"cpu": "11", "usr": 0.00, "nice": 0.00, "sys": 0.00, "iowait": 0.00, "irq": 0.00, "soft": 0.00, "steal": 0.00, "guest": 0.00, "gnice": 0.00, "idle": 100.00},
						{"cpu": "12", "usr": 0.00, "nice": 0.00, "sys": 0.00, "iowait": 0.00, "irq": 0.00, "soft": 0.00, "steal": 0.00, "guest": 0.00, "gnice": 0.00, "idle": 100.00},
						{"cpu": "13", "usr": 0.00, "nice": 0.00, "sys": 0.00, "iowait": 0.00, "irq": 0.00, "soft": 0.00, "steal": 0.00, "guest": 0.00, "gnice": 0.00, "idle": 100.00},
						{"cpu": "14", "usr": 0.00, "nice": 0.00, "sys": 0.00, "iowait": 0.00, "irq": 0.00, "soft": 0.00, "steal": 0.00, "guest": 0.00, "gnice": 0.00, "idle": 100.00},
						{"cpu": "15", "usr": 0.00, "nice": 0.00, "sys": 0.00, "iowait": 0.00, "irq": 0.00, "soft": 0.00, "steal": 0.00, "guest": 0.00, "gnice": 0.00, "idle": 100.00}
					]
				},
				{
					"timestamp": "09:59:42 PM",
					"cpu-load": [
						{"cpu": "0", "usr": 0.00, "nice": 0.00, "sys": 0.00, "iowait": 0.00, "irq": 0.00, "soft": 0.56, "steal": 0.00, "guest": 0.00, "gnice": 0.00, "idle": 99.44},
						{"cpu": "1", "usr": 0.00, "nice": 0.00, "sys": 0.00, "iowait": 0.00, "irq": 0.00, "soft": 0.00, "steal": 0.00, "guest": 0.00, "gnice": 0.00, "idle": 100.00},
						{"cpu": "2", "usr": 0.00, "nice": 0.00, "sys": 0.00, "iowait": 0.00, "irq": 0.00, "soft": 0.52, "steal": 0.00, "guest": 0.00, "gnice": 0.00, "idle": 99.48},
						{"cpu": "3", "usr": 0.00, "nice": 0.00, "sys": 0.00, "iowait": 0.00, "irq": 0.00, "soft": 0.00, "steal": 0.00, "guest": 0.00, "gnice": 0.00, "idle": 100.00},
						{"cpu": "4", "usr": 0.00, "nice": 0.00, "sys": 0.00, "iowait": 0.00, "irq": 0.00, "soft": 0.00, "steal": 0.00, "guest": 0.00, "gnice": 0.00, "idle": 100.00},
						{"cpu": "5", "usr": 0.00, "nice": 0.00, "sys": 0.00, "iowait": 0.00, "irq": 0.00, "soft": 0.00, "steal": 0.00, "guest": 0.00, "gnice": 0.00, "idle": 100.00},
						{"cpu": "6", "usr": 0.00, "nice": 0.00, "sys": 0.00, "iowait": 0.00, "irq": 0.00, "soft": 0.00, "steal": 0.00, "guest": 0.00, "gnice": 0.00, "idle": 100.00},
						{"cpu": "7", "usr": 0.00, "nice": 0.00, "sys": 0.00, "iowait": 0.00, "irq": 0.00, "soft": 0.00, "steal": 0.00, "guest": 0.00, "gnice": 0.00, "idle": 100.00},
						{"cpu": "8", "usr": 0.00, "nice": 0.00, "sys": 0.00, "iowait": 0.00, "irq": 0.00, "soft": 0.00, "steal": 0.00, "guest": 0.00, "gnice": 0.00, "idle": 100.00},
						{"cpu": "9", "usr": 0.00, "nice": 0.00, "sys": 0.00, "iowait": 0.00, "irq": 0.00, "soft": 0.00, "steal": 0.00, "guest": 0.00, "gnice": 0.00, "idle": 100.00},
						{"cpu": "10", "usr": 0.63, "nice": 0.00, "sys": 10.69, "iowait": 0.00, "irq": 0.00, "soft": 0.00, "steal": 0.00, "guest": 0.00, "gnice": 0.00, "idle": 88.68},
						{"cpu": "11", "usr": 0.00, "nice": 0.00, "sys": 0.00, "iowait": 0.00, "irq": 0.00, "soft": 0.00, "steal": 0.00, "guest": 0.00, "gnice": 0.00, "idle": 100.00},
						{"cpu": "12", "usr": 0.00, "nice": 0.00, "sys": 0.00, "iowait": 0.00, "irq": 0.00, "soft": 0.00, "steal": 0.00, "guest": 0.00, "gnice": 0.00, "idle": 100.00},
						{"cpu": "13", "usr": 0.00, "nice": 0.00, "sys": 0.00, "iowait": 0.00, "irq": 0.00, "soft": 0.00, "steal": 0.00, "guest": 0.00, "gnice": 0.00, "idle": 100.00},
						{"cpu": "14", "usr": 0.00, "nice": 0.00, "sys": 0.00, "iowait": 0.00, "irq": 0.00, "soft": 0.00, "steal": 0.00, "guest": 0.00, "gnice": 0.00, "idle": 100.00},
						{"cpu": "15", "usr": 0.50, "nice": 0.00, "sys": 0.00, "iowait": 0.00, "irq": 0.00, "soft": 0.00, "steal": 0.00, "guest": 0.00, "gnice": 0.00, "idle": 99.50}
					]
				},
				{
					"timestamp": "09:59:44 PM",
					"cpu-load": [
						{"cpu": "0", "usr": 0.00, "nice": 0.00, "sys": 0.00, "iowait": 0.00, "irq": 0.00, "soft": 0.56, "steal": 0.00, "guest": 0.00, "gnice": 0.00, "idle": 99.44},
						{"cpu": "1", "usr": 0.00, "nice": 0.00, "sys": 0.00, "iowait": 0.00, "irq": 0.00, "soft": 0.00, "steal": 0.00, "guest": 0.00, "gnice": 0.00, "idle": 100.00},
						{"cpu": "2", "usr": 0.00, "nice": 0.00, "sys": 0.00, "iowait": 0.00, "irq": 0.00, "soft": 0.00, "steal": 0.00, "guest": 0.00, "gnice": 0.00, "idle": 100.00},
						{"cpu": "3", "usr": 0.50, "nice": 0.00, "sys": 0.00, "iowait": 0.00, "irq": 0.00, "soft": 0.00, "steal": 0.00, "guest": 0.00, "gnice": 0.00, "idle": 99.50},
						{"cpu": "4", "usr": 0.50, "nice": 0.00, "sys": 0.00, "iowait": 0.00, "irq": 0.00, "soft": 0.00, "steal": 0.00, "guest": 0.00, "gnice": 0.00, "idle": 99.50},
						{"cpu": "5", "usr": 0.00, "nice": 0.00, "sys": 0.00, "iowait": 0.00, "irq": 0.00, "soft": 0.00, "steal": 0.00, "guest": 0.00, "gnice": 0.00, "idle": 100.00},
						{"cpu": "6", "usr": 0.00, "nice": 0.00, "sys": 0.00, "iowait": 0.00, "irq": 0.00, "soft": 0.00, "steal": 0.00, "guest": 0.00, "gnice": 0.00, "idle": 100.00},
						{"cpu": "7", "usr": 0.50, "nice": 0.00, "sys": 0.00, "iowait": 0.00, "irq": 0.00, "soft": 0.00, "steal": 0.00, "guest": 0.00, "gnice": 0.00, "idle": 99.50},
						{"cpu": "8", "usr": 0.00, "nice": 0.00, "sys": 0.00, "iowait": 0.00, "irq": 0.00, "soft": 0.00, "steal": 0.00, "guest": 0.00, "gnice": 0.00, "idle": 100.00},
						{"cpu": "9", "usr": 0.00, "nice": 0.00, "sys": 0.00, "iowait": 0.00, "irq": 0.00, "soft": 0.00, "steal": 0.00, "guest": 0.00, "gnice": 0.00, "idle": 100.00},
						{"cpu": "10", "usr": 0.00, "nice": 0.00, "sys": 11.25, "iowait": 0.00, "irq": 0.00, "soft": 0.62, "steal": 0.00, "guest": 0.00, "gnice": 0.00, "idle": 88.12},
						{"cpu": "11", "usr": 0.00, "nice": 0.00, "sys": 0.00, "iowait": 0.00, "irq": 0.00, "soft": 0.00, "steal": 0.00, "guest": 0.00, "gnice": 0.00, "idle": 100.00},
						{"cpu": "12", "usr": 0.00, "nice": 0.00, "sys": 0.00, "iowait": 0.00, "irq": 0.00, "soft": 0.00, "steal": 0.00, "guest": 0.00, "gnice": 0.00, "idle": 100.00},
						{"cpu": "13", "usr": 0.00, "nice": 0.00, "sys": 0.00, "iowait": 0.00, "irq": 0.00, "soft": 0.00, "steal": 0.00, "guest": 0.00, "gnice": 0.00, "idle": 100.00},
						{"cpu": "14", "usr": 0.00, "nice": 0.00, "sys": 0.00, "iowait": 0.00, "irq": 0.00, "soft": 0.00, "steal": 0.00, "guest": 0.00, "gnice": 0.00, "idle": 100.00},
						{"cpu": "15", "usr": 0.00, "nice": 0.00, "sys": 0.00, "iowait": 0.00, "irq": 0.00, "soft": 0.00, "steal": 0.00, "guest": 0.00, "gnice": 0.00, "idle": 100.00}
					]
				},
				{
					"timestamp": "09:59:46 PM",
					"cpu-load": [
						{"cpu": "0", "usr": 0.00, "nice": 0.00, "sys": 0.00, "iowait": 0.00, "irq": 0.00, "soft": 1.66, "steal": 0.00, "guest": 0.00, "gnice": 0.00, "idle": 98.34},
						{"cpu": "1", "usr": 0.00, "nice": 0.00, "sys": 0.00, "iowait": 0.00, "irq": 0.00, "soft": 0.00, "steal": 0.00, "guest": 0.00, "gnice": 0.00, "idle": 100.00},
						{"cpu": "2", "usr": 0.00, "nice": 0.00, "sys": 0.00, "iowait": 0.00, "irq": 0.00, "soft": 0.00, "steal": 0.00, "guest": 0.00, "gnice": 0.00, "idle": 100.00},
						{"cpu": "3", "usr": 0.00, "nice": 0.00, "sys": 0.00, "iowait": 0.00, "irq": 0.00, "soft": 0.00, "steal": 0.00, "guest": 0.00, "gnice": 0.00, "idle": 100.00},
						{"cpu": "4", "usr": 0.00, "nice": 0.00, "sys": 0.00, "iowait": 0.00, "irq": 0.00, "soft": 0.00, "steal": 0.00, "guest": 0.00, "gnice": 0.00, "idle": 100.00},
						{"cpu": "5", "usr": 0.00, "nice": 0.00, "sys": 0.00, "iowait": 0.00, "irq": 0.00, "soft": 0.00, "steal": 0.00, "guest": 0.00, "gnice": 0.00, "idle": 100.00},
						{"cpu": "6", "usr": 0.00, "nice": 0.00, "sys": 0.00, "iowait": 0.00, "irq": 0.00, "soft": 0.00, "steal": 0.00, "guest": 0.00, "gnice": 0.00, "idle": 100.00},
						{"cpu": "7", "usr": 0.00, "nice": 0.00, "sys": 0.00, "iowait": 0.00, "irq": 0.00, "soft": 0.00, "steal": 0.00, "guest": 0.00, "gnice": 0.00, "idle": 100.00},
						{"cpu": "8", "usr": 0.00, "nice": 0.00, "sys": 0.00, "iowait": 0.00, "irq": 0.00, "soft": 0.00, "steal": 0.00, "guest": 0.00, "gnice": 0.00, "idle": 100.00},
						{"cpu": "9", "usr": 0.00, "nice": 0.00, "sys": 0.00, "iowait": 0.00, "irq": 0.00, "soft": 0.00, "steal": 0.00, "guest": 0.00, "gnice": 0.00, "idle": 100.00},
						{"cpu": "10", "usr": 0.00, "nice": 0.00, "sys": 10.13, "iowait": 0.00, "irq": 0.00, "soft": 0.63, "steal": 0.00, "guest": 0.00, "gnice": 0.00, "idle": 89.24},
						{"cpu": "11", "usr": 0.00, "nice": 0.00, "sys": 0.00, "iowait": 0.00, "irq": 0.00, "soft": 0.00, "steal": 0.00, "guest": 0.00, "gnice": 0.00, "idle": 100.00},
						{"cpu": "12", "usr": 0.00, "nice": 0.00, "sys": 0.00, "iowait": 0.00, "irq": 0.00, "soft": 0.00, "steal": 0.00, "guest": 0.00, "gnice": 0.00, "idle": 100.00},
						{"cpu": "13", "usr": 0.00, "nice": 0.00, "sys": 0.00, "iowait": 0.00, "irq": 0.00, "soft": 0.00, "steal": 0.00, "guest": 0.00, "gnice": 0.00, "idle": 100.00},
						{"cpu": "14", "usr": 0.00, "nice": 0.00, "sys": 0.00, "iowait": 0.00, "irq": 0.00, "soft": 0.00, "steal": 0.00, "guest": 0.00, "gnice": 0.00, "idle": 100.00},
						{"cpu": "15", "usr": 0.00, "nice": 0.00, "sys": 0.00, "iowait": 0.00, "irq": 0.00, "soft": 0.00, "steal": 0.00, "guest": 0.00, "gnice": 0.00, "idle": 100.00}
					]
				},
				{
					"timestamp": "09:59:48 PM",
					"cpu-load": [
						{"cpu": "0", "usr": 0.00, "nice": 0.00, "sys": 0.00, "iowait": 0.00, "irq": 0.00, "soft": 0.56, "steal": 0.00, "guest": 0.00, "gnice": 0.00, "idle": 99.44},
						{"cpu": "1", "usr": 0.00, "nice": 0.00, "sys": 0.00, "iowait": 0.00, "irq": 0.00, "soft": 0.00, "steal": 0.00, "guest": 0.00, "gnice": 0.00, "idle": 100.00},
						{"cpu": "2", "usr": 0.00, "nice": 0.00, "sys": 0.00, "iowait": 0.00, "irq": 0.00, "soft": 0.00, "steal": 0.00, "guest": 0.00, "gnice": 0.00, "idle": 100.00},
						{"cpu": "3", "usr": 0.00, "nice": 0.00, "sys": 0.00, "iowait": 0.00, "irq": 0.00, "soft": 0.00, "steal": 0.00, "guest": 0.00, "gnice": 0.00, "idle": 100.00},
						{"cpu": "4", "usr": 0.00, "nice": 0.00, "sys": 0.00, "iowait": 0.00, "irq": 0.00, "soft": 0.00, "steal": 0.00, "guest": 0.00, "gnice": 0.00, "idle": 100.00},
						{"cpu": "5", "usr": 0.00, "nice": 0.00, "sys": 0.50, "iowait": 0.00, "irq": 0.00, "soft": 0.00, "steal": 0.00, "guest": 0.00, "gnice": 0.00, "idle": 99.50},
						{"cpu": "6", "usr": 0.00, "nice": 0.00, "sys": 0.00, "iowait": 0.00, "irq": 0.00, "soft": 0.00, "steal": 0.00, "guest": 0.00, "gnice": 0.00, "idle": 100.00},
						{"cpu": "7", "usr": 0.00, "nice": 0.00, "sys": 0.00, "iowait": 0.00, "irq": 0.00, "soft": 0.00, "steal": 0.00, "guest": 0.00, "gnice": 0.00, "idle": 100.00},
						{"cpu": "8", "usr": 0.00, "nice": 0.00, "sys": 0.00, "iowait": 0.00, "irq": 0.00, "soft": 0.00, "steal": 0.00, "guest": 0.00, "gnice": 0.00, "idle": 100.00},
						{"cpu": "9", "usr": 0.00, "nice": 0.00, "sys": 0.00, "iowait": 0.00, "irq": 0.00, "soft": 0.00, "steal": 0.00, "guest": 0.00, "gnice": 0.00, "idle": 100.00},
						{"cpu": "10", "usr": 0.00, "nice": 0.00, "sys": 11.39, "iowait": 0.00, "irq": 0.00, "soft": 0.00, "steal": 0.00, "guest": 0.00, "gnice": 0.00, "idle": 88.61},
						{"cpu": "11", "usr": 0.00, "nice": 0.00, "sys": 0.00, "iowait": 0.00, "irq": 0.00, "soft": 0.00, "steal": 0.00, "guest": 0.00, "gnice": 0.00, "idle": 100.00},
						{"cpu": "12", "usr": 0.00, "nice": 0.00, "sys": 0.00, "iowait": 0.00, "irq": 0.00, "soft": 0.00, "steal": 0.00, "guest": 0.00, "gnice": 0.00, "idle": 100.00},
						{"cpu": "13", "usr": 0.00, "nice": 0.00, "sys": 0.00, "iowait": 0.00, "irq": 0.00, "soft": 0.00, "steal": 0.00, "guest": 0.00, "gnice": 0.00, "idle": 100.00},
						{"cpu": "14", "usr": 0.00, "nice": 0.00, "sys": 0.00, "iowait": 0.00, "irq": 0.00, "soft": 0.00, "steal": 0.00, "guest": 0.00, "gnice": 0.00, "idle": 100.00},
						{"cpu": "15", "usr": 0.00, "nice": 0.00, "sys": 0.00, "iowait": 0.00, "irq": 0.00, "soft": 0.00, "steal": 0.00, "guest": 0.00, "gnice": 0.00, "idle": 100.00}
					]
				},
				{
					"timestamp": "09:59:50 PM",
					"cpu-load": [
						{"cpu": "0", "usr": 0.00, "nice": 0.00, "sys": 0.00, "iowait": 0.00, "irq": 0.00, "soft": 1.10, "steal": 0.00, "guest": 0.00, "gnice": 0.00, "idle": 98.90},
						{"cpu": "1", "usr": 0.00, "nice": 0.00, "sys": 0.00, "iowait": 0.00, "irq": 0.00, "soft": 0.00, "steal": 0.00, "guest": 0.00, "gnice": 0.00, "idle": 100.00},
						{"cpu": "2", "usr": 0.00, "nice": 0.00, "sys": 0.00, "iowait": 0.00, "irq": 0.00, "soft": 0.00, "steal": 0.00, "guest": 0.00, "gnice": 0.00, "idle": 100.00},
						{"cpu": "3", "usr": 0.00, "nice": 0.00, "sys": 0.00, "iowait": 0.00, "irq": 0.00, "soft": 0.00, "steal": 0.00, "guest": 0.00, "gnice": 0.00, "idle": 100.00},
						{"cpu": "4", "usr": 0.00, "nice": 0.00, "sys": 0.00, "iowait": 0.00, "irq": 0.00, "soft": 0.00, "steal": 0.00, "guest": 0.00, "gnice": 0.00, "idle": 100.00},
						{"cpu": "5", "usr": 0.00, "nice": 0.00, "sys": 0.00, "iowait": 0.00, "irq": 0.00, "soft": 0.00, "steal": 0.00, "guest": 0.00, "gnice": 0.00, "idle": 100.00},
						{"cpu": "6", "usr": 0.00, "nice": 0.00, "sys": 0.00, "iowait": 0.00, "irq": 0.00, "soft": 0.00, "steal": 0.00, "guest": 0.00, "gnice": 0.00, "idle": 100.00},
						{"cpu": "7", "usr": 0.00, "nice": 0.00, "sys": 0.00, "iowait": 0.00, "irq": 0.00, "soft": 0.00, "steal": 0.00, "guest": 0.00, "gnice": 0.00, "idle": 100.00},
						{"cpu": "8", "usr": 0.00, "nice": 0.00, "sys": 0.00, "iowait": 0.00, "irq": 0.00, "soft": 0.00, "steal": 0.00, "guest": 0.00, "gnice": 0.00, "idle": 100.00},
						{"cpu": "9", "usr": 0.00, "nice": 0.00, "sys": 0.00, "iowait": 0.00, "irq": 0.00, "soft": 0.00, "steal": 0.00, "guest": 0.00, "gnice": 0.00, "idle": 100.00},
						{"cpu": "10", "usr": 0.63, "nice": 0.00, "sys": 8.18, "iowait": 0.00, "irq": 0.00, "soft": 1.26, "steal": 0.00, "guest": 0.00, "gnice": 0.00, "idle": 89.94},
						{"cpu": "11", "usr": 0.00, "nice": 0.00, "sys": 0.00, "iowait": 0.00, "irq": 0.00, "soft": 0.00, "steal": 0.00, "guest": 0.00, "gnice": 0.00, "idle": 100.00},
						{"cpu": "12", "usr": 0.00, "nice": 0.00, "sys": 0.00, "iowait": 0.00, "irq": 0.00, "soft": 0.00, "steal": 0.00, "guest": 0.00, "gnice": 0.00, "idle": 100.00},
						{"cpu": "13", "usr": 0.00, "nice": 0.00, "sys": 0.00, "iowait": 0.00, "irq": 0.00, "soft": 0.00, "steal": 0.00, "guest": 0.00, "gnice": 0.00, "idle": 100.00},
						{"cpu": "14", "usr": 0.00, "nice": 0.00, "sys": 0.00, "iowait": 0.00, "irq": 0.00, "soft": 0.00, "steal": 0.00, "guest": 0.00, "gnice": 0.00, "idle": 100.00},
						{"cpu": "15", "usr": 0.00, "nice": 0.00, "sys": 0.00, "iowait": 0.00, "irq": 0.00, "soft": 0.00, "steal": 0.00, "guest": 0.00, "gnice": 0.00, "idle": 100.00}
					]
				},
				{
					"timestamp": "09:59:52 PM",
					"cpu-load": [
						{"cpu": "0", "usr": 0.00, "nice": 0.00, "sys": 0.00, "iowait": 0.00, "irq": 0.00, "soft": 0.00, "steal": 0.00, "guest": 0.00, "gnice": 0.00, "idle": 100.00},
						{"cpu": "1", "usr": 0.00, "nice": 0.00, "sys": 0.00, "iowait": 0.00, "irq": 0.00, "soft": 0.00, "steal": 0.00, "guest": 0.00, "gnice": 0.00, "idle": 100.00},
						{"cpu": "2", "usr": 0.00, "nice": 0.00, "sys": 0.00, "iowait": 0.00, "irq": 0.00, "soft": 0.00, "steal": 0.00, "guest": 0.00, "gnice": 0.00, "idle": 100.00},
						{"cpu": "3", "usr": 0.00, "nice": 0.00, "sys": 0.00, "iowait": 0.00, "irq": 0.00, "soft": 0.00, "steal": 0.00, "guest": 0.00, "gnice": 0.00, "idle": 100.00},
						{"cpu": "4", "usr": 0.00, "nice": 0.00, "sys": 0.00, "iowait": 0.00, "irq": 0.00, "soft": 0.00, "steal": 0.00, "guest": 0.00, "gnice": 0.00, "idle": 100.00},
						{"cpu": "5", "usr": 0.00, "nice": 0.00, "sys": 0.00, "iowait": 0.00, "irq": 0.00, "soft": 0.00, "steal": 0.00, "guest": 0.00, "gnice": 0.00, "idle": 100.00},
						{"cpu": "6", "usr": 0.00, "nice": 0.00, "sys": 0.00, "iowait": 0.00, "irq": 0.00, "soft": 0.00, "steal": 0.00, "guest": 0.00, "gnice": 0.00, "idle": 100.00},
						{"cpu": "7", "usr": 0.00, "nice": 0.00, "sys": 0.00, "iowait": 0.00, "irq": 0.00, "soft": 0.00, "steal": 0.00, "guest": 0.00, "gnice": 0.00, "idle": 100.00},
						{"cpu": "8", "usr": 0.00, "nice": 0.00, "sys": 0.00, "iowait": 0.00, "irq": 0.00, "soft": 0.00, "steal": 0.00, "guest": 0.00, "gnice": 0.00, "idle": 100.00},
						{"cpu": "9", "usr": 0.00, "nice": 0.00, "sys": 0.00, "iowait": 0.00, "irq": 0.00, "soft": 0.00, "steal": 0.00, "guest": 0.00, "gnice": 0.00, "idle": 100.00},
						{"cpu": "10", "usr": 0.62, "nice": 0.00, "sys": 10.00, "iowait": 0.00, "irq": 0.00, "soft": 0.62, "steal": 0.00, "guest": 0.00, "gnice": 0.00, "idle": 88.75},
						{"cpu": "11", "usr": 0.00, "nice": 0.00, "sys": 0.00, "iowait": 0.00, "irq": 0.00, "soft": 0.00, "steal": 0.00, "guest": 0.00, "gnice": 0.00, "idle": 100.00},
						{"cpu": "12", "usr": 0.00, "nice": 0.00, "sys": 0.00, "iowait": 0.00, "irq": 0.00, "soft": 0.00, "steal": 0.00, "guest": 0.00, "gnice": 0.00, "idle": 100.00},
						{"cpu": "13", "usr": 0.00, "nice": 0.00, "sys": 0.00, "iowait": 0.00, "irq": 0.00, "soft": 0.00, "steal": 0.00, "guest": 0.00, "gnice": 0.00, "idle": 100.00},
						{"cpu": "14", "usr": 0.00, "nice": 0.00, "sys": 0.00, "iowait": 0.00, "irq": 0.00, "soft": 0.00, "steal": 0.00, "guest": 0.00, "gnice": 0.00, "idle": 100.00},
						{"cpu": "15", "usr": 0.00, "nice": 0.00, "sys": 0.00, "iowait": 0.00, "irq": 0.00, "soft": 0.00, "steal": 0.00, "guest": 0.00, "gnice": 0.00, "idle": 100.00}
					]
				},
				{
					"timestamp": "09:59:54 PM",
					"cpu-load": [
						{"cpu": "0", "usr": 0.00, "nice": 0.00, "sys": 0.00, "iowait": 0.00, "irq": 0.00, "soft": 1.10, "steal": 0.00, "guest": 0.00, "gnice": 0.00, "idle": 98.90},
						{"cpu": "1", "usr": 0.00, "nice": 0.00, "sys": 0.00, "iowait": 0.00, "irq": 0.00, "soft": 0.00, "steal": 0.00, "guest": 0.00, "gnice": 0.00, "idle": 100.00},
						{"cpu": "2", "usr": 0.00, "nice": 0.00, "sys": 0.00, "iowait": 0.00, "irq": 0.00, "soft": 0.00, "steal": 0.00, "guest": 0.00, "gnice": 0.00, "idle": 100.00},
						{"cpu": "3", "usr": 0.00, "nice": 0.00, "sys": 0.00, "iowait": 0.00, "irq": 0.00, "soft": 0.00, "steal": 0.00, "guest": 0.00, "gnice": 0.00, "idle": 100.00},
						{"cpu": "4", "usr": 0.00, "nice": 0.00, "sys": 0.50, "iowait": 0.00, "irq": 0.00, "soft": 0.00, "steal": 0.00, "guest": 0.00, "gnice": 0.00, "idle": 99.50},
						{"cpu": "5", "usr": 0.00, "nice": 0.00, "sys": 0.00, "iowait": 0.00, "irq": 0.00, "soft": 0.00, "steal": 0.00, "guest": 0.00, "gnice": 0.00, "idle": 100.00},
						{"cpu": "6", "usr": 0.00, "nice": 0.00, "sys": 0.00, "iowait": 0.00, "irq": 0.00, "soft": 0.00, "steal": 0.00, "guest": 0.00, "gnice": 0.00, "idle": 100.00},
						{"cpu": "7", "usr": 0.00, "nice": 0.00, "sys": 0.00, "iowait": 0.00, "irq": 0.00, "soft": 0.00, "steal": 0.00, "guest": 0.00, "gnice": 0.00, "idle": 100.00},
						{"cpu": "8", "usr": 0.00, "nice": 0.00, "sys": 0.00, "iowait": 0.00, "irq": 0.00, "soft": 0.00, "steal": 0.00, "guest": 0.00, "gnice": 0.00, "idle": 100.00},
						{"cpu": "9", "usr": 0.00, "nice": 0.00, "sys": 0.00, "iowait": 0.00, "irq": 0.00, "soft": 0.00, "steal": 0.00, "guest": 0.00, "gnice": 0.00, "idle": 100.00},
						{"cpu": "10", "usr": 0.00, "nice": 0.00, "sys": 11.18, "iowait": 0.00, "irq": 0.00, "soft": 0.62, "steal": 0.00, "guest": 0.00, "gnice": 0.00, "idle": 88.20},
						{"cpu": "11", "usr": 0.00, "nice": 0.00, "sys": 0.00, "iowait": 0.00, "irq": 0.00, "soft": 0.00, "steal": 0.00, "guest": 0.00, "gnice": 0.00, "idle": 100.00},
						{"cpu": "12", "usr": 0.00, "nice": 0.00, "sys": 0.00, "iowait": 0.00, "irq": 0.00, "soft": 0.00, "steal": 0.00, "guest": 0.00, "gnice": 0.00, "idle": 100.00},
						{"cpu": "13", "usr": 0.00, "nice": 0.00, "sys": 0.00, "iowait": 0.00, "irq": 0.00, "soft": 0.00, "steal": 0.00, "guest": 0.00, "gnice": 0.00, "idle": 100.00},
						{"cpu": "14", "usr": 0.00, "nice": 0.00, "sys": 0.00, "iowait": 0.00, "irq": 0.00, "soft": 0.00, "steal": 0.00, "guest": 0.00, "gnice": 0.00, "idle": 100.00},
						{"cpu": "15", "usr": 0.00, "nice": 0.00, "sys": 0.00, "iowait": 0.00, "irq": 0.00, "soft": 0.00, "steal": 0.00, "guest": 0.00, "gnice": 0.00, "idle": 100.00}
					]
				},
				{
					"timestamp": "09:59:56 PM",
					"cpu-load": [
						{"cpu": "0", "usr": 0.00, "nice": 0.00, "sys": 0.00, "iowait": 0.00, "irq": 0.00, "soft": 1.11, "steal": 0.00, "guest": 0.00, "gnice": 0.00, "idle": 98.89},
						{"cpu": "1", "usr": 0.00, "nice": 0.00, "sys": 0.00, "iowait": 0.00, "irq": 0.00, "soft": 0.00, "steal": 0.00, "guest": 0.00, "gnice": 0.00, "idle": 100.00},
						{"cpu": "2", "usr": 0.00, "nice": 0.00, "sys": 0.00, "iowait": 0.00, "irq": 0.00, "soft": 0.00, "steal": 0.00, "guest": 0.00, "gnice": 0.00, "idle": 100.00},
						{"cpu": "3", "usr": 0.00, "nice": 0.00, "sys": 0.00, "iowait": 0.00, "irq": 0.00, "soft": 0.00, "steal": 0.00, "guest": 0.00, "gnice": 0.00, "idle": 100.00},
						{"cpu": "4", "usr": 0.00, "nice": 0.00, "sys": 0.00, "iowait": 0.00, "irq": 0.00, "soft": 0.00, "steal": 0.00, "guest": 0.00, "gnice": 0.00, "idle": 100.00},
						{"cpu": "5", "usr": 0.00, "nice": 0.00, "sys": 0.00, "iowait": 0.00, "irq": 0.00, "soft": 0.00, "steal": 0.00, "guest": 0.00, "gnice": 0.00, "idle": 100.00},
						{"cpu": "6", "usr": 0.00, "nice": 0.00, "sys": 0.00, "iowait": 0.00, "irq": 0.00, "soft": 0.00, "steal": 0.00, "guest": 0.00, "gnice": 0.00, "idle": 100.00},
						{"cpu": "7", "usr": 0.00, "nice": 0.00, "sys": 0.00, "iowait": 0.00, "irq": 0.00, "soft": 0.00, "steal": 0.00, "guest": 0.00, "gnice": 0.00, "idle": 100.00},
						{"cpu": "8", "usr": 0.00, "nice": 0.00, "sys": 0.00, "iowait": 0.00, "irq": 0.00, "soft": 0.00, "steal": 0.00, "guest": 0.00, "gnice": 0.00, "idle": 100.00},
						{"cpu": "9", "usr": 0.00, "nice": 0.00, "sys": 0.00, "iowait": 0.00, "irq": 0.00, "soft": 0.00, "steal": 0.00, "guest": 0.00, "gnice": 0.00, "idle": 100.00},
						{"cpu": "10", "usr": 0.00, "nice": 0.00, "sys": 8.97, "iowait": 0.00, "irq": 0.00, "soft": 0.00, "steal": 0.00, "guest": 0.00, "gnice": 0.00, "idle": 91.03},
						{"cpu": "11", "usr": 0.00, "nice": 0.00, "sys": 0.00, "iowait": 0.00, "irq": 0.00, "soft": 0.00, "steal": 0.00, "guest": 0.00, "gnice": 0.00, "idle": 100.00},
						{"cpu": "12", "usr": 0.00, "nice": 0.00, "sys": 0.00, "iowait": 0.00, "irq": 0.00, "soft": 0.00, "steal": 0.00, "guest": 0.00, "gnice": 0.00, "idle": 100.00},
						{"cpu": "13", "usr": 0.00, "nice": 0.00, "sys": 0.00, "iowait": 0.00, "irq": 0.00, "soft": 0.00, "steal": 0.00, "guest": 0.00, "gnice": 0.00, "idle": 100.00},
						{"cpu": "14", "usr": 0.00, "nice": 0.00, "sys": 0.00, "iowait": 0.00, "irq": 0.00, "soft": 0.00, "steal": 0.00, "guest": 0.00, "gnice": 0.00, "idle": 100.00},
						{"cpu": "15", "usr": 0.00, "nice": 0.00, "sys": 0.00, "iowait": 0.00, "irq": 0.00, "soft": 0.00, "steal": 0.00, "guest": 0.00, "gnice": 0.00, "idle": 100.00}
					]
				}
			]
		}
	]
}}
